Workbook

Sheet Nilesh Send Tannage 
B1: Day April-26 | D1: 1 | E1: 2 | F1: 3 | G1: 4 | H1: 5 | I1: 6 | J1: 7 | K1: 8 | L1: 9 | M1: 10 | N1: 11 | O1: 12 | P1: 13 | Q1: 14 | R1: 15 | S1: 16 | T1: 17 | U1: 18 | V1: 19 | W1: 20 | X1: 21 | Y1: 22 | Z1: 23 | AA1: 24 | AB1: 25 | AC1: 26 | AD1: 27 | AE1: 28 | AF1: 29 | AG1: 30 | AH1: Total
B2: FINAL TEAM 1 | D2: 1 | E2: 2 | F2: 3 | G2: 4 | H2: 5 | I2: 6 | J2: 7 | K2: 8 | L2: 9 | M2: 10 | N2: 11 | O2: 12 | P2: 13 | Q2: 14 | R2: 15 | S2: 16 | T2: 17 | U2: 18 | V2: 19 | W2: 20 | X2: 21 | Y2: 22 | Z2: 23 | AA2: 24 | AB2: 25 | AC2: 26 | AD2: 27 | AE2: 28 | AF2: 29 | AG2: 30 | AH2: Total
B3: TOTAL AMOUNT | D3: =D5*D4 -> 0 | E3: =E5*E4 -> 4704.92 | F3: =F5*F4 -> 5196.62 | G3: =G5*G4 -> 5555.22 | H3: =H5*H4 -> 5927.68 | I3: =I5*I4 -> 4180.22 | J3: =J5*J4 -> 5725.28 | K3: =K5*K4 -> 0 | ... AG3: =AG5*AG4 -> 5278.46 | AH3: =SUM(D3:AG3) -> 128661.06
B4: TOTAL MT | E4: 21.386 | F4: 23.621 | G4: 25.251 | H4: 26.944 | I4: 19.001 | J4: 26.024 | L4: 18.952 | M4: 31.11 | N4: 25.191 | O4: 20.545 | P4: 20.893 | Q4: 17.717 | S4: 16.626 | T4: 23.22 | U4: 23.632 | V4: 26.822 | W4: 21.413 | X4: 32.106 | Z4: 21.284 | AA4: 19.088 | AB4: 20.859 | AC4: 19.013 | AD4: 21.611 | AE4: 18.679 | AF4: 19.842 | AG4: 23.993 | AH4: =SUM(D4:AG4) -> 584.823
B5: Rate | D5: 220 | E5: 220 | F5: 220 | G5: 220 | H5: 220 | I5: 220 | J5: 220 | K5: 220 | L5: 220 | M5: 220 | N5: 220 | O5: 220 | P5: 220 | Q5: 220 | R5: 220 | S5: 220 | T5: 220 | U5: 220 | V5: 220 | W5: 220 | X5: 220 | Y5: 220 | Z5: 220 | AA5: 220 | AB5: 220 | AC5: 220 | AD5: 220 | AE5: 220 | AF5: 220 | AG5: 220
B6: No.of Manpawar | E6: 5 | F6: 6 | G6: 6 | H6: 6 | I6: 6 | J6: 6 | L6: 5 | M6: 6 | N6: 6 | O6: 6 | P6: 5 | Q6: 5 | S6: 6 | T6: 6 | U6: 6 | V6: 6 | W6: 6 | X6: 5 | Z6: 5 | AA6: 5 | AB6: 5 | AC6: 5 | AD6: 5 | AE6: 5 | AF6: 5 | AG6: 6 | AH6: =SUM(D6:AG6) -> 144
B7: Paid Amount | D7: =D3/D6 -> #DIV/0! | E7: =E3/E6 -> 940.984 | F7: =F3/F6 -> 866.10333 | G7: =G3/G6 -> 925.87 | H7: =H3/H6 -> 987.94667 | I7: =I3/I6 -> 696.70333 | J7: =J3/J6 -> 954.21333 | K7: =K3/K6 -> #DIV/0! | ... AG7: =AG3/AG6 -> 879.74333 | AH7: =SUM(D7:AG7) -> #DIV/0!
A8: 1 | B8: Mr. ANIL G MALI | C8: 101475240602 | E8: 940 | F8: 1130 | G8: 925 | H8: 987 | I8: 836 | J8: 954 | N8: 923 | P8: 919 | Q8: 779 | S8: 609 | T8: 851 | U8: 888 | V8: 983 | W8: 510 | X8: 1941 | AB8: 917 | AC8: 836 | AD8: 950 | AE8: 889 | AF8: 873 | AG8: 879 | AH8: =SUM(D8:AG8) -> 19519
A9: 2 | B9: Mr. REVANASIDDH SHIVAPPA ISHWARKATTI | C9: 101492178974 | D9: 550 | E9: 940 | F9: 1130 | G9: 925 | H9: 987 | I9: 836 | J9: 954 | K9: 550 | L9: 833 | M9: 1140 | N9: 923 | O9: 903 | P9: 919 | Q9: 779 | R9: 550 | S9: 609 | T9: 851 | U9: 888 | V9: 983 | W9: 1050 | X9: 1941 | Y9: 550 | Z9: 936 | AF9: 873 | AG9: 879 | AH9: =SUM(D9:AG9) -> 22479
A10: 3 | B10: Mr. JITENDRA SIDRAM KOLI | C10: 101603294918 | E10: 940 | F10: 1130 | G10: 925 | H10: 987 | I10: 836 | J10: 954 | L10: 833 | M10: 1140 | N10: 923 | O10: 903 | P10: 919 | S10: 609 | T10: 851 | U10: 888 | V10: 983 | W10: 1050 | X10: 690 | Z10: 936 | AA10: 839 | AB10: 917 | AC10: 836 | AE10: 889 | AF10: 873 | AG10: 879 | AH10: =SUM(D10:AG10) -> 21730
A11: 4 | B11: Mr. VIJAY BHARLE | C11: 101944505682 | F11: 176 | G11: 925 | H11: 987 | J11: 954 | L11: 833 | M11: 1140 | N11: 923 | O11: 903 | Q11: 779 | S11: 609 | T11: 851 | U11: 888 | V11: 983 | W11: 1050 | Z11: 936 | AA11: 839 | AB11: 917 | AC11: 836 | AD11: 950 | AG11: 879 | AH11: =SUM(D11:AG11) -> 17358
A12: 6 | B12: Mr. DIPAK DATTATRAY KUMBHAR | C12: 102052667942 | E12: 940 | G12: 925 | H12: 987 | I12: 836 | J12: 954 | K12: 550 | L12: 833 | M12: 1140 | N12: 923 | O12: 903 | P12: 919 | Q12: 779 | S12: 609 | T12: 851 | U12: 756 | V12: 983 | Z12: 936 | AA12: 839 | AB12: 917 | AC12: 836 | AD12: 950 | AE12: 889 | AG12: 879 | AH12: =SUM(D12:AG12) -> 20134
A13: 7 | B13: Mr. GIRISH SIDDHARAM MADYAL | C13: 101826609019 | E13: 940 | F13: 1130 | G13: 925 | H13: 987 | I13: 836 | J13: 954 | M13: 1140 | N13: 923 | O13: 903 | P13: 919 | Q13: 779 | S13: 609 | T13: 851 | U13: 888 | V13: 983 | W13: 1050 | X13: 1941 | Z13: 936 | AA13: 839 | AB13: 917 | AC13: 836 | AD13: 950 | AE13: 889 | AF13: 873 | AG13: 879 | AH13: =SUM(D13:AG13) -> 23877
B14: Mr. BHIMAHSNKAR SHARNAPPA ISHWARKATTI | C14: 102004077854 | AF14: 873 | AH14: =SUM(D14:AG14) -> 873
B15: Mr.SHVSNAND LANDAGE | L15: 833 | AH15: =SUM(D15:AG15) -> 833
B16: HARUN MULLA | X16: 550 | AH16: =SUM(D16:AG16) -> 550
B17: Fulari | AE17: 550 | AH17: =SUM(D17:AG17) -> 550
A18: 7 | B18: Pundalik Jadhav | M18: 1140 | AA18: 839 | AD18: 950 | AH18: =SUM(D18:AG18) -> 2929
B19: Total | D19: =SUM(D8:D18) -> 550 | E19: =SUM(E8:E18) -> 4700 | F19: =SUM(F8:F18) -> 4696 | G19: =SUM(G8:G18) -> 5550 | H19: =SUM(H8:H18) -> 5922 | I19: =SUM(I8:I18) -> 4180 | J19: =SUM(J8:J18) -> 5724 | K19: =SUM(K8:K18) -> 1100 | ... AH19: =SUM(AH8:AH18) -> 130832
B20: FINAL TEAM 2 | D20: =D19-D3 -> 550 | E20: =E19-E3 -> -4.92 | F20: =F19-F3 -> -500.62 | G20: =G19-G3 -> -5.22 | H20: =H19-H3 -> -5.68 | I20: =I19-I3 -> -0.22 | J20: =J19-J3 -> -1.28 | K20: =K19-K3 -> 1100 | ... AG20: =AG19-AG3 -> -4.46 | AH20: =SUM(D20:AG20) -> 2170.94
B21: TOTAL AMOUNT | D21: =D23*D22 -> 0 | E21: =E23*E22 -> 4045.14 | F21: =F23*F22 -> 3550.8 | G21: =G23*G22 -> 5346.66 | H21: =H23*H22 -> 3077.14 | I21: =I23*I22 -> 6698.34 | J21: =J23*J22 -> 4063.62 | K21: =K23*K22 -> 0 | ... AG21: =AG23*AG22 -> 5463.04 | AH21: =SUM(D21:AG21) -> 120609.94
B22: TOTAL MT | E22: 18.387 | F22: 16.14 | G22: 24.303 | H22: 13.987 | I22: 30.447 | J22: 18.471 | L22: 31.806 | M22: 23.796 | N22: 29.054 | O22: 20.71 | P22: 22.712 | Q22: 19.659 | S22: 22.044 | T22: 20.173 | U22: 24.774 | V22: 16.631 | X22: 30.148 | Z22: 20.175 | AA22: 23.181 | AB22: 22.116 | AC22: 17.191 | AD22: 20.657 | AE22: 22.811 | AF22: 14.022 | AG22: 24.832 | AH22: =SUM(D22:AG22) -> 548.227
B23: Rate | D23: 220 | E23: 220 | F23: 220 | G23: 220 | H23: 220 | I23: 220 | J23: 220 | K23: 220 | L23: 220 | M23: 220 | N23: 220 | O23: 220 | P23: 220 | Q23: 220 | R23: 220 | S23: 220 | T23: 220 | U23: 220 | V23: 220 | W23: 220 | X23: 220 | Y23: 220 | Z23: 220 | AA23: 220 | AB23: 220 | AC23: 220 | AD23: 220 | AE23: 220 | AF23: 220 | AG23: 220
B24: No.of Manpawar | E24: 5 | F24: 6 | G24: 6 | H24: 6 | I24: 5 | J24: 4 | L24: 6 | M24: 5 | N24: 6 | O24: 6 | P24: 6 | Q24: 6 | S24: 6 | T24: 6 | U24: 6 | V24: 5 | X24: 5 | Z24: 6 | AA24: 5 | AB24: 5 | AC24: 5 | AD24: 5 | AE24: 5 | AF24: 5 | AG24: 5 | AH24: =SUM(D24:AG24) -> 136
B25: Paid Amount | D25: =D21/D24 -> #DIV/0! | E25: =E21/E24 -> 809.028 | F25: =F21/F24 -> 591.8 | G25: =G21/G24 -> 891.11 | H25: =H21/H24 -> 512.85667 | I25: =I21/I24 -> 1339.668 | J25: =J21/J24 -> 1015.905 | K25: =K21/K24 -> #DIV/0! | ... AG25: =AG21/AG24 -> 1092.608 | AH25: =SUM(D25:AG25) -> #DIV/0!
A26: 1 | B26: Ambare D.K | F26: 591 | G26: 891 | H26: 280 | L26: 982 | N26: 1065 | O26: 865 | P26: 686 | Q26: 610 | S26: 551 | T26: 740 | U26: 908 | V26: 732 | W26: 550 | X26: 1326 | Z26: 739 | AB26: 973 | AH26: =SUM(D26:AG26) -> 12489
A27: 2 | B27: Mr. KASHINATH JAGANATH BIRJADAR | C27: 101818174092 | E27: 809 | F27: 591 | G27: 891 | H27: 559 | I27: 1339 | J27: 1015 | L27: 1202 | M27: 1047 | N27: 1065 | O27: 865 | P27: 862 | Q27: 742 | S27: 859 | T27: 740 | U27: 908 | W27: 550 | X27: 1326 | Z27: 739 | AA27: 1019 | AC27: 756 | AD27: 908 | AE27: 1003 | AF27: 616 | AG27: 1004 | AH27: =SUM(D27:AG27) -> 21415
A28: 3 | B28: Mr. BHIMAHSNKAR SHARNAPPA ISHWARKATTI | C28: 102004077854 | E28: 809 | F28: 591 | G28: 891 | H28: 559 | I28: 1339 | J28: 1015 | L28: 1202 | M28: 1047 | N28: 1065 | O28: 865 | P28: 862 | Q28: 742 | S28: 859 | T28: 740 | U28: 908 | V28: 732 | W28: 550 | X28: 1326 | Z28: 739 | AA28: 1019 | AB28: 973 | AC28: 756 | AD28: 908 | AE28: 1003 | AF28: 616 | AG28: 1114 | AH28: =SUM(D28:AG28) -> 23230
A29: 4 | B29: Mr. SHIVANAND KANTAPPA KOSHTI | C29: 101817173110 | E29: 809 | F29: 591 | G29: 891 | H29: 559 | I29: 1339 | L29: 1202 | M29: 1047 | N29: 1065 | O29: 230 | P29: 862 | Q29: 742 | S29: 859 | T29: 740 | U29: 908 | V29: 732 | X29: 1326 | Z29: 739 | AA29: 1019 | AB29: 973 | AC29: 756 | AD29: 908 | AE29: 1003 | AF29: 616 | AG29: 1114 | AH29: =SUM(D29:AG29) -> 21030
A30: 5 | B30: Mr. KHAJASAHEB GULAB HIMONE | C30: 102120964651 | E30: 809 | F30: 591 | G30: 891 | H30: 559 | I30: 1339 | J30: 1015 | L30: 1202 | M30: 1047 | N30: 1065 | O30: 865 | P30: 862 | Q30: 742 | S30: 859 | T30: 740 | U30: 908 | V30: 732 | W30: 550 | X30: 1326 | Z30: 739 | AA30: 1019 | AB30: 973 | AC30: 756 | AD30: 908 | AE30: 1003 | AF30: 616 | AG30: 1114 | AH30: =SUM(D30:AG30) -> 23230
A31: 6 | B31: Mr. VISHAL SURESH MANE | C31: 101432431093 | E31: 809 | F31: 591 | G31: 891 | H31: 559 | I31: 1339 | J31: 1015 | L31: 1202 | M31: 1047 | N31: 1065 | O31: 865 | P31: 862 | Q31: 742 | S31: 859 | T31: 740 | U31: 908 | V31: 732 | Z31: 739 | AA31: 1019 | AB31: 973 | AC31: 756 | AD31: 908 | AE31: 1003 | AF31: 616 | AG31: 1114 | AH31: =SUM(D31:AG31) -> 21354
B32: Total | D32: =SUM(D26:D31) -> 0 | E32: =SUM(E26:E31) -> 4045 | F32: =SUM(F26:F31) -> 3546 | G32: =SUM(G26:G31) -> 5346 | H32: =SUM(H26:H31) -> 3075 | I32: =SUM(I26:I31) -> 6695 | J32: =SUM(J26:J31) -> 4060 | K32: =SUM(K26:K31) -> 0 | ... AH32: =SUM(AH26:AH31) -> 122748
B33: HAND EMARY 1 (GroupA) | D33: =D32-D21 -> 0 | E33: =E32-E21 -> -0.14 | F33: =F32-F21 -> -4.8 | G33: =G32-G21 -> -0.66 | H33: =H32-H21 -> -2.14 | I33: =I32-I21 -> -3.34 | J33: =J32-J21 -> -3.62 | K33: =K32-K21 -> 0 | ... AG33: =AG32-AG21 -> -3.04 | AH33: =SUM(D33:AG33) -> 2138.06
B34: TOTAL AMOUNT | D34: =D35*D36 -> 0 | E34: =E35*E36 -> 6940.8 | F34: =F35*F36 -> 8104.96 | G34: =G35*G36 -> 7467.008 | H34: =H35*H36 -> 8408.32 | I34: =I35*I36 -> 6601.92 | J34: =J35*J36 -> 5987.2 | K34: =K35*K36 -> 0 | ... AG34: =AG35*AG36 -> 6517.76 | AH34: =SUM(D34:AG34) -> 168183.49
B35: TOTAL MT | E35: 21.69 | F35: 25.328 | G35: 23.3344 | H35: 26.276 | I35: 20.631 | J35: 18.71 | L35: 20.54 | M35: 24.714 | N35: 17.58 | O35: 19.414 | P35: 14.583 | Q35: 14.877 | R35: 17.008 | S35: 13.17 | T35: 16.932 | U35: 19.653 | V35: 17.759 | W35: 21.011 | X35: 21.7 | Y35: 11.374 | Z35: 12.294 | AA35: 14.706 | AB35: 16.89 | AC35: 20.04 | AD35: 20.792 | AE35: 17.54 | AF35: 16.659 | AG35: 20.368 | AH35: =SUM(D35:AG35) -> 525.5734
B36: Rate | D36: 320 | E36: 320 | F36: 320 | G36: 320 | H36: 320 | I36: 320 | J36: 320 | K36: 320 | L36: 320 | M36: 320 | N36: 320 | O36: 320 | P36: 320 | Q36: 320 | R36: 320 | S36: 320 | T36: 320 | U36: 320 | V36: 320 | W36: 320 | X36: 320 | Y36: 320 | Z36: 320 | AA36: 320 | AB36: 320 | AC36: 320 | AD36: 320 | AE36: 320 | AF36: 320 | AG36: 320
B37: No.of Manpawar | E37: 7 | F37: 7 | G37: 7 | H37: 8 | I37: 7 | J37: 7 | L37: 7 | M37: 7 | N37: 6 | O37: 6 | P37: 7 | Q37: 7 | R37: 7 | S37: 5 | T37: 7 | U37: 7 | V37: 6 | W37: 8 | X37: 8 | Y37: 6 | Z37: 6 | AA37: 7 | AB37: 7 | AC37: 8 | AD37: 8 | AE37: 7 | AF37: 7 | AG37: 8 | AH37: =SUM(D37:AG37) -> 195
B38: Paid Amount | D38: =D34/D37 -> #DIV/0! | E38: =E34/E37 -> 991.54286 | F38: =F34/F37 -> 1157.8514 | G38: =G34/G37 -> 1066.7154 | H38: =H34/H37 -> 1051.04 | I38: =I34/I37 -> 943.13143 | J38: =J34/J37 -> 855.31429 | K38: =K34/K37 -> #DIV/0! | ... AG38: =AG34/AG37 -> 814.72 | AH38: =SUM(D38:AG38) -> #DIV/0!
A39: 1 | B39: Mr. NAMDEV DURGAPPA BANDGAR | C39: 101407413648 | H39: 1131 | I39: 1008 | J39: 906 | L39: 1003 | M39: 1226 | N39: 1025 | O39: 1132 | P39: 686 | Q39: 701 | R39: 815 | T39: 811 | U39: 956 | V39: 1026 | W39: 900 | X39: 1065 | Y39: 617 | Z39: 708 | AA39: 721 | AB39: 809 | AC39: 837 | AG39: 902 | AH39: =SUM(D39:AG39) -> 18985
A40: 2 | B40: Mr. KHALID ILAI SHAIKH | C40: 101373078654 | E40: 1108 | F40: 1259 | G40: 1265 | H40: 1131 | I40: 1008 | J40: 906 | L40: 1003 | M40: 1226 | N40: 1025 | O40: 1132 | P40: 686 | Q40: 701 | S40: 1038 | T40: 811 | U40: 956 | W40: 900 | X40: 1065 | Z40: 708 | AA40: 721 | AB40: 809 | AC40: 837 | AG40: 902 | AH40: =SUM(D40:AG40) -> 21197
A41: 3 | B41: Mr. WAGHMODE DATTATRAY ASHOK | C41: 101391642731 | E41: 1108 | F41: 1259 | G41: 1265 | H41: 1131 | I41: 1008 | J41: 906 | L41: 1003 | M41: 1226 | N41: 1025 | O41: 1132 | P41: 686 | Q41: 701 | T41: 811 | U41: 956 | V41: 1026 | W41: 900 | X41: 659 | Y41: 617 | AA41: 721 | AB41: 809 | AC41: 837 | AD41: 925 | AE41: 902 | AF41: 705 | AG41: 902 | AH41: =SUM(D41:AG41) -> 23220
A42: 7 | B42: Mr. SATISH SHIVAJI SHINDE | C42: 101475170616 | E42: 1108 | F42: 1259 | G42: 1265 | H42: 1131 | I42: 1008 | J42: 906 | L42: 1003 | M42: 1226 | N42: 1025 | O42: 1132 | P42: 686 | Q42: 701 | S42: 1038 | T42: 811 | U42: 956 | V42: 1026 | W42: 900 | X42: 1065 | Z42: 708 | AB42: 809 | AC42: 837 | AD42: 925 | AE42: 902 | AF42: 705 | AG42: 902 | AH42: =SUM(D42:AG42) -> 24034
A43: 8 | B43: Mr. KASHINATH ABHIMANU PATIL | C43: 101520450548 | E43: 1108 | F43: 1259 | G43: 1265 | H43: 1131 | I43: 1008 | J43: 906 | L43: 1003 | M43: 1226 | N43: 1025 | O43: 1132 | P43: 686 | Q43: 701 | R43: 815 | T43: 811 | U43: 956 | V43: 1026 | W43: 900 | X43: 1065 | Y43: 617 | Z43: 708 | AA43: 721 | AB43: 809 | AC43: 837 | AD43: 925 | AE43: 902 | AF43: 705 | AG43: 902 | AH43: =SUM(D43:AG43) -> 25149
A44: 10 | B44: SAGAR GHARSANGE | E44: 850 | F44: 1259 | G44: 592 | H44: 1131 | W44: 770 | AB44: 809 | AC44: 837 | AD44: 925 | AE44: 902 | AF44: 705 | AG44: 902 | AH44: =SUM(D44:AG44) -> 9682
A45: 13 | B45: RAJKUMAR ANDONDI | F45: 1259 | AH45: =SUM(D45:AG45) -> 1259
B46: AJAY PENTA | E46: 550 | F46: 550 | H46: 550 | I46: 550 | J46: 550 | Q46: 550 | S46: 550 | T46: 550 | U46: 550 | V46: 550 | W46: 550 | X46: 550 | Z46: 550 | AA46: 550 | AB46: 550 | AC46: 550 | AD46: 550 | AE46: 550 | AF46: 550 | AG46: 550 | AH46: =SUM(D46:AG46) -> 11000
A47: 11 | B47: Dhanajay shinde | G47: 550 | AH47: =SUM(D47:AG47) -> 550
B48: HARUN MULLA | L48: 550 | M48: 550 | O48: 550 | P48: 550 | R48: 550 | S48: 550 | Y48: 550 | Z48: 550 | AA48: 550 | AD48: 550 | AE48: 550 | AF48: 550 | AG48: 550 | AH48: =SUM(D48:AG48) -> 7150
B49: Arajun Bandagar | N49: 500 | AH49: =SUM(D49:AG49) -> 500
B50: Pundalik Jadhav | P50: 686 | AH50: =SUM(D50:AG50) -> 686
B51: ANKUSH BHALE | Q51: 701 | AD51: 925 | AH51: =SUM(D51:AG51) -> 1626
B52: MANGESH ANKUSHROV | S52: 1038 | T52: 811 | U52: 956 | V52: 1026 | W52: 900 | X52: 1065 | AH52: =SUM(D52:AG52) -> 5796
B53: ANIL RAVAT | R53: 815 | X53: 406 | Y53: 617 | AH53: =SUM(D53:AG53) -> 1838
B54: DINESH SALARGAR | R54: 815 | Y54: 617 | AA54: 721 | AH54: =SUM(D54:AG54) -> 2153
B55: ABHIJIT WAGHMARE | R55: 815 | AF55: 705 | AH55: =SUM(D55:AG55) -> 1520
B56: ROHAN PANDIT | R56: 815 | AH56: =SUM(D56:AG56) -> 815
A57: 4 | B57: Mr. AKASH JAGNNATH TENGALE | C57: 101747190938 | E57: 1108 | G57: 1265 | H57: 1131 | I57: 1008 | J57: 906 | L57: 1003 | M57: 1226 | AC57: 837 | AD57: 925 | AE57: 902 | AF57: 705 | AH57: =SUM(D57:AG57) -> 11016
B58: Total | D58: =SUM(D39:D57) -> 0 | E58: =SUM(E39:E57) -> 6940 | F58: =SUM(F39:F57) -> 8104 | G58: =SUM(G39:G57) -> 7467 | H58: =SUM(H39:H57) -> 8467 | I58: =SUM(I39:I57) -> 6598 | J58: =SUM(J39:J57) -> 5986 | K58: =SUM(K39:K57) -> 0 | ... AG58: =SUM(AG39:AG57) -> 6512 | AH58: =SUM(AH39:AH45) -> 123526
B59: HAND EMARY 2 | D59: =D58-D34 -> 0 | E59: =E58-E34 -> -0.8 | F59: =F58-F34 -> -0.96 | G59: =G58-G34 -> -0.008 | H59: =H58-H34 -> 58.68 | I59: =I58-I34 -> -3.92 | J59: =J58-J34 -> -1.2 | K59: =K58-K34 -> 0 | ... AG59: =AG58-AG34 -> -5.76 | AH59: =SUM(D59:AG59) -> -7.488
B60: TOTAL AMO | D60: =D62*D61 -> 0 | E60: =E62*E61 -> 3753.6 | F60: =F62*F61 -> 7260.8 | G60: =G62*G61 -> 6987.52 | H60: =H62*H61 -> 5436.16 | I60: =I62*I61 -> 8242.56 | J60: =J62*J61 -> 6662.4 | K60: =K62*K61 -> 0 | ... AG60: =AG62*AG61 -> 7408 | AH60: =SUM(D60:AG60) -> 163895.68
B61: TOTAL MT | E61: 11.73 | F61: 22.69 | G61: 21.836 | H61: 16.988 | I61: 25.758 | J61: 20.82 | L61: 17.286 | M61: 20.715 | N61: 23.048 | O61: 21.206 | P61: 18.335 | Q61: 20.868 | S61: 16.893 | T61: 16.635 | U61: 22.291 | V61: 20.022 | W61: 25.075 | X61: 17.566 | Z61: 13.86 | AA61: 19.553 | AB61: 17.82 | AC61: 18.929 | AD61: 20.35 | AE61: 20 | AF61: 18.75 | AG61: 23.15 | AH61: =SUM(D61:AG61) -> 512.174
B62: Rate | D62: 320 | E62: 320 | F62: 320 | G62: 320 | H62: 320 | I62: 320 | J62: 320 | K62: 320 | L62: 320 | M62: 320 | N62: 320 | O62: 320 | P62: 320 | Q62: 320 | R62: 320 | S62: 320 | T62: 320 | U62: 320 | V62: 320 | W62: 320 | X62: 320 | Y62: 320 | Z62: 320 | AA62: 320 | AB62: 320 | AC62: 320 | AD62: 320 | AE62: 320 | AF62: 320 | AG62: 320
B63: No.of Manpawar | E63: 5 | F63: 8 | G63: 8 | H63: 7 | I63: 8 | J63: 7 | L63: 7 | M63: 7 | N63: 8 | O63: 7 | P63: 8 | Q63: 8 | S63: 6 | T63: 8 | U63: 7 | V63: 8 | W63: 8 | X63: 7 | Z63: 7 | AA63: 9 | AB63: 8 | AC63: 7 | AD63: 8 | AE63: 7 | AF63: 7 | AG63: 8 | AH63: =SUM(D63:AG63) -> 193
B64: Paid Amount | D64: =D60/D63 -> #DIV/0! | E64: =E60/E63 -> 750.72 | F64: =F60/F63 -> 907.6 | G64: =G60/G63 -> 873.44 | H64: =H60/H63 -> 776.59429 | I64: =I60/I63 -> 1030.32 | J64: =J60/J63 -> 951.77143 | K64: =K60/K63 -> #DIV/0! | ... AG64: =AG60/AG63 -> 926 | AH64: =SUM(D64:AG64) -> #DIV/0!
A65: 1 | B65: Mr. AMOL TEJU RATHOD | C65: 101509952020 | E65: 750 | F65: 956 | G65: 873 | H65: 856 | I65: 1030 | L65: 830 | M65: 946 | N65: 921 | O65: 909 | P65: 858 | Q65: 834 | S65: 900 | T65: 677 | U65: 1019 | V65: 800 | W65: 1003 | Z65: 659 | AA65: 842 | AB65: 731 | AC65: 772 | AE65: 957 | AF65: 857 | AG65: 953 | AH65: =SUM(D65:AG65) -> 19933
A66: 2 | B66: ANKUSH BHALE | C66: 101835374035 | E66: 750 | F66: 956 | G66: 873 | H66: 343 | I66: 1030 | L66: 830 | M66: 946 | N66: 921 | O66: 418 | T66: 582 | AC66: 772 | AE66: 957 | AF66: 857 | AG66: 953 | AH66: =SUM(D66:AG66) -> 11188
A67: 4 | B67: Mr. MALLINATH SHIVARAM VHANAKADE | C67: 101522138160 | I67: 1030 | J67: 951 | L67: 830 | M67: 946 | N67: 921 | O67: 909 | P67: 858 | Q67: 834 | S67: 900 | T67: 677 | U67: 1019 | V67: 800 | W67: 1003 | X67: 803 | Z67: 659 | AA67: 842 | AF67: 857 | AG67: 953 | AH67: =SUM(D67:AG67) -> 15792
A68: 5 | B68: Mr. DINESH VASANT SALGAR | C68: 102053057886 | E68: 750 | F68: 956 | G68: 873 | H68: 856 | I68: 1030 | J68: 951 | L68: 830 | M68: 946 | N68: 921 | O68: 909 | P68: 714 | Q68: 834 | S68: 900 | T68: 677 | U68: 1019 | V68: 800 | W68: 1003 | X68: 803 | Z68: 659 | AB68: 731 | AC68: 772 | AD68: 901 | AE68: 957 | AG68: 953 | AH68: =SUM(D68:AG68) -> 20745
A69: 6 | B69: Rohan Pandit | F69: 956 | G69: 873 | H69: 856 | I69: 1030 | J69: 951 | L69: 550 | N69: 921 | O69: 909 | P69: 858 | Q69: 834 | S69: 900 | T69: 677 | U69: 1019 | V69: 800 | W69: 1003 | X69: 803 | AA69: 413 | AB69: 731 | AC69: 772 | AG69: 732 | AH69: =SUM(D69:AG69) -> 16588
A70: 8 | B70: YUVARAJ HIRKURE | J70: 951 | S70: 900 | U70: 1019 | V70: 800 | W70: 1003 | X70: 803 | Z70: 659 | AA70: 652 | AB70: 731 | AC70: 772 | AD70: 901 | AE70: 957 | AF70: 857 | AG70: 953 | AH70: =SUM(D70:AG70) -> 11958
A71: 9 | B71: Mr. ABHISHEK SUNIL RATHOD | C71: 102078951370 | F71: 956 | G71: 873 | H71: 856 | I71: 1030 | N71: 921 | O71: 909 | P71: 858 | Q71: 834 | V71: 800 | W71: 1003 | Z71: 659 | AA71: 842 | AB71: 731 | AD71: 494 | AH71: =SUM(D71:AG71) -> 11766
A72: 10 | B72: Mr. RAJAKUMAR BADIGER | C72: 102143026061 | M72: 946 | O72: 909 | Q72: 834 | S72: 900 | T72: 677 | U72: 1019 | V72: 800 | W72: 1003 | X72: 803 | Z72: 480 | AA72: 426 | AB72: 583 | AD72: 901 | AF72: 857 | AG72: 953 | AH72: =SUM(D72:AG72) -> 12091
B73: RAJKUMAR ANDONDI | E73: 750 | G73: 873 | I73: 1030 | J73: 951 | L73: 830 | M73: 946 | N73: 921 | O73: 990 | P73: 858 | Q73: 834 | T73: 677 | X73: 803 | Z73: 659 | AA73: 842 | AB73: 731 | AC73: 772 | AD73: 901 | AE73: 957 | AF73: 857 | AG73: 953 | AH73: =SUM(D73:AG73) -> 17135
B74: ANIL RAVAT | F74: 956 | G74: 873 | H74: 856 | L74: 830 | M74: 946 | N74: 921 | P74: 858 | Q74: 834 | T74: 677 | U74: 1019 | V74: 800 | W74: 1003 | X74: 803 | AA74: 842 | AB74: 731 | AC74: 650 | AD74: 901 | AE74: 806 | AH74: =SUM(D74:AG74) -> 15306
B75: MANGESH ANKUSHROV | F75: 956 | G75: 873 | H75: 811 | I75: 1030 | J75: 951 | AH75: =SUM(D75:AG75) -> 4621
B76: Mr. SATISH SHIVAJI SHINDE | C76: 101475170616 | AA76: 553 | AH76: =SUM(D76:AG76) -> 553
B77: Mr. NAMDEV DURGAPPA BANDGAR | C77: 101407413648 | AC77: 772 | AD77: 783 | AH77: =SUM(D77:AG77) -> 1555
B78: Mr. KHALID ILAI SHAIKH | C78: 101373078654 | AD78: 713 | AE78: 806 | AF78: 857 | AH78: =SUM(D78:AG78) -> 2376
B79: Pundalik Jadhav | E79: 750 | J79: 951 | AH79: =SUM(D79:AG79) -> 1701
B80: Mr. AKASH JAGNNATH TENGALE | C80: 101747190938 | F80: 565 | AH80: =SUM(D80:AG80) -> 565
B81: Total | D81: =SUM(D65:D80) -> 0 | E81: =SUM(E65:E80) -> 3750 | F81: =SUM(F65:F80) -> 7257 | G81: =SUM(G65:G80) -> 6984 | H81: =SUM(H65:H80) -> 5434 | I81: =SUM(I65:I80) -> 8240 | J81: =SUM(J65:J80) -> 6657 | K81: =SUM(K65:K80) -> 0 | ... AH81: =SUM(AH65:AH80) -> 163873
D82: =D81-D60 -> 0 | E82: =E81-E60 -> -3.6 | F82: =F81-F60 -> -3.8 | G82: =G81-G60 -> -3.52 | H82: =H81-H60 -> -2.16 | I82: =I81-I60 -> -2.56 | J82: =J81-J60 -> -5.4 | K82: =K81-K60 -> 0 | ... AG82: =AG81-AG60 -> -5 | AH82: =SUM(D82:AE82) -> -16.68
B83: Final amount | D83: =D19+D32 -> 550 | E83: =E19+E32 -> 8745 | F83: =F19+F32 -> 8242 | G83: =G19+G32 -> 10896 | H83: =H19+H32 -> 8997 | I83: =I19+I32 -> 10875 | J83: =J19+J32 -> 9784 | K83: =K19+K32 -> 1100 | ... AH83: =AH19+AH32 -> 253580
B84: Final MT | D84: =D4+D22 -> 0 | E84: =E4+E22 -> 39.773 | F84: =F4+F22 -> 39.761 | G84: =G4+G22 -> 49.554 | H84: =H4+H22 -> 40.931 | I84: =I4+I22 -> 49.448 | J84: =J4+J22 -> 44.495 | K84: =K4+K22 -> 0 | ... AH84: =AH4+AH22 -> 1133.05
B85: HE amount | D85: =D81+D58 -> 0 | E85: =E81+E58 -> 10690 | F85: =F81+F58 -> 15361 | G85: =G81+G58 -> 14451 | H85: =H81+H58 -> 13901 | I85: =I81+I58 -> 14838 | J85: =J81+J58 -> 12643 | K85: =K81+K58 -> 0 | ... AH85: =AH81+AH58 -> 287399
B86: HE MT | D86: =D61+D35 -> 0 | E86: =E61+E35 -> 33.42 | F86: =F61+F35 -> 48.018 | G86: =G61+G35 -> 45.1704 | H86: =H61+H35 -> 43.264 | I86: =I61+I35 -> 46.389 | J86: =J61+J35 -> 39.53 | K86: =K61+K35 -> 0 | ... AH86: =AH61+AH35 -> 1037.7474

Sheet nilesh sir tannage
B1: Day April-26 | D1: 1 | E1: 2 | F1: 3 | G1: 4 | H1: 5 | I1: 6 | J1: 7 | K1: 8 | L1: 9 | M1: 10 | N1: 11 | O1: 12 | P1: 13 | Q1: 14 | R1: 15 | S1: 16 | T1: 17 | U1: 18 | V1: 19 | W1: 20 | X1: 21 | Y1: 22 | Z1: 23 | AA1: 24 | AB1: 25 | AC1: 26 | AD1: 27 | AE1: 28 | AF1: 29 | AG1: 30 | AH1: Total
B2: FINAL TEAM 1 | D2: 1 | E2: 2 | F2: 3 | G2: 4 | H2: 5 | I2: 6 | J2: 7 | K2: 8 | L2: 9 | M2: 10 | N2: 11 | O2: 12 | P2: 13 | Q2: 14 | R2: 15 | S2: 16 | T2: 17 | U2: 18 | V2: 19 | W2: 20 | X2: 21 | Y2: 22 | Z2: 23 | AA2: 24 | AB2: 25 | AC2: 26 | AD2: 27 | AE2: 28 | AF2: 29 | AG2: 30 | AH2: Total
B3: TOTAL AMOUNT | D3: =D5*D4 -> 0 | E3: =E5*E4 -> 4704.92 | F3: =F5*F4 -> 5196.62 | G3: =G5*G4 -> 5555.22 | H3: =H5*H4 -> 5927.68 | I3: =I5*I4 -> 4180.22 | J3: =J5*J4 -> 5725.28 | K3: =K5*K4 -> 0 | ... AG3: =AG5*AG4 -> 5278.46 | AH3: =SUM(D3:AG3) -> 128661.06
B4: TOTAL MT | E4: 21.386 | F4: 23.621 | G4: 25.251 | H4: 26.944 | I4: 19.001 | J4: 26.024 | L4: 18.952 | M4: 31.11 | N4: 25.191 | O4: 20.545 | P4: 20.893 | Q4: 17.717 | S4: 16.626 | T4: 23.22 | U4: 23.632 | V4: 26.822 | W4: 21.413 | X4: 32.106 | Z4: 21.284 | AA4: 19.088 | AB4: 20.859 | AC4: 19.013 | AD4: 21.611 | AE4: 18.679 | AF4: 19.842 | AG4: 23.993 | AH4: =SUM(D4:AG4) -> 584.823
B5: Rate | D5: 220 | E5: 220 | F5: 220 | G5: 220 | H5: 220 | I5: 220 | J5: 220 | K5: 220 | L5: 220 | M5: 220 | N5: 220 | O5: 220 | P5: 220 | Q5: 220 | R5: 220 | S5: 220 | T5: 220 | U5: 220 | V5: 220 | W5: 220 | X5: 220 | Y5: 220 | Z5: 220 | AA5: 220 | AB5: 220 | AC5: 220 | AD5: 220 | AE5: 220 | AF5: 220 | AG5: 220
B6: No.of Manpawar | E6: 5 | F6: 6 | G6: 6 | H6: 6 | I6: 6 | J6: 6 | L6: 5 | M6: 6 | N6: 6 | O6: 6 | P6: 5 | Q6: 5 | S6: 6 | T6: 6 | U6: 6 | V6: 6 | W6: 6 | X6: 5 | Z6: 5 | AA6: 5 | AB6: 5 | AC6: 5 | AD6: 5 | AE6: 5 | AF6: 5 | AG6: 6 | AH6: =SUM(D6:AG6) -> 144
B7: Paid Amount | D7: =D3/D6 -> #DIV/0! | E7: =E3/E6 -> 940.984 | F7: =F3/F6 -> 866.10333 | G7: =G3/G6 -> 925.87 | H7: =H3/H6 -> 987.94667 | I7: =I3/I6 -> 696.70333 | J7: =J3/J6 -> 954.21333 | K7: =K3/K6 -> #DIV/0! | ... AG7: =AG3/AG6 -> 879.74333 | AH7: =SUM(D7:AG7) -> #DIV/0!
A8: 1 | B8: Mr. ANIL G MALI | C8: 101475240602 | E8: 940 | F8: 1130 | G8: 925 | H8: 987 | I8: 836 | J8: 954 | N8: 923 | P8: 919 | Q8: 779 | S8: 609 | T8: 851 | U8: 888 | V8: 983 | W8: 510 | X8: 1941 | AB8: 917 | AC8: 836 | AD8: 950 | AE8: 889 | AF8: 873 | AG8: 879 | AH8: =SUM(D8:AG8) -> 19519 | AI8: =COUNT(D8:AG8) -> 21
A9: 2 | B9: Mr. REVANASIDDH SHIVAPPA ISHWARKATTI | C9: 101492178974 | D9: 550 | E9: 940 | F9: 1130 | G9: 925 | H9: 987 | I9: 836 | J9: 954 | K9: 550 | L9: 833 | M9: 1140 | N9: 923 | O9: 903 | P9: 919 | Q9: 779 | R9: 550 | S9: 609 | T9: 851 | U9: 888 | V9: 983 | W9: 1050 | X9: 1941 | Y9: 550 | Z9: 936 | AF9: 873 | AG9: 879 | AH9: =SUM(D9:AG9) -> 22479 | AI9: =COUNT(D9:AG9) -> 25
A10: 3 | B10: Mr. JITENDRA SIDRAM KOLI | C10: 101603294918 | E10: 940 | F10: 1130 | G10: 925 | H10: 987 | I10: 836 | J10: 954 | L10: 833 | M10: 1140 | N10: 923 | O10: 903 | P10: 919 | S10: 609 | T10: 851 | U10: 888 | V10: 983 | W10: 1050 | X10: 690 | Z10: 936 | AA10: 839 | AB10: 917 | AC10: 836 | AE10: 889 | AF10: 873 | AG10: 879 | AH10: =SUM(D10:AG10) -> 21730 | AI10: =COUNT(D10:AG10) -> 24
A11: 4 | B11: Mr. VIJAY BHARLE | C11: 101944505682 | F11: 176 | G11: 925 | H11: 987 | J11: 954 | L11: 833 | M11: 1140 | N11: 923 | O11: 903 | Q11: 779 | S11: 609 | T11: 851 | U11: 888 | V11: 983 | W11: 1050 | Z11: 936 | AA11: 839 | AB11: 917 | AC11: 836 | AD11: 950 | AG11: 879 | AH11: =SUM(D11:AG11) -> 17358 | AI11: =COUNT(D11:AG11) -> 20
A12: 5 | B12: Mr. DIPAK DATTATRAY KUMBHAR | C12: 102052667942 | E12: 940 | G12: 925 | H12: 987 | I12: 836 | J12: 954 | K12: 550 | L12: 833 | M12: 1140 | N12: 923 | O12: 903 | P12: 919 | Q12: 779 | S12: 609 | T12: 851 | U12: 756 | V12: 983 | Z12: 936 | AA12: 839 | AB12: 917 | AC12: 836 | AD12: 950 | AE12: 889 | AG12: 879 | AH12: =SUM(D12:AG12) -> 20134 | AI12: =COUNT(D12:AG12) -> 23
A13: 6 | B13: Mr. GIRISH SIDDHARAM MADYAL | C13: 101826609019 | E13: 940 | F13: 1130 | G13: 925 | H13: 987 | I13: 836 | J13: 954 | M13: 1140 | N13: 923 | O13: 903 | P13: 919 | Q13: 779 | S13: 609 | T13: 851 | U13: 888 | V13: 983 | W13: 1050 | X13: 1941 | Z13: 936 | AA13: 839 | AB13: 917 | AC13: 836 | AD13: 950 | AE13: 889 | AF13: 873 | AG13: 879 | AH13: =SUM(D13:AG13) -> 23877 | AI13: =COUNT(D13:AG13) -> 25
A14: 7 | B14: Mr.SHVSNAND LANDAGE | L14: 833 | AH14: =SUM(D14:AG14) -> 833 | AI14: =COUNT(D14:AG14) -> 1
A15: 8 | B15: Fulari | AE15: 550 | AH15: =SUM(D15:AG15) -> 550 | AI15: =COUNT(D15:AG15) -> 1
B16: Total | D16: =SUM(D8:D15) -> 550 | E16: =SUM(E8:E15) -> 4700 | F16: =SUM(F8:F15) -> 4696 | G16: =SUM(G8:G15) -> 5550 | H16: =SUM(H8:H15) -> 5922 | I16: =SUM(I8:I15) -> 4180 | J16: =SUM(J8:J15) -> 5724 | K16: =SUM(K8:K15) -> 1100 | ... AH16: =SUM(AH8:AH15) -> 126480 | AI16: =COUNT(D16:AG16) -> 30
B17: FINAL TEAM 2 | D17: =D16-D3 -> 550 | E17: =E16-E3 -> -4.92 | F17: =F16-F3 -> -500.62 | G17: =G16-G3 -> -5.22 | H17: =H16-H3 -> -5.68 | I17: =I16-I3 -> -0.22 | J17: =J16-J3 -> -1.28 | K17: =K16-K3 -> 1100 | ... AG17: =AG16-AG3 -> -4.46 | AH17: =SUM(D17:AG17) -> -2181.06 | AI17: =COUNT(D17:AG17) -> 30
B18: TOTAL AMOUNT | D18: =D20*D19 -> 0 | E18: =E20*E19 -> 4045.14 | F18: =F20*F19 -> 3550.8 | G18: =G20*G19 -> 5346.66 | H18: =H20*H19 -> 3077.14 | I18: =I20*I19 -> 6698.34 | J18: =J20*J19 -> 4063.62 | K18: =K20*K19 -> 0 | ... AG18: =AG20*AG19 -> 5463.04 | AH18: =SUM(D18:AG18) -> 120609.94 | AI18: =COUNT(D18:AG18) -> 30
B19: TOTAL MT | E19: 18.387 | F19: 16.14 | G19: 24.303 | H19: 13.987 | I19: 30.447 | J19: 18.471 | L19: 31.806 | M19: 23.796 | N19: 29.054 | O19: 20.71 | P19: 22.712 | Q19: 19.659 | S19: 22.044 | T19: 20.173 | U19: 24.774 | V19: 16.631 | X19: 30.148 | Z19: 20.175 | AA19: 23.181 | AB19: 22.116 | AC19: 17.191 | AD19: 20.657 | AE19: 22.811 | AF19: 14.022 | AG19: 24.832 | AH19: =SUM(D19:AG19) -> 548.227 | AI19: =COUNT(D19:AG19) -> 25
B20: Rate | D20: 220 | E20: 220 | F20: 220 | G20: 220 | H20: 220 | I20: 220 | J20: 220 | K20: 220 | L20: 220 | M20: 220 | N20: 220 | O20: 220 | P20: 220 | Q20: 220 | R20: 220 | S20: 220 | T20: 220 | U20: 220 | V20: 220 | W20: 220 | X20: 220 | Y20: 220 | Z20: 220 | AA20: 220 | AB20: 220 | AC20: 220 | AD20: 220 | AE20: 220 | AF20: 220 | AG20: 220 | AI20: =COUNT(D20:AG20) -> 30
B21: No.of Manpawar | E21: 5 | F21: 6 | G21: 6 | H21: 6 | I21: 5 | J21: 4 | L21: 6 | M21: 5 | N21: 6 | O21: 6 | P21: 6 | Q21: 6 | S21: 6 | T21: 6 | U21: 6 | V21: 5 | X21: 5 | Z21: 6 | AA21: 5 | AB21: 5 | AC21: 5 | AD21: 5 | AE21: 5 | AF21: 5 | AG21: 5 | AH21: =SUM(D21:AG21) -> 136 | AI21: =COUNT(D21:AG21) -> 25
B22: Paid Amount | D22: =D18/D21 -> #DIV/0! | E22: =E18/E21 -> 809.028 | F22: =F18/F21 -> 591.8 | G22: =G18/G21 -> 891.11 | H22: =H18/H21 -> 512.85667 | I22: =I18/I21 -> 1339.668 | J22: =J18/J21 -> 1015.905 | K22: =K18/K21 -> #DIV/0! | ... AG22: =AG18/AG21 -> 1092.608 | AH22: =SUM(D22:AG22) -> #DIV/0! | AI22: =COUNT(D22:AG22) -> 25
A23: 1 | B23: Ambare D.K | F23: 591 | G23: 891 | H23: 280 | L23: 982 | N23: 1065 | O23: 865 | P23: 686 | Q23: 610 | S23: 551 | T23: 740 | U23: 908 | V23: 732 | W23: 550 | X23: 1326 | Z23: 739 | AB23: 973 | AH23: =SUM(D23:AG23) -> 12489 | AI23: =COUNT(D23:AG23) -> 16
A24: 2 | B24: Mr. KASHINATH JAGANATH BIRJADAR | C24: 101818174092 | E24: 809 | F24: 591 | G24: 891 | H24: 559 | I24: 1339 | J24: 1015 | L24: 1202 | M24: 1047 | N24: 1065 | O24: 865 | P24: 862 | Q24: 742 | S24: 859 | T24: 740 | U24: 908 | W24: 550 | X24: 1326 | Z24: 739 | AA24: 1019 | AC24: 756 | AD24: 908 | AE24: 1003 | AF24: 616 | AG24: 1004 | AH24: =SUM(D24:AG24) -> 21415 | AI24: =COUNT(D24:AG24) -> 24
A25: 3 | B25: Mr. BHIMAHSNKAR SHARNAPPA ISHWARKATTI | C25: 102004077854 | E25: 809 | F25: 591 | G25: 891 | H25: 559 | I25: 1339 | J25: 1015 | L25: 1202 | M25: 1047 | N25: 1065 | O25: 865 | P25: 862 | Q25: 742 | S25: 859 | T25: 740 | U25: 908 | V25: 732 | W25: 550 | X25: 1326 | Z25: 739 | AA25: 1019 | AB25: 973 | AC25: 756 | AD25: 908 | AE25: 1003 | AF25: =616+873 -> 1489 | AG25: 1114 | AH25: =SUM(D25:AG25) -> 24103 | AI25: =COUNT(D25:AG25)+1 -> 27
A26: 4 | B26: Mr. SHIVANAND KANTAPPA KOSHTI | C26: 101817173110 | E26: 809 | F26: 591 | G26: 891 | H26: 559 | I26: 1339 | L26: 1202 | M26: 1047 | N26: 1065 | O26: 230 | P26: 862 | Q26: 742 | S26: 859 | T26: 740 | U26: 908 | V26: 732 | X26: 1326 | Z26: 739 | AA26: 1019 | AB26: 973 | AC26: 756 | AD26: 908 | AE26: 1003 | AF26: 616 | AG26: 1114 | AH26: =SUM(D26:AG26) -> 21030 | AI26: =COUNT(D26:AG26) -> 24
A27: 5 | B27: Mr. KHAJASAHEB GULAB HIMONE | C27: 102120964651 | E27: 809 | F27: 591 | G27: 891 | H27: 559 | I27: 1339 | J27: 1015 | L27: 1202 | M27: 1047 | N27: 1065 | O27: 865 | P27: 862 | Q27: 742 | S27: 859 | T27: 740 | U27: 908 | V27: 732 | W27: 550 | X27: 1326 | Z27: 739 | AA27: 1019 | AB27: 973 | AC27: 756 | AD27: 908 | AE27: 1003 | AF27: 616 | AG27: 1114 | AH27: =SUM(D27:AG27) -> 23230 | AI27: =COUNT(D27:AG27) -> 26
A28: 6 | B28: Mr. VISHAL SURESH MANE | C28: 101432431093 | E28: 809 | F28: 591 | G28: 891 | H28: 559 | I28: 1339 | J28: 1015 | L28: 1202 | M28: 1047 | N28: 1065 | O28: 865 | P28: 862 | Q28: 742 | S28: 859 | T28: 740 | U28: 908 | V28: 732 | Z28: 739 | AA28: 1019 | AB28: 973 | AC28: 756 | AD28: 908 | AE28: 1003 | AF28: 616 | AG28: 1114 | AH28: =SUM(D28:AG28) -> 21354 | AI28: =COUNT(D28:AG28) -> 24
B29: Total | D29: =SUM(D23:D28) -> 0 | E29: =SUM(E23:E28) -> 4045 | F29: =SUM(F23:F28) -> 3546 | G29: =SUM(G23:G28) -> 5346 | H29: =SUM(H23:H28) -> 3075 | I29: =SUM(I23:I28) -> 6695 | J29: =SUM(J23:J28) -> 4060 | K29: =SUM(K23:K28) -> 0 | ... AH29: =SUM(AH23:AH28) -> 123621 | AI29: =COUNT(D29:AG29) -> 30
B30: HAND EMARY 1 (GroupA) | D30: =D29-D18 -> 0 | E30: =E29-E18 -> -0.14 | F30: =F29-F18 -> -4.8 | G30: =G29-G18 -> -0.66 | H30: =H29-H18 -> -2.14 | I30: =I29-I18 -> -3.34 | J30: =J29-J18 -> -3.62 | K30: =K29-K18 -> 0 | ... AG30: =AG29-AG18 -> -3.04 | AH30: =SUM(D30:AG30) -> 3011.06 | AI30: =COUNT(D30:AG30) -> 30
B31: TOTAL AMOUNT | D31: =D32*D33 -> 0 | E31: =E32*E33 -> 6940.8 | F31: =F32*F33 -> 8104.96 | G31: =G32*G33 -> 7467.008 | H31: =H32*H33 -> 8408.32 | I31: =I32*I33 -> 6601.92 | J31: =J32*J33 -> 5987.2 | K31: =K32*K33 -> 0 | ... AG31: =AG32*AG33 -> 6517.76 | AH31: =SUM(D31:AG31) -> 168183.49 | AI31: =COUNT(D31:AG31) -> 30
B32: TOTAL MT | E32: 21.69 | F32: 25.328 | G32: 23.3344 | H32: 26.276 | I32: 20.631 | J32: 18.71 | L32: 20.54 | M32: 24.714 | N32: 17.58 | O32: 19.414 | P32: 14.583 | Q32: 14.877 | R32: 17.008 | S32: 13.17 | T32: 16.932 | U32: 19.653 | V32: 17.759 | W32: 21.011 | X32: 21.7 | Y32: 11.374 | Z32: 12.294 | AA32: 14.706 | AB32: 16.89 | AC32: 20.04 | AD32: 20.792 | AE32: 17.54 | AF32: 16.659 | AG32: 20.368 | AH32: =SUM(D32:AG32) -> 525.5734 | AI32: =COUNT(D32:AG32) -> 28
B33: Rate | D33: 320 | E33: 320 | F33: 320 | G33: 320 | H33: 320 | I33: 320 | J33: 320 | K33: 320 | L33: 320 | M33: 320 | N33: 320 | O33: 320 | P33: 320 | Q33: 320 | R33: 320 | S33: 320 | T33: 320 | U33: 320 | V33: 320 | W33: 320 | X33: 320 | Y33: 320 | Z33: 320 | AA33: 320 | AB33: 320 | AC33: 320 | AD33: 320 | AE33: 320 | AF33: 320 | AG33: 320 | AI33: =COUNT(D33:AG33) -> 30
B34: No.of Manpawar | E34: 7 | F34: 7 | G34: 7 | H34: 8 | I34: 7 | J34: 7 | L34: 7 | M34: 7 | N34: 6 | O34: 6 | P34: 7 | Q34: 7 | R34: 7 | S34: 5 | T34: 7 | U34: 7 | V34: 6 | W34: 8 | X34: 8 | Y34: 6 | Z34: 6 | AA34: 7 | AB34: 7 | AC34: 8 | AD34: 8 | AE34: 7 | AF34: 7 | AG34: 8 | AH34: =SUM(D34:AG34) -> 195 | AI34: =COUNT(D34:AG34) -> 28
B35: Paid Amount | D35: =D31/D34 -> #DIV/0! | E35: =E31/E34 -> 991.54286 | F35: =F31/F34 -> 1157.8514 | G35: =G31/G34 -> 1066.7154 | H35: =H31/H34 -> 1051.04 | I35: =I31/I34 -> 943.13143 | J35: =J31/J34 -> 855.31429 | K35: =K31/K34 -> #DIV/0! | ... AG35: =AG31/AG34 -> 814.72 | AH35: =SUM(D35:AG35) -> #DIV/0! | AI35: =COUNT(D35:AG35) -> 28
A36: 1 | B36: Mr. NAMDEV DURGAPPA BANDGAR | C36: 101407413648 | H36: 1131 | I36: 1008 | J36: 906 | L36: 1003 | M36: 1226 | N36: 1025 | O36: 1132 | P36: 686 | Q36: 701 | R36: 815 | T36: 811 | U36: 956 | V36: 1026 | W36: 900 | X36: 1065 | Y36: 617 | Z36: 708 | AA36: 721 | AB36: 809 | AC36: =772+837 -> 1609 | AD36: 783 | AG36: 902 | AH36: =SUM(D36:AG36) -> 20540 | AI36: =COUNT(D36:AG36)+1 -> 23
A37: 2 | B37: Mr. KHALID ILAI SHAIKH | C37: 101373078654 | E37: 1108 | F37: 1259 | G37: 1265 | H37: 1131 | I37: 1008 | J37: 906 | L37: 1003 | M37: 1226 | N37: 1025 | O37: 1132 | P37: 686 | Q37: 701 | S37: 1038 | T37: 811 | U37: 956 | W37: 900 | X37: 1065 | Z37: 708 | AA37: 721 | AB37: 809 | AC37: 837 | AD37: 713 | AE37: 806 | AF37: 857 | AG37: 902 | AH37: =SUM(D37:AG37) -> 23573 | AI37: =COUNT(D37:AG37) -> 25
A38: 3 | B38: Mr. WAGHMODE DATTATRAY ASHOK | C38: 101391642731 | E38: 1108 | F38: 1259 | G38: 1265 | H38: 1131 | I38: 1008 | J38: 906 | L38: 1003 | M38: 1226 | N38: 1025 | O38: 1132 | P38: 686 | Q38: 701 | T38: 811 | U38: 956 | V38: 1026 | W38: 900 | X38: 659 | Y38: 617 | AA38: 721 | AB38: 809 | AC38: 837 | AD38: 925 | AE38: 902 | AF38: 705 | AG38: 902 | AH38: =SUM(D38:AG38) -> 23220 | AI38: =COUNT(D38:AG38) -> 25
A39: 4 | B39: Mr. SATISH SHIVAJI SHINDE | C39: 101475170616 | E39: 1108 | F39: 1259 | G39: 1265 | H39: 1131 | I39: 1008 | J39: 906 | L39: 1003 | M39: 1226 | N39: 1025 | O39: 1132 | P39: 686 | Q39: 701 | S39: 1038 | T39: 811 | U39: 956 | V39: 1026 | W39: 900 | X39: 1065 | Z39: 708 | AA39: 553 | AB39: 809 | AC39: 837 | AD39: 925 | AE39: 902 | AF39: 705 | AG39: 902 | AH39: =SUM(D39:AG39) -> 24587 | AI39: =COUNT(D39:AG39) -> 26
A40: 5 | B40: Mr. KASHINATH ABHIMANU PATIL | C40: 101520450548 | E40: 1108 | F40: 1259 | G40: 1265 | H40: 1131 | I40: 1008 | J40: 906 | L40: 1003 | M40: 1226 | N40: 1025 | O40: 1132 | P40: 686 | Q40: 701 | R40: 815 | T40: 811 | U40: 956 | V40: 1026 | W40: 900 | X40: 1065 | Y40: 617 | Z40: 708 | AA40: 721 | AB40: 809 | AC40: 837 | AD40: 925 | AE40: 902 | AF40: 705 | AG40: 902 | AH40: =SUM(D40:AG40) -> 25149 | AI40: =COUNT(D40:AG40) -> 27
A41: 6 | B41: SAGAR GHARSANGE | E41: 850 | F41: 1259 | G41: 592 | H41: 1131 | W41: 770 | AB41: 809 | AC41: 837 | AD41: 925 | AE41: 902 | AF41: 705 | AG41: 902 | AH41: =SUM(D41:AG41) -> 9682 | AI41: =COUNT(D41:AG41) -> 11
A42: 7 | B42: AJAY PENTA | E42: 550 | F42: 550 | H42: 550 | I42: 550 | J42: 550 | Q42: 550 | S42: 550 | T42: 550 | U42: 550 | V42: 550 | W42: 550 | X42: 550 | Z42: 550 | AA42: 550 | AB42: 550 | AC42: 550 | AD42: 550 | AE42: 550 | AF42: 550 | AG42: 550 | AH42: =SUM(D42:AG42) -> 11000 | AI42: =COUNT(D42:AG42) -> 20
A43: 8 | B43: Dhanajay shinde | G43: 550 | AH43: =SUM(D43:AG43) -> 550 | AI43: =COUNT(D43:AG43) -> 1
A44: 9 | B44: HARUN MULLA | L44: 550 | M44: 550 | O44: 550 | P44: 550 | R44: 550 | S44: 550 | X44: 550 | Y44: 550 | Z44: 550 | AA44: 550 | AD44: 550 | AE44: 550 | AF44: 550 | AG44: 550 | AH44: =SUM(D44:AG44) -> 7700 | AI44: =COUNT(D44:AG44) -> 14
A45: 10 | B45: Arajun Bandagar | N45: 500 | AH45: =SUM(D45:AG45) -> 500 | AI45: =COUNT(D45:AG45) -> 1
A46: 11 | B46: DINESH SALARGAR | R46: 815 | Y46: 617 | AA46: 721 | AH46: =SUM(D46:AG46) -> 2153 | AI46: =COUNT(D46:AG46) -> 3
A47: 12 | B47: ABHIJIT WAGHMARE | R47: 815 | AF47: 705 | AH47: =SUM(D47:AG47) -> 1520 | AI47: =COUNT(D47:AG47) -> 2
A48: 13 | B48: Mr. AKASH JAGNNATH TENGALE | C48: 101747190938 | E48: 1108 | F48: 565 | G48: 1265 | H48: 1131 | I48: 1008 | J48: 906 | L48: 1003 | M48: 1226 | AC48: 837 | AD48: 925 | AE48: 902 | AF48: 705 | AH48: =SUM(D48:AG48) -> 11581 | AI48: =COUNT(D48:AG48) -> 12
B49: Total | D49: =SUM(D36:D48) -> 0 | E49: =SUM(E36:E48) -> 6940 | F49: =SUM(F36:F48) -> 7410 | G49: =SUM(G36:G48) -> 7467 | H49: =SUM(H36:H48) -> 8467 | I49: =SUM(I36:I48) -> 6598 | J49: =SUM(J36:J48) -> 5986 | K49: =SUM(K36:K48) -> 0 | ... AG49: =SUM(AG36:AG48) -> 6512 | AH49: =SUM(AH36:AH41) -> 126751 | AI49: =COUNT(D49:AG49) -> 30
B50: HAND EMARY 2 | D50: =D49-D31 -> 0 | E50: =E49-E31 -> -0.8 | F50: =F49-F31 -> -694.96 | G50: =G49-G31 -> -0.008 | H50: =H49-H31 -> 58.68 | I50: =I49-I31 -> -3.92 | J50: =J49-J31 -> -1.2 | K50: =K49-K31 -> 0 | ... AG50: =AG49-AG31 -> -5.76 | AH50: =SUM(D50:AG50) -> -6428.488 | AI50: =COUNT(D50:AG50) -> 30
B51: TOTAL AMO | D51: =D53*D52 -> 0 | E51: =E53*E52 -> 3753.6 | F51: =F53*F52 -> 7260.8 | G51: =G53*G52 -> 6987.52 | H51: =H53*H52 -> 5436.16 | I51: =I53*I52 -> 8242.56 | J51: =J53*J52 -> 6662.4 | K51: =K53*K52 -> 0 | ... AG51: =AG53*AG52 -> 7408 | AH51: =SUM(D51:AG51) -> 163895.68 | AI51: =COUNT(D51:AG51) -> 30
B52: TOTAL MT | E52: 11.73 | F52: 22.69 | G52: 21.836 | H52: 16.988 | I52: 25.758 | J52: 20.82 | L52: 17.286 | M52: 20.715 | N52: 23.048 | O52: 21.206 | P52: 18.335 | Q52: 20.868 | S52: 16.893 | T52: 16.635 | U52: 22.291 | V52: 20.022 | W52: 25.075 | X52: 17.566 | Z52: 13.86 | AA52: 19.553 | AB52: 17.82 | AC52: 18.929 | AD52: 20.35 | AE52: 20 | AF52: 18.75 | AG52: 23.15 | AH52: =SUM(D52:AG52) -> 512.174 | AI52: =COUNT(D52:AG52) -> 26
B53: Rate | D53: 320 | E53: 320 | F53: 320 | G53: 320 | H53: 320 | I53: 320 | J53: 320 | K53: 320 | L53: 320 | M53: 320 | N53: 320 | O53: 320 | P53: 320 | Q53: 320 | R53: 320 | S53: 320 | T53: 320 | U53: 320 | V53: 320 | W53: 320 | X53: 320 | Y53: 320 | Z53: 320 | AA53: 320 | AB53: 320 | AC53: 320 | AD53: 320 | AE53: 320 | AF53: 320 | AG53: 320 | AI53: =COUNT(D53:AG53) -> 30
B54: No.of Manpawar | E54: 5 | F54: 8 | G54: 8 | H54: 7 | I54: 8 | J54: 7 | L54: 7 | M54: 7 | N54: 8 | O54: 7 | P54: 8 | Q54: 8 | S54: 6 | T54: 8 | U54: 7 | V54: 8 | W54: 8 | X54: 7 | Z54: 7 | AA54: 9 | AB54: 8 | AC54: 7 | AD54: 8 | AE54: 7 | AF54: 7 | AG54: 8 | AH54: =SUM(D54:AG54) -> 193 | AI54: =COUNT(D54:AG54) -> 26
B55: Paid Amount | D55: =D51/D54 -> #DIV/0! | E55: =E51/E54 -> 750.72 | F55: =F51/F54 -> 907.6 | G55: =G51/G54 -> 873.44 | H55: =H51/H54 -> 776.59429 | I55: =I51/I54 -> 1030.32 | J55: =J51/J54 -> 951.77143 | K55: =K51/K54 -> #DIV/0! | ... AG55: =AG51/AG54 -> 926 | AH55: =SUM(D55:AG55) -> #DIV/0! | AI55: =COUNT(D55:AG55) -> 26
A56: 1 | B56: Mr. AMOL TEJU RATHOD | C56: 101509952020 | E56: 750 | F56: 956 | G56: 873 | H56: 856 | I56: 1030 | L56: 830 | M56: 946 | N56: 921 | O56: 909 | P56: 858 | Q56: 834 | S56: 900 | T56: 677 | U56: 1019 | V56: 800 | W56: 1003 | Z56: 659 | AA56: 842 | AB56: 731 | AC56: 772 | AE56: 957 | AF56: 857 | AG56: 953 | AH56: =SUM(D56:AG56) -> 19933 | AI56: =COUNT(D56:AG56) -> 23
A57: 2 | B57: ANKUSH BHALE | C57: 101835374035 | E57: 750 | F57: 956 | G57: 873 | H57: 343 | I57: 1030 | L57: 830 | M57: 946 | N57: 921 | O57: 418 | Q57: 701 | T57: 582 | AC57: 772 | AD57: 925 | AE57: 957 | AF57: 857 | AG57: 953 | AH57: =SUM(D57:AG57) -> 12814 | AI57: =COUNT(D57:AG57) -> 16
A58: 3 | B58: Mr. MALLINATH SHIVARAM VHANAKADE | C58: 101522138160 | I58: 1030 | J58: 951 | L58: 830 | M58: 946 | N58: 921 | O58: 909 | P58: 858 | Q58: 834 | S58: 900 | T58: 677 | U58: 1019 | V58: 800 | W58: 1003 | X58: 803 | Z58: 659 | AA58: 842 | AF58: 857 | AG58: 953 | AH58: =SUM(D58:AG58) -> 15792 | AI58: =COUNT(D58:AG58) -> 18
A59: 4 | B59: Mr. DINESH VASANT SALGAR | C59: 102053057886 | E59: 750 | F59: 956 | G59: 873 | H59: 856 | I59: 1030 | J59: 951 | L59: 830 | M59: 946 | N59: 921 | O59: 909 | P59: 714 | Q59: 834 | S59: 900 | T59: 677 | U59: 1019 | V59: 800 | W59: 1003 | X59: 803 | Z59: 659 | AB59: 731 | AC59: 772 | AD59: 901 | AE59: 957 | AG59: 953 | AH59: =SUM(D59:AG59) -> 20745 | AI59: =COUNT(D59:AG59) -> 24
A60: 5 | B60: Rohan Pandit | F60: 956 | G60: 873 | H60: 856 | I60: 1030 | J60: 951 | L60: 550 | N60: 921 | O60: 909 | P60: 858 | Q60: 834 | R60: 815 | S60: 900 | T60: 677 | U60: 1019 | V60: 800 | W60: 1003 | X60: 803 | AA60: 413 | AB60: 731 | AC60: 772 | AG60: 732 | AH60: =SUM(D60:AG60) -> 17403 | AI60: =COUNT(D60:AG60) -> 21
A61: 6 | B61: YUVARAJ HIRKURE | J61: 951 | S61: 900 | U61: 1019 | V61: 800 | W61: 1003 | X61: 803 | Z61: 659 | AA61: 652 | AB61: 731 | AC61: 772 | AD61: 901 | AE61: 957 | AF61: 857 | AG61: 953 | AH61: =SUM(D61:AG61) -> 11958 | AI61: =COUNT(D61:AG61) -> 14
A62: 7 | B62: Mr. ABHISHEK SUNIL RATHOD | C62: 102078951370 | F62: 956 | G62: 873 | H62: 856 | I62: 1030 | N62: 921 | O62: 909 | P62: 858 | Q62: 834 | V62: 800 | W62: 1003 | Z62: 659 | AA62: 842 | AB62: 731 | AD62: 494 | AH62: =SUM(D62:AG62) -> 11766 | AI62: =COUNT(D62:AG62) -> 14
A63: 8 | B63: Mr. RAJAKUMAR BADIGER | C63: 102143026061 | M63: 946 | O63: 909 | Q63: 834 | S63: 900 | T63: 677 | U63: 1019 | V63: 800 | W63: 1003 | X63: 803 | Z63: 480 | AA63: 426 | AB63: 583 | AD63: 901 | AF63: 857 | AG63: 953 | AH63: =SUM(D63:AG63) -> 12091 | AI63: =COUNT(D63:AG63) -> 15
A64: 9 | B64: RAJKUMAR ANDONDI | E64: 750 | F64: 1259 | G64: 873 | I64: 1030 | J64: 951 | L64: 830 | M64: 946 | N64: 921 | O64: 990 | P64: 858 | Q64: 834 | T64: 677 | X64: 803 | Z64: 659 | AA64: 842 | AB64: 731 | AC64: 772 | AD64: 901 | AE64: 957 | AF64: 857 | AG64: 953 | AH64: =SUM(D64:AG64) -> 18394 | AI64: =COUNT(D64:AG64) -> 21
A65: 10 | B65: ANIL RAVAT | F65: 956 | G65: 873 | H65: 856 | L65: 830 | M65: 946 | N65: 921 | P65: 858 | Q65: 834 | R65: 815 | T65: 677 | U65: 1019 | V65: 800 | W65: 1003 | X65: =406+803 -> 1209 | Y65: 617 | AA65: 842 | AB65: 731 | AC65: 650 | AD65: 901 | AE65: 806 | AH65: =SUM(D65:AG65) -> 17144 | AI65: =COUNT(D65:AG65)+1 -> 21
A66: 11 | B66: MANGESH ANKUSHROV | F66: 956 | G66: 873 | H66: 811 | I66: 1030 | J66: 951 | S66: 1038 | T66: 811 | U66: 956 | V66: 1026 | W66: 900 | X66: 1065 | AH66: =SUM(D66:AG66) -> 10417 | AI66: =COUNT(D66:AG66) -> 11
A67: 12 | B67: Pundalik Jadhav | E67: 750 | J67: 951 | M67: 1140 | P67: 686 | AA67: 839 | AD67: 950 | AH67: =SUM(D67:AG67) -> 5316 | AI67: =COUNT(D67:AG67) -> 6
B68: Total | D68: =SUM(D56:D67) -> 0 | E68: =SUM(E56:E67) -> 3750 | F68: =SUM(F56:F67) -> 7951 | G68: =SUM(G56:G67) -> 6984 | H68: =SUM(H56:H67) -> 5434 | I68: =SUM(I56:I67) -> 8240 | J68: =SUM(J56:J67) -> 6657 | K68: =SUM(K56:K67) -> 0 | ... AH68: =SUM(AH56:AH67) -> 173773 | AI68: =COUNT(D68:AG68) -> 30
D69: =D68-D51 -> 0 | E69: =E68-E51 -> -3.6 | F69: =F68-F51 -> 690.2 | G69: =G68-G51 -> -3.52 | H69: =H68-H51 -> -2.16 | I69: =I68-I51 -> -2.56 | J69: =J68-J51 -> -5.4 | K69: =K68-K51 -> 0 | ... AG69: =AG68-AG51 -> -5 | AH69: =SUM(D69:AE69) -> 10740.32 | AI69: =COUNT(D69:AG69) -> 30
B70: Final amount | D70: =D16+D29 -> 550 | E70: =E16+E29 -> 8745 | F70: =F16+F29 -> 8242 | G70: =G16+G29 -> 10896 | H70: =H16+H29 -> 8997 | I70: =I16+I29 -> 10875 | J70: =J16+J29 -> 9784 | K70: =K16+K29 -> 1100 | ... AH70: =AH16+AH29 -> 250101 | AI70: =COUNT(D70:AG70) -> 30
B71: Final MT | D71: =D4+D19 -> 0 | E71: =E4+E19 -> 39.773 | F71: =F4+F19 -> 39.761 | G71: =G4+G19 -> 49.554 | H71: =H4+H19 -> 40.931 | I71: =I4+I19 -> 49.448 | J71: =J4+J19 -> 44.495 | K71: =K4+K19 -> 0 | ... AH71: =AH4+AH19 -> 1133.05 | AI71: =COUNT(D71:AG71) -> 30
B72: HE amount | D72: =D68+D49 -> 0 | E72: =E68+E49 -> 10690 | F72: =F68+F49 -> 15361 | G72: =G68+G49 -> 14451 | H72: =H68+H49 -> 13901 | I72: =I68+I49 -> 14838 | J72: =J68+J49 -> 12643 | K72: =K68+K49 -> 0 | ... AH72: =AH68+AH49 -> 300524 | AI72: =COUNT(D72:AG72) -> 30
B73: HE MT | D73: =D52+D32 -> 0 | E73: =E52+E32 -> 33.42 | F73: =F52+F32 -> 48.018 | G73: =G52+G32 -> 45.1704 | H73: =H52+H32 -> 43.264 | I73: =I52+I32 -> 46.389 | J73: =J52+J32 -> 39.53 | K73: =K52+K32 -> 0 | ... AH73: =AH52+AH32 -> 1037.7474 | AI73: =COUNT(D73:AG73) -> 30

Sheet FINAL TANNAGE AMO.
B1: Day April-26 | D1: 1 | E1: 2 | F1: 3 | G1: 4 | H1: 5 | I1: 6 | J1: 7 | K1: 8 | L1: 9 | M1: 10 | N1: 11 | O1: 12 | P1: 13 | Q1: 14 | R1: 15 | S1: 16 | T1: 17 | U1: 18 | V1: 19 | W1: 20 | X1: 21 | Y1: 22 | Z1: 23 | AA1: 24 | AB1: 25 | AC1: 26 | AD1: 27 | AE1: 28 | AF1: 29 | AG1: 30 | AH1: Total
A2: 1 | B2: Mr. ANIL G MALI | C2: 101475240602 | E2: 940 | F2: 1130 | G2: 925 | H2: 987 | I2: 836 | J2: 954 | N2: 923 | P2: 919 | Q2: 779 | S2: 609 | T2: 851 | U2: 888 | V2: 983 | W2: 510 | X2: 1941 | AB2: 917 | AC2: 836 | AD2: 950 | AE2: 889 | AF2: 873 | AG2: 879 | AH2: =SUM(D2:AG2) -> 19519 | AI2: =COUNT(D2:AG2) -> 21 | AJ2: =VLOOKUP(C2,'Name Details'!A:C,3,0) -> Mr. ANIL G MALI | AK2: =AJ2=B2 -> TRUE
A3: 2 | B3: Mr. REVANASIDDH SHIVAPPA ISHWARKATTI | C3: 101492178974 | D3: 550 | E3: 940 | F3: 1130 | G3: 925 | H3: 987 | I3: 836 | J3: 954 | K3: 550 | L3: 833 | M3: 1140 | N3: 923 | O3: 903 | P3: 919 | Q3: 779 | R3: 550 | S3: 609 | T3: 851 | U3: 888 | V3: 983 | W3: 1050 | X3: 1941 | Y3: 550 | Z3: 936 | AF3: 873 | AG3: 879 | AH3: =SUM(D3:AG3) -> 22479 | AI3: =COUNT(D3:AG3) -> 25 | AJ3: =VLOOKUP(C3,'Name Details'!A:C,3,0) -> Mr. REVANASIDDH SHIVAPPA ISHWARKATTI | AK3: =AJ3=B3 -> TRUE
A4: 3 | B4: Mr. JITENDRA SIDRAM KOLI | C4: 101603294918 | E4: 940 | F4: 1130 | G4: 925 | H4: 987 | I4: 836 | J4: 954 | L4: 833 | M4: 1140 | N4: 923 | O4: 903 | P4: 919 | S4: 609 | T4: 851 | U4: 888 | V4: 983 | W4: 1050 | X4: 690 | Z4: 936 | AA4: 839 | AB4: 917 | AC4: 836 | AE4: 889 | AF4: 873 | AG4: 879 | AH4: =SUM(D4:AG4) -> 21730 | AI4: =COUNT(D4:AG4) -> 24 | AJ4: =VLOOKUP(C4,'Name Details'!A:C,3,0) -> Mr. JITENDRA SIDRAM KOLI | AK4: =AJ4=B4 -> TRUE
A5: 4 | B5: Mr. VIJAY BHARLE | C5: 101944505682 | F5: 176 | G5: 925 | H5: 987 | J5: 954 | L5: 833 | M5: 1140 | N5: 923 | O5: 903 | Q5: 779 | S5: 609 | T5: 851 | U5: 888 | V5: 983 | W5: 1050 | Z5: 936 | AA5: 839 | AB5: 917 | AC5: 836 | AD5: 950 | AG5: 879 | AH5: =SUM(D5:AG5) -> 17358 | AI5: =COUNT(D5:AG5) -> 20 | AJ5: =VLOOKUP(C5,'Name Details'!A:C,3,0) -> Mr. VIJAY BHARLE | AK5: =AJ5=B5 -> TRUE
A6: 5 | B6: Mr. DIPAK DATTATRAY KUMBHAR | C6: 102052667942 | E6: 940 | G6: 925 | H6: 987 | I6: 836 | J6: 954 | K6: 550 | L6: 833 | M6: 1140 | N6: 923 | O6: 903 | P6: 919 | Q6: 779 | S6: 609 | T6: 851 | U6: 756 | V6: 983 | Z6: 936 | AA6: 839 | AB6: 917 | AC6: 836 | AD6: 950 | AE6: 889 | AG6: 879 | AH6: =SUM(D6:AG6) -> 20134 | AI6: =COUNT(D6:AG6) -> 23 | AJ6: =VLOOKUP(C6,'Name Details'!A:C,3,0) -> Mr. DIPAK DATTATRAY KUMBHAR | AK6: =AJ6=B6 -> TRUE
A7: 6 | B7: Mr. GIRISH SIDDHARAM MADYAL | C7: 101826609019 | E7: 940 | F7: 1130 | G7: 925 | H7: 987 | I7: 836 | J7: 954 | M7: 1140 | N7: 923 | O7: 903 | P7: 919 | Q7: 779 | S7: 609 | T7: 851 | U7: 888 | V7: 983 | W7: 1050 | X7: 1941 | Z7: 936 | AA7: 839 | AB7: 917 | AC7: 836 | AD7: 950 | AE7: 889 | AF7: 873 | AG7: 879 | AH7: =SUM(D7:AG7) -> 23877 | AI7: =COUNT(D7:AG7) -> 25 | AJ7: =VLOOKUP(C7,'Name Details'!A:C,3,0) -> Mr. GIRISH SIDDHARAM MADYAL | AK7: =AJ7=B7 -> TRUE
A8: 7 | B8: Mr. SHAVRSIDDHA KHANDAPPA LANDAGE | C8: 101951607397 | L8: 833 | AH8: =SUM(D8:AG8) -> 833 | AI8: =COUNT(D8:AG8) -> 1 | AJ8: =VLOOKUP(C8,'Name Details'!A:C,3,0) -> Mr. SHAVRSIDDHA KHANDAPPA LANDAGE | AK8: =AJ8=B8 -> TRUE
A9: 8 | B9: Mr. SUFIYAN SHEKULAL FULARI | C9: 102125816854 | AE9: 550 | AH9: =SUM(D9:AG9) -> 550 | AI9: =COUNT(D9:AG9) -> 1 | AJ9: =VLOOKUP(C9,'Name Details'!A:C,3,0) -> Mr. SUFIYAN SHEKULAL FULARI | AK9: =AJ9=B9 -> TRUE
A10: 1 | B10: DHANNAJAY AMBURE | C10: DHANNAJAY AMBURE | F10: 591 | G10: 891 | H10: 280 | L10: 982 | N10: 1065 | O10: 865 | P10: 686 | Q10: 610 | S10: 551 | T10: 740 | U10: 908 | V10: 732 | W10: 550 | X10: 1326 | Z10: 739 | AB10: 973 | AH10: =SUM(D10:AG10) -> 12489 | AI10: =COUNT(D10:AG10) -> 16 | AJ10: =VLOOKUP(C10,'Name Details'!A:C,3,0) -> #N/A | AK10: =AJ10=B10 -> #N/A
A11: 2 | B11: Mr. KASHINATH JAGANATH BIRJADAR | C11: 101818174092 | E11: 809 | F11: 591 | G11: 891 | H11: 559 | I11: 1339 | J11: 1015 | L11: 1202 | M11: 1047 | N11: 1065 | O11: 865 | P11: 862 | Q11: 742 | S11: 859 | T11: 740 | U11: 908 | W11: 550 | X11: 1326 | Z11: 739 | AA11: 1019 | AC11: 756 | AD11: 908 | AE11: 1003 | AF11: 616 | AG11: 1004 | AH11: =SUM(D11:AG11) -> 21415 | AI11: =COUNT(D11:AG11) -> 24 | AJ11: =VLOOKUP(C11,'Name Details'!A:C,3,0) -> Mr. KASHINATH JAGANATH BIRJADAR | AK11: =AJ11=B11 -> TRUE
A12: 3 | B12: Mr. BHIMAHSNKAR SHARNAPPA ISHWARKATTI | C12: 102004077854 | E12: 809 | F12: 591 | G12: 891 | H12: 559 | I12: 1339 | J12: 1015 | L12: 1202 | M12: 1047 | N12: 1065 | O12: 865 | P12: 862 | Q12: 742 | S12: 859 | T12: 740 | U12: 908 | V12: 732 | W12: 550 | X12: 1326 | Z12: 739 | AA12: 1019 | AB12: 973 | AC12: 756 | AD12: 908 | AE12: 1003 | AF12: =616+873 -> 1489 | AG12: 1114 | AH12: =SUM(D12:AG12) -> 24103 | AI12: =COUNT(D12:AG12)+1 -> 27 | AJ12: =VLOOKUP(C12,'Name Details'!A:C,3,0) -> Mr. BHIMAHSNKAR SHARNAPPA ISHWARKATTI | AK12: =AJ12=B12 -> TRUE
A13: 4 | B13: Mr. SHIVANAND KANTAPPA KOSHTI | C13: 101817173110 | E13: 809 | F13: 591 | G13: 891 | H13: 559 | I13: 1339 | L13: 1202 | M13: 1047 | N13: 1065 | O13: 230 | P13: 862 | Q13: 742 | S13: 859 | T13: 740 | U13: 908 | V13: 732 | X13: 1326 | Z13: 739 | AA13: 1019 | AB13: 973 | AC13: 756 | AD13: 908 | AE13: 1003 | AF13: 616 | AG13: 1114 | AH13: =SUM(D13:AG13) -> 21030 | AI13: =COUNT(D13:AG13) -> 24 | AJ13: =VLOOKUP(C13,'Name Details'!A:C,3,0) -> Mr. SHIVANAND KANTAPPA KOSHTI | AK13: =AJ13=B13 -> TRUE
A14: 5 | B14: Mr. KHAJASAHEB GULAB HIMONE | C14: 102120964651 | E14: 809 | F14: 591 | G14: 891 | H14: 559 | I14: 1339 | J14: 1015 | L14: 1202 | M14: 1047 | N14: 1065 | O14: 865 | P14: 862 | Q14: 742 | S14: 859 | T14: 740 | U14: 908 | V14: 732 | W14: 550 | X14: 1326 | Z14: 739 | AA14: 1019 | AB14: 973 | AC14: 756 | AD14: 908 | AE14: 1003 | AF14: 616 | AG14: 1114 | AH14: =SUM(D14:AG14) -> 23230 | AI14: =COUNT(D14:AG14) -> 26 | AJ14: =VLOOKUP(C14,'Name Details'!A:C,3,0) -> Mr. KHAJASAHEB GULAB HIMONE | AK14: =AJ14=B14 -> TRUE
A15: 6 | B15: Mr. VISHAL SURESH MANE | C15: 101432431093 | E15: 809 | F15: 591 | G15: 891 | H15: 559 | I15: 1339 | J15: 1015 | L15: 1202 | M15: 1047 | N15: 1065 | O15: 865 | P15: 862 | Q15: 742 | S15: 859 | T15: 740 | U15: 908 | V15: 732 | Z15: 739 | AA15: 1019 | AB15: 973 | AC15: 756 | AD15: 908 | AE15: 1003 | AF15: 616 | AG15: 1114 | AH15: =SUM(D15:AG15) -> 21354 | AI15: =COUNT(D15:AG15) -> 24 | AJ15: =VLOOKUP(C15,'Name Details'!A:C,3,0) -> Mr. VISHAL SURESH MANE | AK15: =AJ15=B15 -> TRUE
A16: 1 | B16: Mr. NAMDEV DURGAPPA BANDGAR | C16: 101407413648 | H16: 1131 | I16: 1008 | J16: 906 | L16: 1003 | M16: 1226 | N16: 1025 | O16: 1132 | P16: 686 | Q16: 701 | R16: 815 | T16: 811 | U16: 956 | V16: 1026 | W16: 900 | X16: 1065 | Y16: 617 | Z16: 708 | AA16: 721 | AB16: 809 | AC16: =772+837 -> 1609 | AD16: 783 | AG16: 902 | AH16: =SUM(D16:AG16) -> 20540 | AI16: =COUNT(D16:AG16)+1 -> 23 | AJ16: =VLOOKUP(C16,'Name Details'!A:C,3,0) -> Mr. NAMDEV DURGAPPA BANDGAR | AK16: =AJ16=B16 -> TRUE
A17: 2 | B17: Mr. KHALID ILAI SHAIKH | C17: 101373078654 | E17: 1108 | F17: 1259 | G17: 1265 | H17: 1131 | I17: 1008 | J17: 906 | L17: 1003 | M17: 1226 | N17: 1025 | O17: 1132 | P17: 686 | Q17: 701 | S17: 1038 | T17: 811 | U17: 956 | W17: 900 | X17: 1065 | Z17: 708 | AA17: 721 | AB17: 809 | AC17: 837 | AD17: 713 | AE17: 806 | AF17: 857 | AG17: 902 | AH17: =SUM(D17:AG17) -> 23573 | AI17: =COUNT(D17:AG17) -> 25 | AJ17: =VLOOKUP(C17,'Name Details'!A:C,3,0) -> Mr. KHALID ILAI SHAIKH | AK17: =AJ17=B17 -> TRUE
A18: 3 | B18: Mr. WAGHMODE DATTATRAY ASHOK | C18: 101391642731 | E18: 1108 | F18: 1259 | G18: 1265 | H18: 1131 | I18: 1008 | J18: 906 | L18: 1003 | M18: 1226 | N18: 1025 | O18: 1132 | P18: 686 | Q18: 701 | T18: 811 | U18: 956 | V18: 1026 | W18: 900 | X18: 659 | Y18: 617 | AA18: 721 | AB18: 809 | AC18: 837 | AD18: 925 | AE18: 902 | AF18: 705 | AG18: 902 | AH18: =SUM(D18:AG18) -> 23220 | AI18: =COUNT(D18:AG18) -> 25 | AJ18: =VLOOKUP(C18,'Name Details'!A:C,3,0) -> Mr. WAGHMODE DATTATRAY ASHOK | AK18: =AJ18=B18 -> TRUE
A19: 4 | B19: Mr. SATISH SHIVAJI SHINDE | C19: 101475170616 | E19: 1108 | F19: 1259 | G19: 1265 | H19: 1131 | I19: 1008 | J19: 906 | L19: 1003 | M19: 1226 | N19: 1025 | O19: 1132 | P19: 686 | Q19: 701 | S19: 1038 | T19: 811 | U19: 956 | V19: 1026 | W19: 900 | X19: 1065 | Z19: 708 | AA19: 553 | AB19: 809 | AC19: 837 | AD19: 925 | AE19: 902 | AF19: 705 | AG19: 902 | AH19: =SUM(D19:AG19) -> 24587 | AI19: =COUNT(D19:AG19) -> 26 | AJ19: =VLOOKUP(C19,'Name Details'!A:C,3,0) -> Mr. SATISH SHIVAJI SHINDE | AK19: =AJ19=B19 -> TRUE
A20: 5 | B20: Mr. KASHINATH ABHIMANYU PATIL | C20: 101520450548 | E20: 1108 | F20: 1259 | G20: 1265 | H20: 1131 | I20: 1008 | J20: 906 | L20: 1003 | M20: 1226 | N20: 1025 | O20: 1132 | P20: 686 | Q20: 701 | R20: 815 | T20: 811 | U20: 956 | V20: 1026 | W20: 900 | X20: 1065 | Y20: 617 | Z20: 708 | AA20: 721 | AB20: 809 | AC20: 837 | AD20: 925 | AE20: 902 | AF20: 705 | AG20: 902 | AH20: =SUM(D20:AG20) -> 25149 | AI20: =COUNT(D20:AG20) -> 27 | AJ20: =VLOOKUP(C20,'Name Details'!A:C,3,0) -> Mr. KASHINATH ABHIMANYU PATIL | AK20: =AJ20=B20 -> TRUE
A21: 6 | B21: Mr. SAGAR RAMESH GHARSANGI | C21: 101154454730 | E21: 850 | F21: 1259 | G21: 592 | H21: 1131 | W21: 770 | AB21: 809 | AC21: 837 | AD21: 925 | AE21: 902 | AF21: 705 | AG21: 902 | AH21: =SUM(D21:AG21) -> 9682 | AI21: =COUNT(D21:AG21) -> 11 | AJ21: =VLOOKUP(C21,'Name Details'!A:C,3,0) -> Mr. SAGAR RAMESH GHARSANGI | AK21: =AJ21=B21 -> TRUE
A22: 7 | B22: AJAY SHRINIVAS PENTA | C22: AJAY SHRINIVAS PENTA | E22: 550 | F22: 550 | H22: 550 | I22: 550 | J22: 550 | Q22: 550 | S22: 550 | T22: 550 | U22: 550 | V22: 550 | W22: 550 | X22: 550 | Z22: 550 | AA22: 550 | AB22: 550 | AC22: 550 | AD22: 550 | AE22: 550 | AF22: 550 | AG22: 550 | AH22: =SUM(D22:AG22) -> 11000 | AI22: =COUNT(D22:AG22) -> 20 | AJ22: =VLOOKUP(C22,'Name Details'!A:C,3,0) -> #N/A | AK22: =AJ22=B22 -> #N/A
A23: 8 | B23: Mr. DHANRAJ DATTATRAY SHINDE | C23: 102260241245 | G23: 550 | AH23: =SUM(D23:AG23) -> 550 | AI23: =COUNT(D23:AG23) -> 1 | AJ23: =VLOOKUP(C23,'Name Details'!A:C,3,0) -> Mr. DHANRAJ DATTATRAY SHINDE | AK23: =AJ23=B23 -> TRUE
A24: 9 | B24: Mr. HARUN BASHA MULLA | C24: 102209140373 | L24: 550 | M24: 550 | O24: 550 | P24: 550 | R24: 550 | S24: 550 | X24: 550 | Y24: 550 | Z24: 550 | AA24: 550 | AD24: 550 | AE24: 550 | AF24: 550 | AG24: 550 | AH24: =SUM(D24:AG24) -> 7700 | AI24: =COUNT(D24:AG24) -> 14 | AJ24: =VLOOKUP(C24,'Name Details'!A:C,3,0) -> Mr. HARUN BASHA MULLA | AK24: =AJ24=B24 -> TRUE
A25: 10 | B25: ARJUN HIRACHAND BANDAGAR | C25: ARJUN HIRACHAND BANDAGAR | N25: 500 | AH25: =SUM(D25:AG25) -> 500 | AI25: =COUNT(D25:AG25) -> 1 | AJ25: =VLOOKUP(C25,'Name Details'!A:C,3,0) -> #N/A | AK25: =AJ25=B25 -> #N/A
A26: 12 | B26: Mr. ABHIJIT PIRAPPA WAGHMARE | C26: 101447270865 | R26: 815 | AF26: 705 | AH26: =SUM(D26:AG26) -> 1520 | AI26: =COUNT(D26:AG26) -> 2 | AJ26: =VLOOKUP(C26,'Name Details'!A:C,3,0) -> Mr. ABHIJIT PIRAPPA WAGHMARE | AK26: =AJ26=B26 -> TRUE
A27: 13 | B27: Mr. AKASH JAGNNATH TENGALE | C27: 101747190938 | E27: 1108 | F27: 565 | G27: 1265 | H27: 1131 | I27: 1008 | J27: 906 | L27: 1003 | M27: 1226 | AC27: 837 | AD27: 925 | AE27: 902 | AF27: 705 | AH27: =SUM(D27:AG27) -> 11581 | AI27: =COUNT(D27:AG27) -> 12 | AJ27: =VLOOKUP(C27,'Name Details'!A:C,3,0) -> Mr. AKASH JAGNNATH TENGALE | AK27: =AJ27=B27 -> TRUE
A28: 1 | B28: Mr. AMOL TEJU RATHOD | C28: 101509952020 | E28: 750 | F28: 956 | G28: 873 | H28: 856 | I28: 1030 | L28: 830 | M28: 946 | N28: 921 | O28: 909 | P28: 858 | Q28: 834 | S28: 900 | T28: 677 | U28: 1019 | V28: 800 | W28: 1003 | Z28: 659 | AA28: 842 | AB28: 731 | AC28: 772 | AE28: 957 | AF28: 857 | AG28: 953 | AH28: =SUM(D28:AG28) -> 19933 | AI28: =COUNT(D28:AG28) -> 23 | AJ28: =VLOOKUP(C28,'Name Details'!A:C,3,0) -> Mr. AMOL TEJU RATHOD | AK28: =AJ28=B28 -> TRUE
A29: 2 | B29: Mr. ANKUASH SANJAY BHALE | C29: 101835374035 | E29: 750 | F29: 956 | G29: 873 | H29: 343 | I29: 1030 | L29: 830 | M29: 946 | N29: 921 | O29: 418 | Q29: 701 | T29: 582 | AC29: 772 | AD29: 925 | AE29: 957 | AF29: 857 | AG29: 953 | AH29: =SUM(D29:AG29) -> 12814 | AI29: =COUNT(D29:AG29) -> 16 | AJ29: =VLOOKUP(C29,'Name Details'!A:C,3,0) -> Mr. ANKUASH SANJAY BHALE | AK29: =AJ29=B29 -> TRUE
A30: 3 | B30: Mr. MALLINATH SHIVARAM VHANAKADE | C30: 101522138160 | I30: 1030 | J30: 951 | L30: 830 | M30: 946 | N30: 921 | O30: 909 | P30: 858 | Q30: 834 | S30: 900 | T30: 677 | U30: 1019 | V30: 800 | W30: 1003 | X30: 803 | Z30: 659 | AA30: 842 | AF30: 857 | AG30: 953 | AH30: =SUM(D30:AG30) -> 15792 | AI30: =COUNT(D30:AG30) -> 18 | AJ30: =VLOOKUP(C30,'Name Details'!A:C,3,0) -> Mr. MALLINATH SHIVARAM VHANAKADE | AK30: =AJ30=B30 -> TRUE
A31: 4 | B31: Mr. DINESH VASANT SALGAR | C31: 102053057886 | E31: 750 | F31: 956 | G31: 873 | H31: 856 | I31: 1030 | J31: 951 | L31: 830 | M31: 946 | N31: 921 | O31: 909 | P31: 714 | Q31: 834 | R31: 815 | S31: 900 | T31: 677 | U31: 1019 | V31: 800 | W31: 1003 | X31: 803 | Y31: 617 | Z31: 659 | AA31: 721 | AB31: 731 | AC31: 772 | AD31: 901 | AE31: 957 | AG31: 953 | AH31: =SUM(D31:AG31) -> 22898 | AI31: =COUNT(D31:AG31) -> 27 | AJ31: =VLOOKUP(C31,'Name Details'!A:C,3,0) -> Mr. DINESH VASANT SALGAR | AK31: =AJ31=B31 -> TRUE
A32: 5 | B32: Mr. ROHAN BABURAV PANDIT | C32: 101424676055 | F32: 956 | G32: 873 | H32: 856 | I32: 1030 | J32: 951 | L32: 550 | N32: 921 | O32: 909 | P32: 858 | Q32: 834 | R32: 815 | S32: 900 | T32: 677 | U32: 1019 | V32: 800 | W32: 1003 | X32: 803 | AA32: 413 | AB32: 731 | AC32: 772 | AG32: 732 | AH32: =SUM(D32:AG32) -> 17403 | AI32: =COUNT(D32:AG32) -> 21 | AJ32: =VLOOKUP(C32,'Name Details'!A:C,3,0) -> Mr. ROHAN BABURAV PANDIT | AK32: =AJ32=B32 -> TRUE
A33: 6 | B33: Mr. YUVRAJ MALAKARI HIRKURE | C33: 102190249257 | J33: 951 | S33: 900 | U33: 1019 | V33: 800 | W33: 1003 | X33: 803 | Z33: 659 | AA33: 652 | AB33: 731 | AC33: 772 | AD33: 901 | AE33: 957 | AF33: 857 | AG33: 953 | AH33: =SUM(D33:AG33) -> 11958 | AI33: =COUNT(D33:AG33) -> 14 | AJ33: =VLOOKUP(C33,'Name Details'!A:C,3,0) -> Mr. YUVRAJ MALAKARI HIRKURE | AK33: =AJ33=B33 -> TRUE
A34: 7 | B34: Mr. ABHISHEK SUNIL RATHOD | C34: 102078951370 | F34: 956 | G34: 873 | H34: 856 | I34: 1030 | N34: 921 | O34: 909 | P34: 858 | Q34: 834 | V34: 800 | W34: 1003 | Z34: 659 | AA34: 842 | AB34: 731 | AD34: 494 | AH34: =SUM(D34:AG34) -> 11766 | AI34: =COUNT(D34:AG34) -> 14 | AJ34: =VLOOKUP(C34,'Name Details'!A:C,3,0) -> Mr. ABHISHEK SUNIL RATHOD | AK34: =AJ34=B34 -> TRUE
A35: 8 | B35: Mr. RAJAKUMAR BADIGER | C35: 102143026061 | M35: 946 | O35: 909 | Q35: 834 | S35: 900 | T35: 677 | U35: 1019 | V35: 800 | W35: 1003 | X35: 803 | Z35: 480 | AA35: 426 | AB35: 583 | AD35: 901 | AF35: 857 | AG35: 953 | AH35: =SUM(D35:AG35) -> 12091 | AI35: =COUNT(D35:AG35) -> 15 | AJ35: =VLOOKUP(C35,'Name Details'!A:C,3,0) -> Mr. RAJAKUMAR BADIGER | AK35: =AJ35=B35 -> TRUE
A36: 9 | B36: Mr. RAJSHEKHAR ANDODGI | C36: 101591620448 | E36: 750 | F36: 1259 | G36: 873 | I36: 1030 | J36: 951 | L36: 830 | M36: 946 | N36: 921 | O36: 990 | P36: 858 | Q36: 834 | T36: 677 | X36: 803 | Z36: 659 | AA36: 842 | AB36: 731 | AC36: 772 | AD36: 901 | AE36: 957 | AF36: 857 | AG36: 953 | AH36: =SUM(D36:AG36) -> 18394 | AI36: =COUNT(D36:AG36) -> 21 | AJ36: =VLOOKUP(C36,'Name Details'!A:C,3,0) -> Mr. RAJSHEKHAR ANDODGI | AK36: =AJ36=B36 -> TRUE
A37: 10 | B37: Mr. ANIL KUMAR RAWAT | C37: 101241926666 | F37: 956 | G37: 873 | H37: 856 | L37: 830 | M37: 946 | N37: 921 | P37: 858 | Q37: 834 | R37: 815 | T37: 677 | U37: 1019 | V37: 800 | W37: 1003 | X37: =406+803 -> 1209 | Y37: 617 | AA37: 842 | AB37: 731 | AC37: 650 | AD37: 901 | AE37: 806 | AH37: =SUM(D37:AG37) -> 17144 | AI37: =COUNT(D37:AG37)+1 -> 21 | AJ37: =VLOOKUP(C37,'Name Details'!A:C,3,0) -> Mr. ANIL KUMAR RAWAT | AK37: =AJ37=B37 -> TRUE
A38: 11 | B38: Mr. MANGESH NAVNATH ANKUSHRAO | C38: 101084612898 | F38: 956 | G38: 873 | H38: 811 | I38: 1030 | J38: 951 | S38: 1038 | T38: 811 | U38: 956 | V38: 1026 | W38: 900 | X38: 1065 | AH38: =SUM(D38:AG38) -> 10417 | AI38: =COUNT(D38:AG38) -> 11 | AJ38: =VLOOKUP(C38,'Name Details'!A:C,3,0) -> Mr. MANGESH NAVNATH ANKUSHRAO | AK38: =AJ38=B38 -> TRUE
A39: 12 | B39: Mr. PUNDALIK CHANDU JADHAV | C39: 101486099649 | E39: 750 | J39: 951 | M39: 1140 | P39: 686 | AA39: 839 | AD39: 950 | AH39: =SUM(D39:AG39) -> 5316 | AI39: =COUNT(D39:AG39) -> 6 | AJ39: =VLOOKUP(C39,'Name Details'!A:C,3,0) -> Mr. PUNDALIK CHANDU JADHAV | AK39: =AJ39=B39 -> TRUE
D40: =SUM(D2:D39) -> 550 | E40: =SUM(E2:E39) -> 19435 | F40: =SUM(F2:F39) -> 23603 | G40: =SUM(G2:G39) -> 25347 | H40: =SUM(H2:H39) -> 22898 | I40: =SUM(I2:I39) -> 25713 | J40: =SUM(J2:J39) -> 22427 | K40: =SUM(K2:K39) -> 1100 | ... AI40: =SUM(AI2:AI39) -> 675

Sheet REWORK
A1: 46113 | H1: FIRE WALL STATION REWORK TEAM
B3: 1) GHANTE SACHIN BHAGWAN | H3: 2) SAGAR BASVRAJ ARJUN | N3: 3) MUSTAK RASHID SHAIKH | T3: 4) CHOUGULE HRUSHIKESH CHANDRAKANT
B4: DATE | C4: QTY | D4: RATE | E4: AMOUNT | F4: PRESENTY | H4: DATE | I4: QTY | J4: RATE | K4: AMOUNT | L4: PRESENTY | N4: DATE | O4: QTY | P4: RATE | Q4: AMOUNT | R4: PRESENTY | T4: DATE | U4: QTY | V4: RATE | W4: AMOUNT | X4: PRESENTY
B5: 46113 | D5: 2.45 | E5: =C5*D5 -> 0 | F5: 550 | H5: 46113 | I5: 0 | J5: 2.45 | K5: =I5*J5 -> 0 | N5: 46113 | P5: 2.45 | Q5: =O5*P5 -> 0 | T5: 46113 | U5: 0 | V5: 2.45 | W5: =U5*V5 -> 0
B6: 46114 | D6: 2.45 | E6: =C6*D6 -> 0 | F6: 550 | H6: 46114 | I6: 0 | J6: 2.45 | K6: =I6*J6 -> 0 | N6: 46114 | P6: 2.45 | Q6: =O6*P6 -> 0 | T6: 46114 | U6: 0 | V6: 2.45 | W6: =U6*V6 -> 0
B7: 46115 | D7: 2.45 | E7: =C7*D7 -> 0 | F7: 550 | H7: 46115 | I7: 0 | J7: 2.45 | K7: =I7*J7 -> 0 | N7: 46115 | P7: 2.45 | Q7: =O7*P7 -> 0 | T7: 46115 | V7: 2.45 | W7: =U7*V7 -> 0 | X7: 550
B8: 46116 | D8: 2.45 | E8: =C8*D8 -> 0 | F8: 550 | H8: 46116 | I8: 0 | J8: 2.45 | K8: =I8*J8 -> 0 | N8: 46116 | P8: 2.45 | Q8: =O8*P8 -> 0 | T8: 46116 | V8: 2.45 | W8: =U8*V8 -> 0 | X8: 550
B9: 46117 | D9: 2.45 | E9: =C9*D9 -> 0 | F9: 550 | H9: 46117 | I9: 0 | J9: 2.45 | K9: =I9*J9 -> 0 | N9: 46117 | P9: 2.45 | Q9: =O9*P9 -> 0 | T9: 46117 | U9: 310 | V9: 2.45 | W9: =U9*V9 -> 759.5
B10: 46118 | D10: 2.45 | E10: =C10*D10 -> 0 | F10: 550 | H10: 46118 | I10: 0 | J10: 2.45 | K10: =I10*J10 -> 0 | N10: 46118 | P10: 2.45 | Q10: =O10*P10 -> 0 | T10: 46118 | U10: 286 | V10: 2.45 | W10: =U10*V10 -> 700.7
B11: 46119 | D11: 2.45 | E11: =C11*D11 -> 0 | F11: 550 | H11: 46119 | I11: 0 | J11: 2.45 | K11: =I11*J11 -> 0 | N11: 46119 | P11: 2.45 | Q11: =O11*P11 -> 0 | T11: 46119 | U11: 286 | V11: 2.45 | W11: =U11*V11 -> 700.7
B12: 46120 | C12: 0 | D12: 2.45 | E12: =C12*D12 -> 0 | H12: 46120 | I12: 0 | J12: 2.45 | K12: =I12*J12 -> 0 | N12: 46120 | P12: 2.45 | Q12: =O12*P12 -> 0 | T12: 46120 | V12: 2.45 | W12: =U12*V12 -> 0 | X12: 550
B13: 46121 | C13: 299 | D13: 2.45 | E13: =C13*D13 -> 732.55 | H13: 46121 | I13: 0 | J13: 2.45 | K13: =I13*J13 -> 0 | N13: 46121 | P13: 2.45 | Q13: =O13*P13 -> 0 | T13: 46121 | V13: 2.45 | W13: =U13*V13 -> 0 | X13: 550
B14: 46122 | C14: 280 | D14: 2.45 | E14: =C14*D14 -> 686 | H14: 46122 | I14: 0 | J14: 2.45 | K14: =I14*J14 -> 0 | N14: 46122 | P14: 2.45 | Q14: =O14*P14 -> 0 | T14: 46122 | V14: 2.45 | W14: =U14*V14 -> 0 | X14: 550
B15: 46123 | C15: 295 | D15: 2.45 | E15: =C15*D15 -> 722.75 | H15: 46123 | I15: 0 | J15: 2.45 | K15: =I15*J15 -> 0 | N15: 46123 | P15: 2.45 | Q15: =O15*P15 -> 0 | T15: 46123 | U15: 0 | V15: 2.45 | W15: =U15*V15 -> 0
B16: 46124 | C16: 316 | D16: 2.45 | E16: =C16*D16 -> 774.2 | F16: 550 | H16: 46124 | I16: 0 | J16: 2.45 | K16: =I16*J16 -> 0 | N16: 46124 | P16: 2.45 | Q16: =O16*P16 -> 0 | T16: 46124 | U16: 274 | V16: 2.45 | W16: =U16*V16 -> 671.3
B17: 46125 | C17: 286 | D17: 2.45 | E17: =C17*D17 -> 700.7 | H17: 46125 | I17: 0 | J17: 2.45 | K17: =I17*J17 -> 0 | N17: 46125 | P17: 2.45 | Q17: =O17*P17 -> 0 | T17: 46125 | U17: 0 | V17: 2.45 | W17: =U17*V17 -> 0
B18: 46126 | C18: 275 | D18: 2.45 | E18: =C18*D18 -> 673.75 | H18: 46126 | I18: 0 | J18: 2.45 | K18: =I18*J18 -> 0 | N18: 46126 | P18: 2.45 | Q18: =O18*P18 -> 0 | T18: 46126 | U18: 0 | V18: 2.45 | W18: =U18*V18 -> 0
B19: 46127 | C19: 0 | D19: 2.45 | E19: =C19*D19 -> 0 | H19: 46127 | I19: 0 | J19: 2.45 | K19: =I19*J19 -> 0 | N19: 46127 | P19: 2.45 | Q19: =O19*P19 -> 0 | T19: 46127 | V19: 2.45 | W19: =U19*V19 -> 0 | X19: 550
B20: 46128 | C20: 289 | D20: 2.45 | E20: =C20*D20 -> 708.05 | H20: 46128 | I20: 0 | J20: 2.45 | K20: =I20*J20 -> 0 | N20: 46128 | P20: 2.45 | Q20: =O20*P20 -> 0 | T20: 46128 | U20: 0 | V20: 2.45 | W20: =U20*V20 -> 0
B21: 46129 | C21: 305 | D21: 2.45 | E21: =C21*D21 -> 747.25 | H21: 46129 | I21: 0 | J21: 2.45 | K21: =I21*J21 -> 0 | N21: 46129 | P21: 2.45 | Q21: =O21*P21 -> 0 | T21: 46129 | U21: 273 | V21: 2.45 | W21: =U21*V21 -> 668.85
B22: 46130 | C22: 297 | D22: 2.45 | E22: =C22*D22 -> 727.65 | H22: 46130 | I22: 0 | J22: 2.45 | K22: =I22*J22 -> 0 | N22: 46130 | P22: 2.45 | Q22: =O22*P22 -> 0 | T22: 46130 | U22: 297 | V22: 2.45 | W22: =U22*V22 -> 727.65
B23: 46131 | C23: 277 | D23: 2.45 | E23: =C23*D23 -> 678.65 | H23: 46131 | I23: 0 | J23: 2.45 | K23: =I23*J23 -> 0 | N23: 46131 | P23: 2.45 | Q23: =O23*P23 -> 0 | T23: 46131 | V23: 2.45 | W23: =U23*V23 -> 0 | X23: 550
B24: 46132 | C24: 301 | D24: 2.45 | E24: =C24*D24 -> 737.45 | H24: 46132 | I24: 0 | J24: 2.45 | K24: =I24*J24 -> 0 | N24: 46132 | P24: 2.45 | Q24: =O24*P24 -> 0 | T24: 46132 | V24: 2.45 | W24: =U24*V24 -> 0 | X24: 550
B25: 46133 | C25: 279 | D25: 2.45 | E25: =C25*D25 -> 683.55 | H25: 46133 | I25: 0 | J25: 2.45 | K25: =I25*J25 -> 0 | N25: 46133 | P25: 2.45 | Q25: =O25*P25 -> 0 | T25: 46133 | U25: 264 | V25: 2.45 | W25: =U25*V25 -> 646.8
B26: 46134 | C26: 0 | D26: 2.45 | E26: =C26*D26 -> 0 | H26: 46134 | I26: 0 | J26: 2.45 | K26: =I26*J26 -> 0 | N26: 46134 | P26: 2.45 | Q26: =O26*P26 -> 0 | T26: 46134 | V26: 2.45 | W26: =U26*V26 -> 0 | X26: 550
B27: 46135 | D27: 2.45 | E27: =C27*D27 -> 0 | F27: 550 | H27: 46135 | I27: 0 | J27: 2.45 | K27: =I27*J27 -> 0 | N27: 46135 | P27: 2.45 | Q27: =O27*P27 -> 0 | T27: 46135 | V27: 2.45 | W27: =U27*V27 -> 0 | X27: 550
B28: 46136 | D28: 2.45 | E28: =C28*D28 -> 0 | F28: 550 | H28: 46136 | I28: 0 | J28: 2.45 | K28: =I28*J28 -> 0 | N28: 46136 | P28: 2.45 | Q28: =O28*P28 -> 0 | T28: 46136 | U28: 312 | V28: 2.45 | W28: =U28*V28 -> 764.4
B29: 46137 | D29: 2.45 | E29: =C29*D29 -> 0 | F29: 550 | H29: 46137 | I29: 0 | J29: 2.45 | K29: =I29*J29 -> 0 | N29: 46137 | P29: 2.45 | Q29: =O29*P29 -> 0 | T29: 46137 | U29: 242 | V29: 2.45 | W29: =U29*V29 -> 592.9
B30: 46138 | D30: 2.45 | E30: =C30*D30 -> 0 | F30: 550 | H30: 46138 | I30: 0 | J30: 2.45 | K30: =I30*J30 -> 0 | N30: 46138 | P30: 2.45 | Q30: =O30*P30 -> 0 | T30: 46138 | V30: 2.45 | W30: =U30*V30 -> 0 | X30: 550
B31: 46139 | D31: 2.45 | E31: =C31*D31 -> 0 | F31: 550 | H31: 46139 | I31: 0 | J31: 2.45 | K31: =I31*J31 -> 0 | N31: 46139 | P31: 2.45 | Q31: =O31*P31 -> 0 | T31: 46139 | V31: 2.45 | W31: =U31*V31 -> 0 | X31: 550
B32: 46140 | D32: 2.45 | E32: =C32*D32 -> 0 | F32: 550 | H32: 46140 | I32: 0 | J32: 2.45 | K32: =I32*J32 -> 0 | N32: 46140 | P32: 2.45 | Q32: =O32*P32 -> 0 | T32: 46140 | V32: 2.45 | W32: =U32*V32 -> 0
B33: 46141 | D33: 2.45 | E33: =C33*D33 -> 0 | F33: 550 | H33: 46141 | I33: 0 | J33: 2.45 | K33: =I33*J33 -> 0 | N33: 46141 | P33: 2.45 | Q33: =O33*P33 -> 0 | T33: 46141 | V33: 2.45 | W33: =U33*V33 -> 0 | X33: 550
B34: 46142 | D34: 2.45 | E34: =C34*D34 -> 0 | F34: 550 | H34: 46142 | I34: 0 | J34: 2.45 | K34: =I34*J34 -> 0 | N34: 46142 | P34: 2.45 | Q34: =O34*P34 -> 0 | T34: 46142 | U34: 221 | V34: 2.45 | W34: =U34*V34 -> 541.45
D35: 2.45 | E35: =C35*D35 -> 0 | J35: 2.45 | K35: =I35*J35 -> 0 | P35: 2.45 | Q35: =O35*P35 -> 0 | T35: 46112 | V35: 2.45 | W35: =U35*V35 -> 0
B36: TOTAL | C36: =SUM(C5:C35) -> 3499 | E36: =SUM(E5:E35) -> 8572.55 | F36: =SUM(F5:F35) -> 8800 | H36: TOTAL | I36: =SUM(I5:I35) -> 0 | K36: =SUM(K5:K35) -> 0 | L36: =SUM(L5:L35) -> 0 | N36: TOTAL | O36: =SUM(O5:O35) -> 0 | Q36: =SUM(Q5:Q35) -> 0 | R36: =SUM(R5:R35) -> 0 | T36: TOTAL | U36: =SUM(U5:U35) -> 2765 | W36: =SUM(W5:W35) -> 6774.25 | X36: =SUM(X5:X35) -> 7150
E37: =E36+F36 -> 17372.55 | K37: =K36+L36 -> 0 | R37: =Q36+R36 -> 0 | X37: =W36+X36 -> 13924.25
B38: 5) SOHEL SAHEBLAL JAMADAR | H38: 6)ARBAJ AMIN JAMADAR
B39: DATE | C39: QTY | D39: RATE | E39: AMOUNT | F39: PRESENTY | H39: DATE | I39: QTY | J39: RATE | K39: AMOUNT
B40: 46113 | C40: 0 | D40: 2.45 | E40: =C40*D40 -> 0 | H40: 46113 | I40: 0 | J40: 2.45 | K40: =I40*J40 -> 0
B41: 46114 | C41: 227 | D41: 2.45 | E41: =C41*D41 -> 556.15 | H41: 46114 | I41: 277 | J41: 2.45 | K41: =I41*J41 -> 678.65
B42: 46115 | D42: 2.45 | E42: =C42*D42 -> 0 | F42: 550 | H42: 46115 | I42: 243 | J42: 2.45 | K42: =I42*J42 -> 595.35
B43: 46116 | C43: 250 | D43: 2.45 | E43: =C43*D43 -> 612.5 | H43: 46116 | I43: 255 | J43: 2.45 | K43: =I43*J43 -> 624.75
B44: 46117 | C44: 275 | D44: 2.45 | E44: =C44*D44 -> 673.75 | H44: 46117 | I44: 320 | J44: 2.45 | K44: =I44*J44 -> 784
B45: 46118 | D45: 2.45 | E45: =C45*D45 -> 0 | F45: 550 | H45: 46118 | I45: 295 | J45: 2.45 | K45: =I45*J45 -> 722.75
B46: 46119 | C46: 274 | D46: 2.45 | E46: =C46*D46 -> 671.3 | H46: 46119 | I46: 332 | J46: 2.45 | K46: =I46*J46 -> 813.4
B47: 46120 | C47: 0 | D47: 2.45 | E47: =C47*D47 -> 0 | H47: 46120 | J47: 2.45 | K47: =I47*J47 -> 0 | L47: 550
B48: 46121 | D48: 2.45 | E48: =C48*D48 -> 0 | F48: 550 | H48: 46121 | J48: 2.45 | K48: =I48*J48 -> 0 | L48: 550
B49: 46122 | C49: 316 | D49: 2.45 | E49: =C49*D49 -> 774.2 | H49: 46122 | I49: 0 | J49: 2.45 | K49: =I49*J49 -> 0
B50: 46123 | C50: 268 | D50: 2.45 | E50: =C50*D50 -> 656.6 | H50: 46123 | I50: 0 | J50: 2.45 | K50: =I50*J50 -> 0
B51: 46124 | C51: 274 | D51: 2.45 | E51: =C51*D51 -> 671.3 | H51: 46124 | I51: 0 | J51: 2.45 | K51: =I51*J51 -> 0
B52: 46125 | C52: 251 | D52: 2.45 | E52: =C52*D52 -> 614.95 | H52: 46125 | I52: 0 | J52: 2.45 | K52: =I52*J52 -> 0
B53: 46126 | C53: 0 | D53: 2.45 | E53: =C53*D53 -> 0 | H53: 46126 | I53: 0 | J53: 2.45 | K53: =I53*J53 -> 0
B54: 46127 | C54: 0 | D54: 2.45 | E54: =C54*D54 -> 0 | H54: 46127 | I54: 0 | J54: 2.45 | K54: =I54*J54 -> 0
B55: 46128 | D55: 2.45 | E55: =C55*D55 -> 0 | F55: 550 | H55: 46128 | I55: 254 | J55: 2.45 | K55: =I55*J55 -> 622.3
B56: 46129 | D56: 2.45 | E56: =C56*D56 -> 0 | F56: 550 | H56: 46129 | J56: 2.45 | K56: =I56*J56 -> 0 | L56: 550
B57: 46130 | D57: 2.45 | E57: =C57*D57 -> 0 | F57: 550 | H57: 46130 | I57: 246 | J57: 2.45 | K57: =I57*J57 -> 602.7
B58: 46131 | D58: 2.45 | E58: =C58*D58 -> 0 | F58: 550 | H58: 46131 | J58: 2.45 | K58: =I58*J58 -> 0 | L58: 550
B59: 46132 | D59: 2.45 | E59: =C59*D59 -> 0 | F59: 550 | H59: 46132 | J59: 2.45 | K59: =I59*J59 -> 0 | L59: 550
B60: 46133 | D60: 2.45 | E60: =C60*D60 -> 0 | F60: 550 | H60: 46133 | I60: 283 | J60: 2.45 | K60: =I60*J60 -> 693.35
B61: 46134 | C61: 0 | D61: 2.45 | E61: =C61*D61 -> 0 | H61: 46134 | J61: 2.45 | K61: =I61*J61 -> 0 | L61: 550
B62: 46135 | C62: 0 | D62: 2.45 | E62: =C62*D62 -> 0 | H62: 46134 | I62: 301 | J62: 2.45 | K62: =I62*J62 -> 737.45
B63: 46136 | C63: 0 | D63: 2.45 | E63: =C63*D63 -> 0 | H63: 46136 | I63: 265 | J63: 2.45 | K63: =I63*J63 -> 649.25
B64: 46137 | C64: 376 | D64: 2.45 | E64: =C64*D64 -> 921.2 | H64: 46137 | I64: 376 | J64: 2.45 | K64: =I64*J64 -> 921.2
B65: 46138 | C65: 306 | D65: 2.45 | E65: =C65*D65 -> 749.7 | H65: 46138 | I65: 306 | J65: 2.45 | K65: =I65*J65 -> 749.7
B66: 46139 | C66: 245 | D66: 2.45 | E66: =C66*D66 -> 600.25 | H66: 46139 | I66: 0 | J66: 2.45 | K66: =I66*J66 -> 0
B67: 46140 | C67: 175 | D67: 2.45 | E67: =C67*D67 -> 428.75 | H67: 46140 | J67: 2.45 | K67: =I67*J67 -> 0 | L67: 550
B68: 46141 | D68: 2.45 | E68: =C68*D68 -> 0 | F68: 550 | H68: 46141 | J68: 2.45 | K68: =I68*J68 -> 0 | L68: 550
B69: 46142 | C69: 135 | D69: 2.45 | E69: =C69*D69 -> 330.75 | H69: 46142 | I69: 254 | J69: 2.45 | K69: =I69*J69 -> 622.3
B70: 46112 | D70: 2.45 | E70: =C70*D70 -> 0 | H70: 46112 | J70: 2.45 | K70: =I70*J70 -> 0
B71: TOTAL | C71: =SUM(C40:C70) -> 3372 | E71: =SUM(E40:E70) -> 8261.4 | F71: =SUM(F40:F70) -> 5500 | H71: TOTAL | I71: =SUM(I40:I70) -> 4007 | K71: =SUM(K40:K70) -> 9817.15 | L71: =SUM(L40:L70) -> 4400
F72: =E71+F71 -> 13761.4 | L72: =K71+L71 -> 14217.15
A74: PAINTER
B75: 1) KHIDGIKAR SHARNAPPA | H75: 2) BHARAT SARADE | N75: 1) NAGNATH SONAVANE
B76: DATE | C76: QTY | D76: RATE | E76: AMOUNT | F76: PRESENTY | H76: DATE | I76: QTY | J76: RATE | K76: AMOUNT | L76: PRESENTY | N76: DATE | O76: QTY | P76: RATE | Q76: AMOUNT | R76: PRESENTY | S76: DATE | T76: QTY | U76: RATE | V76: AMOUNT | W76: PRESENTY
B77: 46113 | D77: 2 | E77: =C77*D77 -> 0 | F77: 575 | H77: 46113 | J77: 2 | K77: =I77*J77 -> 0 | L77: 550 | N77: 46113 | P77: 2 | Q77: =O77*P77 -> 0 | R77: 0 | S77: 46113 | U77: 2 | V77: =T77*U77 -> 0
B78: 46114 | D78: 2 | E78: =C78*D78 -> 0 | F78: 575 | H78: 46114 | J78: 2 | K78: =I78*J78 -> 0 | L78: 550 | N78: 46114 | P78: 2 | Q78: =O78*P78 -> 0 | R78: 550 | S78: 46114 | U78: 2 | V78: =T78*U78 -> 0
B79: 46115 | D79: 2 | E79: =C79*D79 -> 0 | F79: 0 | H79: 46115 | J79: 2 | K79: =I79*J79 -> 0 | L79: 550 | N79: 46115 | P79: 2 | Q79: =O79*P79 -> 0 | R79: 550 | S79: 46115 | U79: 2 | V79: =T79*U79 -> 0
B80: 46116 | D80: 2 | E80: =C80*D80 -> 0 | F80: 575 | H80: 46116 | J80: 2 | K80: =I80*J80 -> 0 | L80: 550 | N80: 46116 | P80: 2 | Q80: =O80*P80 -> 0 | R80: 550 | S80: 46116 | U80: 2 | V80: =T80*U80 -> 0
B81: 46117 | D81: 2 | E81: =C81*D81 -> 0 | F81: 575 | H81: 46117 | J81: 2 | K81: =I81*J81 -> 0 | L81: 550 | N81: 46117 | P81: 2 | Q81: =O81*P81 -> 0 | R81: 550 | S81: 46117 | U81: 2 | V81: =T81*U81 -> 0
B82: 46118 | D82: 2 | E82: =C82*D82 -> 0 | F82: 575 | H82: 46118 | J82: 2 | K82: =I82*J82 -> 0 | L82: 550 | N82: 46118 | P82: 2 | Q82: =O82*P82 -> 0 | S82: 46118 | U82: 2 | V82: =T82*U82 -> 0
B83: 46119 | D83: 2 | E83: =C83*D83 -> 0 | F83: 575 | H83: 46119 | J83: 2 | K83: =I83*J83 -> 0 | L83: 550 | N83: 46119 | P83: 2 | Q83: =O83*P83 -> 0 | R83: 550 | S83: 46119 | U83: 2 | V83: =T83*U83 -> 0
B84: 46120 | C84: 0 | D84: 2 | E84: =C84*D84 -> 0 | F84: 0 | H84: 46120 | J84: 2 | K84: =I84*J84 -> 0 | N84: 46120 | P84: 2 | Q84: =O84*P84 -> 0 | R84: 0 | S84: 46120 | U84: 2 | V84: =T84*U84 -> 0
B85: 46121 | D85: 2 | E85: =C85*D85 -> 0 | F85: 575 | H85: 46121 | J85: 2 | K85: =I85*J85 -> 0 | L85: 550 | N85: 46121 | P85: 2 | Q85: =O85*P85 -> 0 | R85: 550 | S85: 46121 | U85: 2 | V85: =T85*U85 -> 0
B86: 46122 | C86: 351 | D86: 2 | E86: =C86*D86 -> 702 | H86: 46122 | I86: 351 | J86: 2 | K86: =I86*J86 -> 702 | L86: 550 | N86: 46122 | O86: 351 | P86: 2 | Q86: =O86*P86 -> 702 | R86: 550 | S86: 46122 | U86: 2 | V86: =T86*U86 -> 0
B87: 46123 | C87: 351 | D87: 2 | E87: =C87*D87 -> 702 | H87: 46123 | I87: 351 | J87: 2 | K87: =I87*J87 -> 702 | N87: 46123 | O87: 351 | P87: 2 | Q87: =O87*P87 -> 702 | S87: 46123 | U87: 2 | V87: =T87*U87 -> 0
B88: 46124 | C88: 300 | D88: 2 | E88: =C88*D88 -> 600 | H88: 46124 | I88: 300 | J88: 2 | K88: =I88*J88 -> 600 | L88: 550 | N88: 46124 | O88: 300 | P88: 2 | Q88: =O88*P88 -> 600 | S88: 46124 | U88: 2 | V88: =T88*U88 -> 0
B89: 46125 | C89: 311 | D89: 2 | E89: =C89*D89 -> 622 | H89: 46125 | I89: 311 | J89: 2 | K89: =I89*J89 -> 622 | N89: 46125 | O89: 311 | P89: 2 | Q89: =O89*P89 -> 622 | R89: 550 | S89: 46125 | U89: 2 | V89: =T89*U89 -> 0
B90: 46126 | C90: 355 | D90: 2 | E90: =C90*D90 -> 710 | H90: 46126 | I90: 355 | J90: 2 | K90: =I90*J90 -> 710 | N90: 46126 | O90: 355 | P90: 2 | Q90: =O90*P90 -> 710 | S90: 46126 | U90: 2 | V90: =T90*U90 -> 0
B91: 46127 | C91: 0 | D91: 2 | E91: =C91*D91 -> 0 | F91: 0 | H91: 46127 | I91: 0 | J91: 2 | K91: =I91*J91 -> 0 | L91: 550 | N91: 46127 | O91: 0 | P91: 2 | Q91: =O91*P91 -> 0 | R91: 550 | S91: 46127 | U91: 2 | V91: =T91*U91 -> 0
B92: 46128 | D92: 2 | E92: =C92*D92 -> 0 | F92: 575 | H92: 46128 | J92: 2 | K92: =I92*J92 -> 0 | L92: 550 | N92: 46128 | P92: 2 | Q92: =O92*P92 -> 0 | R92: 550 | S92: 46128 | U92: 2 | V92: =T92*U92 -> 0
B93: 46129 | C93: 308 | D93: 2 | E93: =C93*D93 -> 616 | H93: 46129 | I93: 308 | J93: 2 | K93: =I93*J93 -> 616 | N93: 46129 | O93: 308 | P93: 2 | Q93: =O93*P93 -> 616 | S93: 46129 | U93: 2 | V93: =T93*U93 -> 0
B94: 46130 | C94: 340 | D94: 2 | E94: =C94*D94 -> 680 | H94: 46130 | I94: 340 | J94: 2 | K94: =I94*J94 -> 680 | N94: 46130 | O94: 340 | P94: 2 | Q94: =O94*P94 -> 680 | S94: 46130 | U94: 2 | V94: =T94*U94 -> 0
B95: 46131 | D95: 2 | E95: =C95*D95 -> 0 | F95: 575 | H95: 46131 | J95: 2 | K95: =I95*J95 -> 0 | L95: 550 | N95: 46131 | P95: 2 | Q95: =O95*P95 -> 0 | R95: 550 | S95: 46131 | U95: 2 | V95: =T95*U95 -> 0
B96: 46132 | D96: 2 | E96: =C96*D96 -> 0 | F96: 575 | H96: 46132 | J96: 2 | K96: =I96*J96 -> 0 | L96: 550 | N96: 46132 | P96: 2 | Q96: =O96*P96 -> 0 | R96: 550 | S96: 46132 | U96: 2 | V96: =T96*U96 -> 0
B97: 46133 | C97: 351 | D97: 2 | E97: =C97*D97 -> 702 | H97: 46133 | I97: 351 | J97: 2 | K97: =I97*J97 -> 702 | N97: 46133 | O97: 351 | P97: 2 | Q97: =O97*P97 -> 702 | S97: 46133 | U97: 2 | V97: =T97*U97 -> 0
B98: 46134 | D98: 2 | E98: =C98*D98 -> 0 | F98: 0 | H98: 46134 | I98: 0 | J98: 2 | K98: =I98*J98 -> 0 | N98: 46134 | P98: 2 | Q98: =O98*P98 -> 0 | R98: 0 | S98: 46134 | U98: 2 | V98: =T98*U98 -> 0
B99: 46135 | D99: 2 | E99: =C99*D99 -> 0 | F99: 575 | H99: 46135 | I99: 0 | J99: 2 | K99: =I99*J99 -> 0 | N99: 46135 | P99: 2 | Q99: =O99*P99 -> 0 | R99: 550 | S99: 46135 | U99: 2 | V99: =T99*U99 -> 0
B100: 46136 | D100: 2 | E100: =C100*D100 -> 0 | F100: 575 | H100: 46136 | J100: 2 | K100: =I100*J100 -> 0 | L100: 550 | N100: 46136 | P100: 2 | Q100: =O100*P100 -> 0 | R100: 550 | S100: 46136 | U100: 2 | V100: =T100*U100 -> 0
B101: 46137 | D101: 2 | E101: =C101*D101 -> 0 | F101: 575 | H101: 46137 | J101: 2 | K101: =I101*J101 -> 0 | L101: 550 | N101: 46137 | O101: 341 | P101: 2 | Q101: =O101*P101 -> 682 | S101: 46137 | U101: 2 | V101: =T101*U101 -> 0
B102: 46138 | D102: 2 | E102: =C102*D102 -> 0 | F102: 575 | H102: 46138 | J102: 2 | K102: =I102*J102 -> 0 | L102: 550 | N102: 46138 | P102: 2 | Q102: =O102*P102 -> 0 | R102: 550 | S102: 46138 | U102: 2 | V102: =T102*U102 -> 0
...

Sheet Google attandance April -26
A1: 46113
A2: Sr No | B2: Panching No. | C2: UNA No. | D2: Emp Name | F2: 1 | G2: 2 | H2: 3 | I2: 4 | J2: 5 | K2: 6 | L2: 7 | M2: 8 | N2: 9 | O2: 10 | P2: 11 | Q2: 12 | R2: 13 | S2: 14 | T2: 15 | U2: 16 | V2: 17 | W2: 18 | X2: 19 | Y2: 20 | Z2: 21 | AA2: 22 | AB2: 23 | AC2: 24 | AD2: 25 | AE2: 26 | AF2: 27 | AG2: 28 | AH2: 29 | AI2: 30 | AJ2: Total
A3: 1 | B3: FOU29 | C3: 101540070377 | D3: SANTOSH LAXMAN KOLI | E3: AVG | T3: 1 | U3: 1 | V3: 1 | W3: 1 | X3: 1 | Y3: 1 | Z3: 1 | AA3: 1 | AB3: 1 | AC3: 1 | AD3: 2 | AE3: 2 | AF3: 1 | AG3: 1 | AH3: 1 | AI3: 1 | AJ3: =SUM(F3:AI3) -> 18 | AK3: =VLOOKUP(C3,'Name Details'!A:C,3,0) -> Mr. SANTOSH LAXMAN KOLI | AL3: =VLOOKUP(B3,'[2]APRIL-2026'!$B$1:$J$65536,9,0) -> #N/A | AN3: =VLOOKUP(C3,Work!D:F,3,0) -> Mr. SANTOSH LAXMAN KOLI | AO3: =AN3=AK3 -> TRUE | AP3: FOU29
A4: 2 | B4: FOU28 | C4: 101424675655 | D4: VIJAY VISHNU MANE | E4: AVG | F4: 1 | G4: 1 | H4: 1 | I4: 1 | J4: 1 | L4: 1 | N4: 1 | O4: 1 | P4: 1 | Q4: 1 | R4: 1 | S4: 1 | U4: 1 | V4: 1 | W4: 1 | X4: 1 | Y4: 1 | Z4: 1 | AB4: 1 | AC4: 1 | AD4: 1 | AE4: 1 | AF4: 1 | AG4: 1 | AH4: 1 | AI4: 1 | AJ4: =SUM(F4:AI4) -> 26 | AK4: =VLOOKUP(C4,'Name Details'!A:C,3,0) -> Mr. VIJAY MANE | AL4: =VLOOKUP(B4,'[2]APRIL-2026'!$B$1:$J$65536,9,0) -> 487.18 | AM4: 487.18 | AN4: =VLOOKUP(C4,Work!D:F,3,0) -> Mr. VIJAY MANE | AO4: =AN4=AK4 -> TRUE | AP4: FOU28
A5: 3 | B5: FOU277 | C5: 102090872186 | D5: MAHESH BABUSHA LANDAGE | E5: AVG | F5: 1 | G5: 1 | H5: 1 | I5: 1 | J5: 1 | N5: 1 | O5: 1 | P5: 1 | Q5: 1 | R5: 1 | S5: 1 | T5: 1 | U5: 1 | V5: 1 | W5: 1 | X5: 1 | Y5: 1 | Z5: 1 | AA5: 1 | AB5: 1 | AC5: 1 | AD5: 1 | AF5: 1 | AG5: 1 | AH5: 1 | AJ5: =SUM(F5:AI5) -> 25 | AK5: =VLOOKUP(C5,'Name Details'!A:C,3,0) -> Mr. MAHESH BABUSHA LANDAGE | AL5: =VLOOKUP(B5,'[2]APRIL-2026'!$B$1:$J$65536,9,0) -> 391.26 | AM5: 391.26 | AN5: =VLOOKUP(C5,Work!D:F,3,0) -> Mr. MAHESH BABUSHA LANDAGE | AO5: =AN5=AK5 -> TRUE | AP5: FOU277
A6: 4 | B6: FOU367 | C6: 101960331774 | D6: SAMARTH IRRANA DHAVANE | E6: AVG | F6: 1 | G6: 1 | H6: 1 | I6: 1 | J6: 1 | K6: 1 | L6: 1 | N6: 1 | O6: 1 | P6: 1 | Q6: 1 | R6: 1 | S6: 1 | T6: 1.5 | U6: 1 | V6: 1 | W6: 1 | X6: 1 | Y6: 1 | Z6: 1 | AB6: 1 | AC6: 1 | AG6: 1 | AH6: 1 | AI6: 1 | AJ6: =SUM(F6:AI6) -> 25.5 | AK6: =VLOOKUP(C6,'Name Details'!A:C,3,0) -> Mr. SAMARTH IRANNA DHAVANE | AL6: =VLOOKUP(B6,'[2]APRIL-2026'!$B$1:$J$65536,9,0) -> 154.24 | AM6: 154.24 | AN6: =VLOOKUP(C6,Work!D:F,3,0) -> Mr. SAMARTH IRANNA DHAVANE | AO6: =AN6=AK6 -> TRUE | AP6: FOU367
A7: 5 | B7: FOU703 | C7: 102267132379 | D7: VISHAL RAJKUMAR KOLI | E7: AVG | F7: 1 | H7: 1 | I7: 1 | J7: 1 | K7: 1 | L7: 1 | O7: 1 | P7: 1 | Q7: 1 | R7: 1 | S7: 1 | U7: 1 | V7: 1 | W7: 1 | X7: 1 | Y7: 1 | Z7: 1 | AB7: 1 | AC7: 1 | AD7: 1 | AE7: 1 | AF7: 1 | AG7: 1 | AI7: 0.5 | AJ7: =SUM(F7:AI7) -> 23.5 | AK7: =VLOOKUP(C7,'Name Details'!A:C,3,0) -> Mr. VISHAL RAJKUMAR KOLI | AL7: =VLOOKUP(B7,'[2]APRIL-2026'!$B$1:$J$65536,9,0) -> 448.66 | AM7: 448.66 | AN7: =VLOOKUP(C7,Work!D:F,3,0) -> Mr. VISHAL RAJKUMAR KOLI | AO7: =AN7=AK7 -> TRUE | AP7: FOU703
A8: 6 | B8: FOU79 | C8: 101281737627 | D8: AVINASH PATANGE | E8: AVG | J8: 1 | K8: 1 | L8: 1 | M8: 1 | N8: 1 | O8: 1 | P8: 1 | Q8: 1 | S8: 1 | X8: 1 | Y8: 1 | Z8: 1 | AB8: 1 | AD8: 1 | AE8: 1 | AF8: 1 | AJ8: =SUM(F8:AI8) -> 16 | AK8: =VLOOKUP(C8,'Name Details'!A:C,3,0) -> Mr. AVINASH NILKANTH PATANGE | AL8: =VLOOKUP(B8,'[2]APRIL-2026'!$B$1:$J$65536,9,0) -> 146.71 | AM8: 146.71 | AN8: =VLOOKUP(C8,Work!D:F,3,0) -> Mr. AVINASH NILKANTH PATANGE | AO8: =AN8=AK8 -> TRUE | AP8: FOU79
A9: 7 | B9: 0 | C9: SAMARTH MANJUNATH SIRSAT | D9: SAMARTH MANJUNATH SIRSAT | E9: AVG | G9: 1 | H9: 1 | I9: 1 | J9: 1 | K9: 1 | L9: 1 | O9: 1 | P9: 1 | Q9: 1 | T9: 1 | U9: 2 | V9: 1 | W9: 1 | Y9: 1 | Z9: 1 | AB9: 1 | AC9: 1 | AD9: 1 | AE9: 1 | AF9: 1 | AH9: 1 | AJ9: =SUM(F9:AI9) -> 22 | AK9: =VLOOKUP(C9,'Name Details'!A:C,3,0) -> #N/A | AL9: =VLOOKUP(B9,'[2]APRIL-2026'!$B$1:$J$65536,9,0) -> #N/A | AN9: =VLOOKUP(C9,Work!D:F,3,0) -> SAMARTH MANJUNATH SIRSAT | AO9: =AN9=AK9 -> #N/A | AP9: 0
A10: 8 | B10: FOU850 | C10: TURBE PARSHURAM MARUTI | D10: TURBE PARSHURAM MARUTI | E10: AVG | G10: 1 | H10: 1 | I10: 1 | J10: 1 | K10: 1 | L10: 1 | N10: 1 | O10: 1 | R10: 1 | S10: 1 | U10: 1 | AD10: 1 | AE10: 1 | AF10: 1 | AG10: 1 | AI10: 1 | AJ10: =SUM(F10:AI10) -> 16 | AK10: =VLOOKUP(C10,'Name Details'!A:C,3,0) -> #N/A | AL10: =VLOOKUP(B10,'[2]APRIL-2026'!$B$1:$J$65536,9,0) -> 337.15 | AM10: 337.15 | AN10: =VLOOKUP(C10,Work!D:F,3,0) -> TURBE PARSHURAM MARUTI | AO10: =AN10=AK10 -> #N/A | AP10: FOU850
A11: 9 | B11: FOU328 | C11: 101623086404 | D11: BANDENAVAJ MULLA | E11: AVG | H11: 1 | I11: 1 | J11: 1 | K11: 1 | L11: 1 | N11: 1 | P11: 1 | Q11: 1 | R11: 1 | S11: 1 | U11: 1 | V11: 1 | W11: 1 | X11: 1 | Y11: 1 | Z11: 1 | AB11: 1 | AC11: 1 | AD11: 1 | AE11: 1 | AF11: 1 | AG11: 1 | AH11: 1 | AI11: 1 | AJ11: =SUM(F11:AI11) -> 24 | AK11: =VLOOKUP(C11,'Name Details'!A:C,3,0) -> Mr. BANDENAWAJ SAIPAN MULLA | AL11: =VLOOKUP(B11,'[2]APRIL-2026'!$B$1:$J$65536,9,0) -> 433.21 | AM11: 433.21 | AN11: =VLOOKUP(C11,Work!D:F,3,0) -> Mr. BANDENAWAJ SAIPAN MULLA | AO11: =AN11=AK11 -> TRUE | AP11: FOU328
A12: 10 | B12: FOU84 | C12: 102028098436 | D12: BASAVARAJ TALWAR | E12: AVG | F12: 1 | G12: 1 | H12: 1 | I12: 1 | J12: 1 | K12: 1 | L12: 1 | M12: 1 | N12: 1 | O12: 1 | P12: 1 | Q12: 1 | R12: 1 | S12: 1 | T12: 1 | V12: 1 | W12: 1 | X12: 1 | Y12: 1 | Z12: 1 | AA12: 2 | AB12: 1 | AC12: 1 | AD12: 1 | AG12: 1 | AH12: 1 | AI12: 1 | AJ12: =SUM(F12:AI12) -> 28 | AK12: =VLOOKUP(C12,'Name Details'!A:C,3,0) -> Mr. BSAVRAJ IRANNA TALWAR | AL12: =VLOOKUP(B12,'[2]APRIL-2026'!$B$1:$J$65536,9,0) -> 413.8 | AM12: 413.8 | AN12: =VLOOKUP(C12,Work!D:F,3,0) -> Mr. BSAVRAJ IRANNA TALWAR | AO12: =AN12=AK12 -> TRUE | AP12: FOU84
A13: 11 | B13: FOU56 | C13: 101951607402 | D13: DAVALSAB NADAF MATTU | E13: AVG | F13: 1 | G13: 1 | H13: 1 | I13: 1 | J13: 1 | K13: 1 | L13: 1 | M13: 1 | N13: 1 | O13: 1 | P13: 1 | R13: 1 | S13: 1 | T13: 1 | U13: 1 | V13: 1 | W13: 1 | X13: 1 | Y13: 1 | Z13: 1 | AB13: 1 | AC13: 1 | AD13: 1 | AE13: 1 | AF13: 1 | AG13: 1 | AH13: 2 | AI13: 2 | AJ13: =SUM(F13:AI13) -> 30 | AK13: =VLOOKUP(C13,'Name Details'!A:C,3,0) -> Mr. DAVALSAB MATTU NADAF | AL13: =VLOOKUP(B13,'[2]APRIL-2026'!$B$1:$J$65536,9,0) -> 195.63 | AM13: 195.63 | AN13: =VLOOKUP(C13,Work!D:F,3,0) -> Mr. DAVALSAB MATTU NADAF | AO13: =AN13=AK13 -> TRUE | AP13: FOU56
A14: 12 | B14: FOU63 | C14: 101969547233 | D14: HEMANT ANAVIRAPPA NANDURE | E14: AVG | G14: 1 | H14: 1 | I14: 1 | N14: 1 | O14: 1 | P14: 1 | R14: 1 | S14: 1 | U14: 1 | V14: 1 | W14: 1 | X14: 0.5 | Y14: 1 | Z14: 1 | AB14: 1 | AC14: 1 | AD14: 1 | AE14: 1 | AF14: 1 | AG14: 1 | AH14: 1 | AI14: 1 | AJ14: =SUM(F14:AI14) -> 21.5 | AK14: =VLOOKUP(C14,'Name Details'!A:C,3,0) -> Mr. NANDURE HEMANT ANAVIRAPPA | AL14: =VLOOKUP(B14,'[2]APRIL-2026'!$B$1:$J$65536,9,0) -> 236.97 | AM14: 236.97 | AN14: =VLOOKUP(C14,Work!D:F,3,0) -> Mr. NANDURE HEMANT ANAVIRAPPA | AO14: =AN14=AK14 -> TRUE | AP14: FOU63
A15: 13 | B15: FOU90 | C15: 102043325356 | D15: AKIB SHAIKH | E15: AVG | F15: 1 | G15: 1 | I15: 1 | J15: 1 | K15: 1 | L15: 1 | M15: 1 | N15: 1 | O15: 1 | P15: 1 | R15: 1 | S15: 1 | T15: 1 | U15: 1 | V15: 1 | W15: 1 | X15: 1 | Y15: 1 | Z15: 1 | AB15: 1 | AC15: 1 | AD15: 1 | AE15: 1 | AF15: 1 | AG15: 1 | AH15: 1 | AI15: 1 | AJ15: =SUM(F15:AI15) -> 27 | AK15: =VLOOKUP(C15,'Name Details'!A:C,3,0) -> Mr. AKIB SHAIKH | AL15: =VLOOKUP(B15,'[2]APRIL-2026'!$B$1:$J$65536,9,0) -> 165.51 | AM15: 165.51 | AN15: =VLOOKUP(C15,Work!D:F,3,0) -> Mr. AKIB SHAIKH | AO15: =AN15=AK15 -> TRUE | AP15: FOU90
A16: 14 | B16: FOU625 | C16: 101958132802 | D16: IRANNA IDDHARAM KANNI | E16: AVG | G16: 1 | H16: 1 | I16: 1 | J16: 1 | K16: 1 | L16: 1 | N16: 1 | O16: 1 | P16: 1 | Q16: 1 | R16: 1 | S16: 1 | U16: 1 | V16: 1 | W16: 1 | Y16: 1 | Z16: 1 | AC16: 1 | AD16: 1 | AF16: 1 | AH16: 1 | AI16: 1 | AJ16: =SUM(F16:AI16) -> 22 | AK16: =VLOOKUP(C16,'Name Details'!A:C,3,0) -> Mr. IRANNA SIDDHARAM KANNI | AL16: =VLOOKUP(B16,'[2]APRIL-2026'!$B$1:$J$65536,9,0) -> 183.05 | AM16: 183.05 | AN16: =VLOOKUP(C16,Work!D:F,3,0) -> Mr. IRANNA SIDDHARAM KANNI | AO16: =AN16=AK16 -> TRUE | AP16: FOU625
A17: 15 | B17: FOU75 | C17: SAQIB SAYYAD | D17: SAQIB SAYYAD | E17: AVG | H17: 1 | I17: 1 | J17: 1 | K17: 1 | L17: 1 | M17: 1 | N17: 1 | O17: 1 | P17: 1 | Q17: 1 | R17: 1 | S17: 1 | T17: 1 | U17: 1 | V17: 1 | X17: 1 | Y17: 1 | AB17: 2 | AD17: 2 | AE17: 1 | AF17: 2 | AG17: 0.5 | AH17: 1 | AI17: 1 | AJ17: =SUM(F17:AI17) -> 26.5 | AK17: =VLOOKUP(C17,'Name Details'!A:C,3,0) -> #N/A | AL17: =VLOOKUP(B17,'[2]APRIL-2026'!$B$1:$J$65536,9,0) -> 423.25 | AM17: 423 | AN17: =VLOOKUP(C17,Work!D:F,3,0) -> SAQIB SAYYAD | AO17: =AN17=AK17 -> #N/A | AP17: FOU75
A18: 15 | B18: FOU624 | C18: 102232142117 | D18: AYAN ARIF USTAD | E18: AVG | AJ18: =SUM(F18:AI18) -> 0 | AK18: =VLOOKUP(C18,'Name Details'!A:C,3,0) -> Mr. AYAN ARIF USTAD | AL18: =VLOOKUP(B18,'[2]APRIL-2026'!$B$1:$J$65536,9,0) -> #N/A | AN18: =VLOOKUP(C18,Work!D:F,3,0) -> Mr. AYAN ARIF USTAD | AO18: =AN18=AK18 -> TRUE | AP18: FOU624
A19: 16 | B19: 0 | C19: 101216844424 | D19: HUSEN BABULAL NADAF | E19: AVG | G19: 1 | H19: 1 | I19: 1 | J19: 1 | K19: 1 | L19: 1 | Q19: 1 | R19: 1 | S19: 1 | U19: 1 | V19: 1 | W19: 1 | AB19: 1 | AC19: 1 | AD19: 1 | AJ19: =SUM(F19:AI19) -> 15 | AK19: =VLOOKUP(C19,'Name Details'!A:C,3,0) -> Mr. HUSEN NADAF | AL19: =VLOOKUP(B19,'[2]APRIL-2026'!$B$1:$J$65536,9,0) -> #N/A | AN19: =VLOOKUP(C19,Work!D:F,3,0) -> Mr. HUSEN NADAF | AO19: =AN19=AK19 -> TRUE | AP19: 0
A20: 17 | B20: FOU675 | C20: 102192447029 | D20: PAGA GURURAJ MAHANTESH | E20: AVG | I20: 1 | J20: 1 | K20: 1 | L20: 1 | N20: 1 | O20: 1 | P20: 1 | Q20: 1 | R20: 1 | S20: 1 | T20: 1 | U20: 1 | V20: 1 | W20: 1 | X20: 1 | Y20: 1 | Z20: 1 | AD20: 1 | AE20: 1 | AF20: 1 | AG20: 1 | AH20: 2 | AI20: 1 | AJ20: =SUM(F20:AI20) -> 24 | AK20: =VLOOKUP(C20,'Name Details'!A:C,3,0) -> Mr. GURURAJ MAHANTESH PAGA | AL20: =VLOOKUP(B20,'[2]APRIL-2026'!$B$1:$J$65536,9,0) -> 389.73 | AM20: 389.73 | AN20: =VLOOKUP(C20,Work!D:F,3,0) -> Mr. GURURAJ MAHANTESH PAGA | AO20: =AN20=AK20 -> TRUE | AP20: FOU675
A21: 18 | B21: FOU91 | C21: 102043325341 | D21: SAGAR PATIL | E21: AVG | F21: 1 | G21: 1 | H21: 1 | I21: 1 | J21: 1 | K21: 1 | L21: 1 | N21: 1 | O21: 1 | P21: 1 | Q21: 1 | R21: 1 | S21: 1 | T21: 1 | U21: 1 | V21: 1 | W21: 1 | X21: 1 | Y21: 1 | Z21: 1 | AB21: 1 | AC21: 1 | AD21: 1 | AE21: 1 | AF21: 1 | AG21: 1 | AH21: 1 | AI21: 1 | AJ21: =SUM(F21:AI21) -> 28 | AK21: =VLOOKUP(C21,'Name Details'!A:C,3,0) -> Mr. SAGAR CHANDRASHEKHAR PATIL | AL21: =VLOOKUP(B21,'[2]APRIL-2026'!$B$1:$J$65536,9,0) -> 13.36 | AM21: 13.36 | AN21: =VLOOKUP(C21,Work!D:F,3,0) -> Mr. SAGAR CHANDRASHEKHAR PATIL | AO21: =AN21=AK21 -> TRUE | AP21: FOU91
A22: 19 | B22: FOU61 | C22: 100590315745 | D22: DARGAPPA SHIVANAND ARAVAT | E22: AVG | G22: 1 | H22: 2 | J22: 1 | K22: 1 | L22: 1 | N22: 1 | O22: 1 | P22: 1 | Q22: 1 | R22: 1 | S22: 1 | U22: 1 | V22: 1 | W22: 1 | X22: 1 | Y22: 1 | Z22: 1 | AC22: 1 | AD22: 1 | AE22: 1 | AF22: 1 | AG22: 1 | AH22: 1 | AI22: 1 | AJ22: =SUM(F22:AI22) -> 25 | AK22: =VLOOKUP(C22,'Name Details'!A:C,3,0) -> Mr. DARGAPPA SHIVANAND ARWAT | AL22: =VLOOKUP(B22,'[2]APRIL-2026'!$B$1:$J$65536,9,0) -> 186.79 | AM22: 186.79 | AN22: =VLOOKUP(C22,Work!D:F,3,0) -> Mr. DARGAPPA SHIVANAND ARWAT | AO22: =AN22=AK22 -> TRUE | AP22: FOU61
A23: 20 | B23: FOU21 | C23: 101475240602 | D23: ANIL GOVIND MALI | E23: FINAL | G23: 1 | H23: 1 | I23: 1 | J23: 1 | K23: 1 | L23: 1 | P23: 1 | R23: 1 | S23: 1 | U23: 1 | V23: 1 | W23: 1 | X23: 1 | Y23: 0.5 | Z23: 1 | AD23: 1 | AE23: 1 | AF23: 1 | AG23: 1 | AH23: 1 | AI23: 1 | AJ23: =SUM(F23:AI23) -> 20.5 | AK23: =VLOOKUP(C23,'Name Details'!A:C,3,0) -> Mr. ANIL G MALI | AL23: =VLOOKUP(B23,'[2]APRIL-2026'!$B$1:$J$65536,9,0) -> 84.6 | AM23: 84.6 | AN23: =VLOOKUP(C23,Work!D:F,3,0) -> Mr. ANIL G MALI | AO23: =AN23=AK23 -> TRUE | AP23: FOU21
A24: 21 | B24: FOU23 | C24: 101492178974 | D24: REVANSHDDHA SHIVAPPA ISHWARKATTI | E24: FINAL | F24: 1 | G24: 1 | H24: 1 | I24: 1 | J24: 1 | K24: 1 | L24: 1 | M24: 1 | N24: 1 | O24: 1 | P24: 1 | Q24: 1 | R24: 2 | S24: 1 | T24: 1 | U24: 1 | V24: 1 | W24: 1 | X24: 1 | Y24: 1 | Z24: 1 | AA24: 1 | AB24: 1 | AH24: 1 | AI24: 1 | AJ24: =SUM(F24:AI24) -> 26 | AK24: =VLOOKUP(C24,'Name Details'!A:C,3,0) -> Mr. REVANASIDDH SHIVAPPA ISHWARKATTI | AL24: =VLOOKUP(B24,'[2]APRIL-2026'!$B$1:$J$65536,9,0) -> 138.48 | AM24: 138.48 | AN24: =VLOOKUP(C24,Work!D:F,3,0) -> Mr. REVANASIDDH SHIVAPPA ISHWARKATTI | AO24: =AN24=AK24 -> TRUE | AP24: FOU23
A25: 22 | B25: FOU97 | C25: 102052667942 | D25: DIPAK DATTRAY KUMBHAR | E25: FINAL | G25: 1 | I25: 1 | J25: 1 | K25: 1 | L25: 2 | M25: 1 | N25: 1 | O25: 1 | P25: 1 | Q25: 1 | R25: 1 | S25: 1 | U25: 1 | V25: 1 | W25: 1 | X25: 1 | AB25: 1 | AC25: 1 | AD25: 1 | AE25: 1 | AF25: 2 | AG25: 1 | AI25: 1 | AJ25: =SUM(F25:AI25) -> 25 | AK25: =VLOOKUP(C25,'Name Details'!A:C,3,0) -> Mr. DIPAK DATTATRAY KUMBHAR | AL25: =VLOOKUP(B25,'[2]APRIL-2026'!$B$1:$J$65536,9,0) -> 190.14 | AM25: 190.14 | AN25: =VLOOKUP(C25,Work!D:F,3,0) -> Mr. DIPAK DATTATRAY KUMBHAR | AO25: =AN25=AK25 -> TRUE | AP25: FOU97
A26: 23 | B26: FOU42 | C26: 101826609019 | D26: GIRISH SIDDHRAM MADYAL | E26: FINAL | G26: 1 | H26: 1 | I26: 1 | J26: 1 | K26: 1 | L26: 1 | O26: 1 | P26: 1 | Q26: 1 | R26: 1 | S26: 1 | U26: 1 | V26: 1 | W26: 1 | X26: 1 | Y26: 1 | Z26: 1 | AB26: 1 | AC26: 1 | AD26: 1 | AE26: 1 | AF26: 1 | AG26: 1 | AH26: 1 | AI26: 1 | AJ26: =SUM(F26:AI26) -> 25 | AK26: =VLOOKUP(C26,'Name Details'!A:C,3,0) -> Mr. GIRISH SIDDHARAM MADYAL | AL26: =VLOOKUP(B26,'[2]APRIL-2026'!$B$1:$J$65536,9,0) -> 536.05 | AM26: 536.05 | AN26: =VLOOKUP(C26,Work!D:F,3,0) -> Mr. GIRISH SIDDHARAM MADYAL | AO26: =AN26=AK26 -> TRUE | AP26: FOU42
A27: 24 | B27: FOU82 | C27: 101944505682 | D27: VIJAY BHARALE | E27: FINAL | I27: 1 | J27: 1 | L27: 1 | N27: 1 | O27: 1 | P27: 1 | Q27: 1 | R27: 1 | S27: 1 | U27: 1 | V27: 1 | W27: 1 | X27: 1 | Y27: 1 | AB27: 1 | AC27: 1 | AD27: 1 | AE27: 1 | AF27: 1 | AI27: 1 | AJ27: =SUM(F27:AI27) -> 20 | AK27: =VLOOKUP(C27,'Name Details'!A:C,3,0) -> Mr. VIJAY BHARLE | AL27: =VLOOKUP(B27,'[2]APRIL-2026'!$B$1:$J$65536,9,0) -> 234.57 | AM27: 234.57 | AN27: =VLOOKUP(C27,Work!D:F,3,0) -> Mr. VIJAY BHARLE | AO27: =AN27=AK27 -> TRUE | AP27: FOU82
A28: 25 | B28: FOU43 | C28: 101603294918 | D28: JITENDRA SIDRAM KOLI | E28: FINAL | G28: 1 | H28: 1 | I28: 1 | J28: 1 | K28: 1 | L28: 1 | N28: 1 | O28: 1 | P28: 1 | Q28: 1 | R28: 1 | U28: 1 | V28: 1 | W28: 1 | X28: 1 | Y28: 1 | Z28: 0.5 | AB28: 1 | AC28: 1 | AD28: 1 | AE28: 2 | AG28: 1 | AH28: 1 | AI28: 1 | AJ28: =SUM(F28:AI28) -> 24.5 | AK28: =VLOOKUP(C28,'Name Details'!A:C,3,0) -> Mr. JITENDRA SIDRAM KOLI | AL28: =VLOOKUP(B28,'[2]APRIL-2026'!$B$1:$J$65536,9,0) -> 417.54 | AM28: 417.54 | AN28: =VLOOKUP(C28,Work!D:F,3,0) -> Mr. JITENDRA SIDRAM KOLI | AO28: =AN28=AK28 -> TRUE | AP28: FOU43
A29: 26 | B29: FOU40 | C29: 101818174092 | D29: KASHINATH JAGANATH BIRAJDAR | E29: FINAL | G29: 1 | H29: 1 | I29: 1 | J29: 1 | K29: 1 | L29: 1 | N29: 1 | O29: 1 | P29: 1 | Q29: 1 | R29: 1 | S29: 1 | U29: 1 | V29: 1 | W29: 1 | Y29: 1 | Z29: 1 | AB29: 1 | AC29: 1 | AE29: 1 | AF29: 1 | AG29: 1 | AH29: 1 | AI29: 1 | AJ29: =SUM(F29:AI29) -> 24 | AK29: =VLOOKUP(C29,'Name Details'!A:C,3,0) -> Mr. KASHINATH JAGANATH BIRJADAR | AL29: =VLOOKUP(B29,'[2]APRIL-2026'!$B$1:$J$65536,9,0) -> 203.28 | AM29: 203.28 | AN29: =VLOOKUP(C29,Work!D:F,3,0) -> Mr. KASHINATH JAGANATH BIRJADAR | AO29: =AN29=AK29 -> TRUE | AP29: FOU40
A30: 27 | B30: FOU294 | C30: 102120964651 | D30: KHAWAJASAHAB GULAB HIMONE | E30: FINAL | G30: 1 | H30: 1 | I30: 1 | J30: 1 | K30: 1 | L30: 1 | N30: 1 | O30: 1 | P30: 1 | Q30: 1 | R30: 1 | S30: 1 | U30: 1 | V30: 1 | W30: 1 | X30: 1 | Y30: 1 | Z30: 1 | AB30: 1 | AC30: 1 | AD30: 1 | AE30: 1 | AF30: 1 | AG30: 1 | AH30: 1 | AI30: 1 | AJ30: =SUM(F30:AI30) -> 26 | AK30: =VLOOKUP(C30,'Name Details'!A:C,3,0) -> Mr. KHAJASAHEB GULAB HIMONE | AL30: =VLOOKUP(B30,'[2]APRIL-2026'!$B$1:$J$65536,9,0) -> 225.7 | AM30: 225.7 | AN30: =VLOOKUP(C30,Work!D:F,3,0) -> Mr. KHAJASAHEB GULAB HIMONE | AO30: =AN30=AK30 -> TRUE | AP30: FOU294
A31: 28 | B31: FOU73 | C31: 102004077854 | D31: BHIMASHANKAR SHARANAPPA ISHWARKATTI | E31: FINAL | G31: 1 | H31: 1 | I31: 1 | J31: 1 | K31: 1 | L31: 1 | N31: 1 | O31: 1 | P31: 1 | Q31: 1 | R31: 1 | S31: 1 | U31: 1 | V31: 1 | W31: 1 | X31: 1 | Y31: 1 | Z31: 1 | AB31: 1 | AC31: 1 | AD31: 1 | AE31: 1 | AF31: 1 | AG31: 1 | AH31: 2 | AI31: 1 | AJ31: =SUM(F31:AI31) -> 27 | AK31: =VLOOKUP(C31,'Name Details'!A:C,3,0) -> Mr. BHIMAHSNKAR SHARNAPPA ISHWARKATTI | AL31: =VLOOKUP(B31,'[2]APRIL-2026'!$B$1:$J$65536,9,0) -> 182.83 | AM31: 182.83 | AN31: =VLOOKUP(C31,Work!D:F,3,0) -> Mr. BHIMAHSNKAR SHARNAPPA ISHWARKATTI | AO31: =AN31=AK31 -> TRUE | AP31: FOU73
A32: 29 | B32: FOU218 | C32: 101432431093 | D32: VISHAL SURESH MANE | E32: FINAL | G32: 1 | H32: 1 | I32: 1 | J32: 1 | K32: 1 | L32: 1 | N32: 1 | O32: 1 | P32: 1 | Q32: 1 | R32: 1 | S32: 1 | U32: 1 | V32: 1 | W32: 1 | X32: 1 | AB32: 1 | AC32: 1 | AD32: 1 | AE32: 1 | AF32: 1 | AG32: 1 | AH32: 1 | AI32: 1 | AJ32: =SUM(F32:AI32) -> 24 | AK32: =VLOOKUP(C32,'Name Details'!A:C,3,0) -> Mr. VISHAL SURESH MANE | AL32: =VLOOKUP(B32,'[2]APRIL-2026'!$B$1:$J$65536,9,0) -> 498.92 | AM32: 498.92 | AN32: =VLOOKUP(C32,Work!D:F,3,0) -> Mr. VISHAL SURESH MANE | AO32: =AN32=AK32 -> TRUE | AP32: FOU218
A33: 30 | B33: FOU86 | C33: 101817173110 | D33: SHIVANAND KANTAPPA KOSHTI | E33: FINAL | G33: 1 | H33: 1 | I33: 1 | J33: 1 | K33: 1 | N33: 1 | O33: 1 | P33: 1 | Q33: 0.5 | R33: 1 | S33: 1 | U33: 1 | V33: 1 | W33: 1 | X33: 1 | Z33: 1 | AB33: 1 | AC33: 1 | AD33: 1 | AE33: 1 | AF33: 1 | AG33: 1 | AH33: 1 | AI33: 1 | AJ33: =SUM(F33:AI33) -> 23.5 | AK33: =VLOOKUP(C33,'Name Details'!A:C,3,0) -> Mr. SHIVANAND KANTAPPA KOSHTI | AL33: =VLOOKUP(B33,'[2]APRIL-2026'!$B$1:$J$65536,9,0) -> 400.66 | AM33: 400.66 | AN33: =VLOOKUP(C33,Work!D:F,3,0) -> Mr. SHIVANAND KANTAPPA KOSHTI | AO33: =AN33=AK33 -> TRUE | AP33: FOU86
A34: 31 | B34: 0 | C34: DHANNAJAY AMBURE | D34: DHANNAJAY AMBURE | E34: FINAL | G34: 1 | H34: 1 | I34: 1 | J34: 0.5 | N34: 1 | P34: 1 | Q34: 1 | R34: 1 | S34: 1 | U34: 0.5 | V34: 1 | W34: 1 | X34: 1 | Y34: 1 | Z34: 1 | AB34: 1 | AD34: 1 | AJ34: =SUM(F34:AI34) -> 16 | AK34: =VLOOKUP(C34,'Name Details'!A:C,3,0) -> #N/A | AL34: =VLOOKUP(B34,'[2]APRIL-2026'!$B$1:$J$65536,9,0) -> #N/A | AN34: =VLOOKUP(C34,Work!D:F,3,0) -> DHANNAJAY AMBURE | AO34: =AN34=AK34 -> #N/A | AP34: 0
A35: 32 | B35: FOU44 | C35: 101410043453 | D35: CHITTAMANI SHAMRAO KADERKAR | E35: FINAL | H35: 1 | I35: 1 | J35: 1 | K35: 1 | L35: 1 | N35: 1 | O35: 1 | V35: 1 | W35: 1 | X35: 1 | Y35: 1 | Z35: 1 | AB35: 1 | AC35: 1 | AJ35: =SUM(F35:AI35) -> 14 | AK35: =VLOOKUP(C35,'Name Details'!A:C,3,0) -> Mr. KADERKAR CHINTAMANI SHAMRAO | AL35: =VLOOKUP(B35,'[2]APRIL-2026'!$B$1:$J$65536,9,0) -> #N/A | AN35: =VLOOKUP(C35,Work!D:F,3,0) -> Mr. KADERKAR CHINTAMANI SHAMRAO | AO35: =AN35=AK35 -> TRUE | AP35: FOU44
A36: 33 | B36: FOU19 | C36: 101407413648 | D36: NAMDEV BANDGAR | E36: HE | J36: 1 | K36: 1 | L36: 1 | N36: 1 | O36: 1 | P36: 1 | Q36: 1 | R36: 1 | S36: 1 | T36: 1 | V36: 1 | W36: 1 | X36: 1 | Y36: 1 | Z36: 1 | AA36: 1 | AB36: 1 | AC36: 1 | AD36: 1 | AE36: 2 | AF36: 1 | AI36: 1 | AJ36: =SUM(F36:AI36) -> 23 | AK36: =VLOOKUP(C36,'Name Details'!A:C,3,0) -> Mr. NAMDEV DURGAPPA BANDGAR | AL36: =VLOOKUP(B36,'[2]APRIL-2026'!$B$1:$J$65536,9,0) -> 494.83 | AM36: 494.83 | AN36: =VLOOKUP(C36,Work!D:F,3,0) -> Mr. NAMDEV DURGAPPA BANDGAR | AO36: =AN36=AK36 -> TRUE | AP36: FOU19
A37: 34 | B37: FOU20 | C37: 101391642731 | D37: DATTATRAY ASHOK WAGHMODE | E37: HE | G37: 1 | H37: 1 | I37: 1 | J37: 1 | K37: 1 | L37: 1 | N37: 1 | O37: 1 | P37: 1 | Q37: 1 | R37: 1 | S37: 1 | V37: 1 | W37: 1 | X37: 1 | Y37: 1 | Z37: 0.5 | AA37: 1 | AC37: 1 | AD37: 1 | AE37: 1 | AF37: 1 | AG37: 1 | AH37: 1 | AI37: 1 | AJ37: =SUM(F37:AI37) -> 24.5 | AK37: =VLOOKUP(C37,'Name Details'!A:C,3,0) -> Mr. WAGHMODE DATTATRAY ASHOK | AL37: =VLOOKUP(B37,'[2]APRIL-2026'!$B$1:$J$65536,9,0) -> 337.41 | AM37: 337.41 | AN37: =VLOOKUP(C37,Work!D:F,3,0) -> Mr. WAGHMODE DATTATRAY ASHOK | AO37: =AN37=AK37 -> TRUE | AP37: FOU20
A38: 35 | B38: FOU27 | C38: 101373078654 | D38: KHALID ILAHI SHIAKH | E38: HE | G38: 1 | H38: 1 | I38: 1 | J38: 1 | K38: 1 | L38: 1 | N38: 1 | O38: 1 | P38: 1 | Q38: 1 | R38: 1 | S38: 1 | U38: 1 | V38: 1 | W38: 1 | Y38: 1 | Z38: 1 | AB38: 1 | AC38: 1 | AD38: 1 | AE38: 1 | AF38: 1 | AG38: 1 | AH38: 1 | AI38: 1 | AJ38: =SUM(F38:AI38) -> 25 | AK38: =VLOOKUP(C38,'Name Details'!A:C,3,0) -> Mr. KHALID ILAI SHAIKH | AL38: =VLOOKUP(B38,'[2]APRIL-2026'!$B$1:$J$65536,9,0) -> 63.93 | AM38: 63.93 | AN38: =VLOOKUP(C38,Work!D:F,3,0) -> Mr. KHALID ILAI SHAIKH | AO38: =AN38=AK38 -> TRUE | AP38: FOU27
A39: 37 | B39: FOU32 | C39: 101747190938 | D39: AKASH JAGNNATH TENAGLE | E39: HE | G39: 1 | H39: 0.5 | I39: 1 | J39: 1 | K39: 1 | L39: 1 | N39: 1 | O39: 1 | AE39: 1 | AF39: 1 | AG39: 1 | AH39: 1 | AJ39: =SUM(F39:AI39) -> 11.5 | AK39: =VLOOKUP(C39,'Name Details'!A:C,3,0) -> Mr. AKASH JAGNNATH TENGALE | AL39: =VLOOKUP(B39,'[2]APRIL-2026'!$B$1:$J$65536,9,0) -> 286.28 | AM39: 286.28 | AN39: =VLOOKUP(C39,Work!D:F,3,0) -> Mr. AKASH JAGNNATH TENGALE | AO39: =AN39=AK39 -> TRUE | AP39: FOU32
A40: 38 | B40: FOU51 | C40: 101520450548 | D40: KASHINATH ABHIMANU PATIL | E40: HE | G40: 1 | H40: 1 | I40: 1 | J40: 1 | K40: 1 | L40: 1 | N40: 1 | O40: 1 | P40: 1 | Q40: 1 | R40: 1 | S40: 1 | T40: 1 | V40: 1 | W40: 1 | X40: 1 | Y40: 1 | Z40: 1 | AA40: 1 | AB40: 1 | AC40: 1 | AD40: 1 | AE40: 1 | AF40: 1 | AG40: 1 | AH40: 1 | AI40: 1 | AJ40: =SUM(F40:AI40) -> 27 | AK40: =VLOOKUP(C40,'Name Details'!A:C,3,0) -> Mr. KASHINATH ABHIMANYU PATIL | AL40: =VLOOKUP(B40,'[2]APRIL-2026'!$B$1:$J$65536,9,0) -> 214.77 | AM40: 214.77 | AN40: =VLOOKUP(C40,Work!D:F,3,0) -> Mr. KASHINATH ABHIMANYU PATIL | AO40: =AN40=AK40 -> TRUE | AP40: FOU51
A41: 39 | B41: FOU22 | C41: 101475170616 | D41: SATISH SHIVAJI SHINDE | E41: HE | G41: 1 | H41: 1 | I41: 1 | J41: 1 | K41: 1 | L41: 1 | N41: 1 | O41: 1 | P41: 1 | Q41: 1 | R41: 1 | S41: 1 | U41: 1 | V41: 1 | W41: 1 | X41: 1 | Y41: 1 | Z41: 1 | AB41: 1 | AC41: 1 | AD41: 1 | AE41: 1 | AF41: 1 | AG41: 1 | AH41: 1 | AI41: 1 | AJ41: =SUM(F41:AI41) -> 26 | AK41: =VLOOKUP(C41,'Name Details'!A:C,3,0) -> Mr. SATISH SHIVAJI SHINDE | AL41: =VLOOKUP(B41,'[2]APRIL-2026'!$B$1:$J$65536,9,0) -> 570.3 | AM41: 570.3 | AN41: =VLOOKUP(C41,Work!D:F,3,0) -> Mr. SATISH SHIVAJI SHINDE | AO41: =AN41=AK41 -> TRUE | AP41: FOU22
A42: 40 | B42: FOU35 | C42: 101154454730 | D42: SAGAR GHERSANGI | E42: HE | G42: 1 | H42: 1 | I42: 0.5 | J42: 1 | Y42: 1 | AD42: 1 | AE42: 1 | AF42: 1 | AG42: 1 | AH42: 1 | AI42: 1 | AJ42: =SUM(F42:AI42) -> 10.5 | AK42: =VLOOKUP(C42,'Name Details'!A:C,3,0) -> Mr. SAGAR RAMESH GHARSANGI | AL42: =VLOOKUP(B42,'[2]APRIL-2026'!$B$1:$J$65536,9,0) -> 69.59 | AM42: 69.59 | AN42: =VLOOKUP(C42,Work!D:F,3,0) -> Mr. SAGAR RAMESH GHARSANGI | AO42: =AN42=AK42 -> TRUE | AP42: FOU35
A43: 41 | B43: FOU791 | C43: AJAY SHRINIVAS PENTA | D43: AJAY SHRINIVAS PENTA | E43: HE | G43: 1 | H43: 1 | J43: 1 | K43: 1 | L43: 1 | S43: 1 | U43: 1 | V43: 1 | W43: 1 | X43: 1 | Y43: 1 | Z43: 1 | AB43: 1 | AC43: 1 | AD43: 1 | AE43: 1 | AF43: 1 | AG43: 1 | AH43: 1 | AI43: 1 | AJ43: =SUM(F43:AI43) -> 20 | AK43: =VLOOKUP(C43,'Name Details'!A:C,3,0) -> #N/A | AL43: =VLOOKUP(B43,'[2]APRIL-2026'!$B$1:$J$65536,9,0) -> 406.88 | AM43: 406.88 | AN43: =VLOOKUP(C43,Work!D:F,3,0) -> AJAY SHRINIVAS PENTA | AO43: =AN43=AK43 -> #N/A | AP43: FOU791
A44: 42 | B44: FOU555 | C44: 102209140373 | D44: HARUN MULLA | E44: HE | G44: 1 | L44: 1 | M44: 1 | N44: 1 | O44: 1 | P44: 1 | Q44: 1 | R44: 1 | S44: 1 | T44: 1 | U44: 1 | W44: 1 | X44: 1 | Y44: 1 | Z44: 1 | AA44: 1 | AB44: 1 | AC44: 1 | AD44: 1 | AE44: 1 | AF44: 1 | AG44: 1 | AH44: 1 | AI44: 1 | AJ44: =SUM(F44:AI44) -> 24 | AK44: =VLOOKUP(C44,'Name Details'!A:C,3,0) -> Mr. HARUN BASHA MULLA | AL44: =VLOOKUP(B44,'[2]APRIL-2026'!$B$1:$J$65536,9,0) -> 414.58 | AM44: 414.58 | AN44: =VLOOKUP(C44,Work!D:F,3,0) -> Mr. HARUN BASHA MULLA | AO44: =AN44=AK44 -> TRUE | AP44: FOU555
A45: 43 | B45: 0 | C45: 101591620448 | D45: RAJSHEKHAR ANDODGI | E45: HE | G45: 1 | H45: 1 | I45: 1 | K45: 1 | L45: 2 | N45: 1 | O45: 1 | P45: 1 | Q45: 1 | R45: 1 | S45: 1 | V45: 1 | Z45: 1 | AB45: 1 | AC45: 1 | AD45: 1 | AE45: 1 | AF45: 1 | AG45: 1 | AH45: 1 | AI45: 1 | AJ45: =SUM(F45:AI45) -> 22 | AK45: =VLOOKUP(C45,'Name Details'!A:C,3,0) -> Mr. RAJSHEKHAR ANDODGI | AL45: =VLOOKUP(B45,'[2]APRIL-2026'!$B$1:$J$65536,9,0) -> #N/A | AN45: =VLOOKUP(C45,Work!D:F,3,0) -> Mr. RAJSHEKHAR ANDODGI | AO45: =AN45=AK45 -> TRUE | AP45: 0
A46: 44 | B46: 0 | C46: 101509952020 | D46: AMOL TEJU RATHOD | E46: HE | G46: 1 | H46: 1 | I46: 1 | J46: 1 | K46: 2 | N46: 1 | O46: 1 | P46: 1 | Q46: 1 | R46: 1 | S46: 1 | W46: 1 | X46: 1 | Y46: 2 | AA46: 1 | AB46: 1 | AC46: 1 | AD46: 1 | AG46: 1 | AH46: 1 | AI46: 1 | AJ46: =SUM(F46:AI46) -> 23 | AK46: =VLOOKUP(C46,'Name Details'!A:C,3,0) -> Mr. AMOL TEJU RATHOD | AL46: =VLOOKUP(B46,'[2]APRIL-2026'!$B$1:$J$65536,9,0) -> #N/A | AN46: =VLOOKUP(C46,Work!D:F,3,0) -> Mr. AMOL TEJU RATHOD | AO46: =AN46=AK46 -> TRUE | AP46: 0
A47: 45 | B47: FOU224 | C47: 102078951370 | D47: ABHISHEK SUNIL RATHOD | E47: HE | H47: 1 | I47: 1 | J47: 1 | K47: 1 | P47: 1 | Q47: 1 | R47: 1 | S47: 1 | U47: 1 | V47: 1 | X47: 1 | Y47: 1 | AB47: 1 | AC47: 1 | AD47: 1 | AE47: 1 | AF47: 0.5 | AJ47: =SUM(F47:AI47) -> 16.5 | AK47: =VLOOKUP(C47,'Name Details'!A:C,3,0) -> Mr. ABHISHEK SUNIL RATHOD | AL47: =VLOOKUP(B47,'[2]APRIL-2026'!$B$1:$J$65536,9,0) -> 73.33 | AM47: 73.33 | AN47: =VLOOKUP(C47,Work!D:F,3,0) -> Mr. ABHISHEK SUNIL RATHOD | AO47: =AN47=AK47 -> TRUE | AP47: FOU224
A48: 46 | B48: FOU53 | C48: 101424676055 | D48: ROHAN BABURAO PANDIT | E48: HE | H48: 1 | I48: 1 | J48: 1 | K48: 1 | L48: 1 | N48: 1 | P48: 1 | Q48: 1 | R48: 1 | S48: 1 | T48: 1 | U48: 1 | V48: 1 | W48: 1 | X48: 1 | Y48: 1 | Z48: 1 | AB48: 0.5 | AC48: 1 | AD48: 1 | AE48: 1 | AI48: 1 | AJ48: =SUM(F48:AI48) -> 21.5 | AK48: =VLOOKUP(C48,'Name Details'!A:C,3,0) -> Mr. ROHAN BABURAV PANDIT | AL48: =VLOOKUP(B48,'[2]APRIL-2026'!$B$1:$J$65536,9,0) -> 35.73 | AM48: 35.73 | AN48: =VLOOKUP(C48,Work!D:F,3,0) -> Mr. ROHAN BABURAV PANDIT | AO48: =AN48=AK48 -> TRUE | AP48: FOU53
A49: 45 | B49: FOU535 | C49: 101591620411 | D49: SAGAR MALIKARI KOLI | E49: HE | AJ49: =SUM(F49:AI49) -> 0 | AK49: =VLOOKUP(C49,'Name Details'!A:C,3,0) -> Mr. SAGAR MALAKARI KOLI | AL49: =VLOOKUP(B49,'[2]APRIL-2026'!$B$1:$J$65536,9,0) -> #N/A | AN49: =VLOOKUP(C49,Work!D:F,3,0) -> Mr. SAGAR MALAKARI KOLI | AO49: =AN49=AK49 -> TRUE | AP49: FOU535
A50: 46 | B50: FOU94 | C50: 101732689727 | D50: MOIN GULAB MULLA | E50: HE | AJ50: =SUM(F50:AI50) -> 0 | AK50: =VLOOKUP(C50,'Name Details'!A:C,3,0) -> Mr. MOIN GULAB MULLA | AL50: =VLOOKUP(B50,'[2]APRIL-2026'!$B$1:$J$65536,9,0) -> #N/A | AN50: =VLOOKUP(C50,Work!D:F,3,0) -> Mr. MOIN GULAB MULLA | AO50: =AN50=AK50 -> TRUE | AP50: FOU94
A51: 47 | B51: FOU31 | C51: 101522138160 | D51: MALLINATH SHIVRAM VHANKADE | E51: HE | K51: 1 | L51: 1 | N51: 1 | O51: 1 | P51: 1 | Q51: 1 | R51: 1 | S51: 1 | U51: 1 | V51: 1 | W51: 1 | X51: 1 | Y51: 1 | Z51: 1 | AB51: 1 | AC51: 1 | AH51: 1 | AI51: 1 | AJ51: =SUM(F51:AI51) -> 18 | AK51: =VLOOKUP(C51,'Name Details'!A:C,3,0) -> Mr. MALLINATH SHIVARAM VHANAKADE | AL51: =VLOOKUP(B51,'[2]APRIL-2026'!$B$1:$J$65536,9,0) -> 74.72 | AM51: 74.72 | AN51: =VLOOKUP(C51,Work!D:F,3,0) -> Mr. MALLINATH SHIVARAM VHANAKADE | AO51: =AN51=AK51 -> TRUE | AP51: FOU31
A52: 48 | B52: FOU70 | C52: 101835374035 | D52: ANKUSH SANJAY BHALE | E52: HE | G52: 1 | H52: 1 | I52: 1 | J52: 1 | K52: 2 | N52: 1 | O52: 1 | P52: 1 | Q52: 0.5 | S52: 1 | U52: 1 | V52: 1 | W52: 1 | X52: 1 | Y52: 1 | Z52: 1 | AE52: 1 | AF52: 1 | AG52: 1 | AH52: 1 | AI52: 1 | AJ52: =SUM(F52:AI52) -> 21.5 | AK52: =VLOOKUP(C52,'Name Details'!A:C,3,0) -> Mr. ANKUASH SANJAY BHALE | AL52: =VLOOKUP(B52,'[2]APRIL-2026'!$B$1:$J$65536,9,0) -> 163.59 | AM52: 163.59 | AN52: =VLOOKUP(C52,Work!D:F,3,0) -> Mr. ANKUASH SANJAY BHALE | AO52: =AN52=AK52 -> TRUE | AP52: FOU70
A53: 49 | B53: 0 | C53: 102053057886 | D53: DINESH VASANT SALGAR | E53: HE | G53: 1 | H53: 1 | I53: 1 | J53: 0.5 | K53: 1 | L53: 1 | N53: 1 | O53: 1 | P53: 1 | Q53: 1 | R53: 1 | S53: 1 | T53: 1 | U53: 1 | V53: 1 | W53: 1 | X53: 1 | Y53: 1 | Z53: 1 | AA53: 1 | AB53: 1 | AC53: 1 | AD53: 1 | AE53: 1 | AF53: 1 | AG53: 1 | AI53: 1 | AJ53: =SUM(F53:AI53) -> 26.5 | AK53: =VLOOKUP(C53,'Name Details'!A:C,3,0) -> Mr. DINESH VASANT SALGAR | AL53: =VLOOKUP(B53,'[2]APRIL-2026'!$B$1:$J$65536,9,0) -> #N/A | AN53: =VLOOKUP(C53,Work!D:F,3,0) -> Mr. DINESH VASANT SALGAR | AO53: =AN53=AK53 -> TRUE | AP53: 0
A54: 50 | B54: FOU741 | C54: 101241926666 | D54: ANIL RAWAT | E54: HE | H54: 1 | I54: 1 | J54: 1 | N54: 1 | O54: 1 | P54: 1 | R54: 1 | S54: 1 | T54: 1 | V54: 1 | W54: 1 | X54: 1 | Y54: 1 | Z54: 1.5 | AA54: 1 | AC54: 1 | AD54: 1 | AE54: 1 | AF54: 1 | AG54: 1 | AJ54: =SUM(F54:AI54) -> 20.5 | AK54: =VLOOKUP(C54,'Name Details'!A:C,3,0) -> Mr. ANIL KUMAR RAWAT | AL54: =VLOOKUP(B54,'[2]APRIL-2026'!$B$1:$J$65536,9,0) -> 355.7 | AM54: 355.7 | AN54: =VLOOKUP(C54,Work!D:F,3,0) -> Mr. ANIL KUMAR RAWAT | AO54: =AN54=AK54 -> TRUE | AP54: FOU741
A55: 51 | B55: FOU379 | C55: 102143026061 | D55: BADIGER RAJKUMAR | E55: HE | O55: 1 | P55: 1 | Q55: 1 | S55: 1 | U55: 1 | V55: 1 | W55: 1 | X55: 1 | Y55: 1 | Z55: 1 | AB55: 0.5 | AC55: 0.5 | AD55: 0.5 | AF55: 1 | AH55: 1 | AI55: 1 | AJ55: =SUM(F55:AI55) -> 14.5 | AK55: =VLOOKUP(C55,'Name Details'!A:C,3,0) -> Mr. RAJAKUMAR BADIGER | AL55: =VLOOKUP(B55,'[2]APRIL-2026'!$B$1:$J$65536,9,0) -> 417.62 | AM55: 417.62 | AN55: =VLOOKUP(C55,Work!D:F,3,0) -> Mr. RAJAKUMAR BADIGER | AO55: =AN55=AK55 -> TRUE | AP55: FOU379
A56: 52 | B56: FOU743 | C56: 101807758862 | D56: RAKESH ASHOK RAUT | E56: HE | G56: 1 | H56: 1 | I56: 1 | J56: 1 | K56: 1 | L56: 1 | N56: 1 | O56: 1 | P56: 1 | R56: 1 | S56: 1 | U56: 1 | V56: 1 | W56: 1 | X56: 1 | Y56: 1 | Z56: 1 | AB56: 1 | AC56: 1 | AD56: 1 | AE56: 1 | AG56: 1 | AJ56: =SUM(F56:AI56) -> 22 | AK56: =VLOOKUP(C56,'Name Details'!A:C,3,0) -> Mr. RAKESH ASHOK RAUT | AL56: =VLOOKUP(B56,'[2]APRIL-2026'!$B$1:$J$65536,9,0) -> #N/A | AN56: =VLOOKUP(C56,Work!D:F,3,0) -> Mr. RAKESH ASHOK RAUT | AO56: =AN56=AK56 -> TRUE | AP56: FOU743
A57: 53 | B57: FOU208 | C57: 102086533444 | D57: KHATAL SANDIP CHANDRAKANT | E57: HE | G57: 1 | H57: 1 | I57: 1 | J57: 1 | K57: 1 | O57: 1 | P57: 1 | Q57: 1 | R57: 1 | S57: 1 | U57: 1 | W57: 1 | Y57: 1 | Z57: 1 | AC57: 1 | AD57: 1 | AE57: 1 | AH57: 1 | AI57: 1 | AJ57: =SUM(F57:AI57) -> 19 | AK57: =VLOOKUP(C57,'Name Details'!A:C,3,0) -> Mr. SANDIP CHANDRAKANT KHATAL | AL57: =VLOOKUP(B57,'[2]APRIL-2026'!$B$1:$J$65536,9,0) -> 9.4 | AM57: 9.4 | AN57: =VLOOKUP(C57,Work!D:F,3,0) -> Mr. SANDIP CHANDRAKANT KHATAL | AO57: =AN57=AK57 -> TRUE | AP57: FOU208
A58: 54 | B58: FOU628 | C58: 102235752061 | D58: SAISAMARTH VITTHAL ZAMPALE | E58: HE | G58: 1 | H58: 1 | I58: 1 | J58: 1 | K58: 1 | L58: 1 | O58: 1 | P58: 1 | Q58: 1 | S58: 1 | U58: 1 | V58: 1 | W58: 1 | X58: 1 | Y58: 1 | Z58: 1 | AB58: 1 | AC58: 1 | AD58: 1 | AE58: 1 | AF58: 1 | AG58: 1 | AH58: 1 | AI58: 1 | AJ58: =SUM(F58:AI58) -> 24 | AK58: =VLOOKUP(C58,'Name Details'!A:C,3,0) -> Mr. SAISAMARTH VITTHAL ZAMPALE | AL58: =VLOOKUP(B58,'[2]APRIL-2026'!$B$1:$J$65536,9,0) -> 9.4 | AM58: 9.4 | AN58: =VLOOKUP(C58,Work!D:F,3,0) -> Mr. SAISAMARTH VITTHAL ZAMPALE | AO58: =AN58=AK58 -> TRUE | AP58: FOU628
A59: 55 | B59: FOU514 | C59: 101084612898 | D59: MANGESH NAVNATH ANKUSHRAO | E59: HE | H59: 1 | I59: 1 | J59: 1 | K59: 1 | L59: 1 | N59: 1 | O59: 1 | P59: 1 | R59: 1 | S59: 1 | U59: 1 | V59: 1 | W59: 1 | X59: 1 | Y59: 1 | Z59: 1 | AC59: 1 | AD59: 1 | AE59: 1 | AF59: 1 | AH59: 1 | AJ59: =SUM(F59:AI59) -> 21 | AK59: =VLOOKUP(C59,'Name Details'!A:C,3,0) -> Mr. MANGESH NAVNATH ANKUSHRAO | AL59: =VLOOKUP(B59,'[2]APRIL-2026'!$B$1:$J$65536,9,0) -> 209.94 | AM59: 209.94 | AN59: =VLOOKUP(C59,Work!D:F,3,0) -> Mr. MANGESH NAVNATH ANKUSHRAO | AO59: =AN59=AK59 -> TRUE | AP59: FOU514
A60: 56 | B60: FOU459 | C60: 102190249257 | D60: HIRKUR YUVRAJ MALAKARI | E60: HE | G60: 1 | J60: 1 | K60: 1 | L60: 1 | O60: 1 | P60: 1 | Q60: 1 | R60: 1 | S60: 1 | U60: 1 | V60: 1 | W60: 1 | X60: 1 | Y60: 1 | Z60: 1 | AB60: 1 | AC60: 0.5 | AD60: 1 | AE60: 1 | AF60: 1 | AG60: 1 | AH60: 1 | AI60: 1 | AJ60: =SUM(F60:AI60) -> 22.5 | AK60: =VLOOKUP(C60,'Name Details'!A:C,3,0) -> Mr. YUVRAJ MALAKARI HIRKURE | AL60: =VLOOKUP(B60,'[2]APRIL-2026'!$B$1:$J$65536,9,0) -> 414.14 | AM60: 414.14 | AN60: =VLOOKUP(C60,Work!D:F,3,0) -> Mr. YUVRAJ MALAKARI HIRKURE | AO60: =AN60=AK60 -> TRUE | AP60: FOU459
A61: 57 | B61: FOU38 | C61: 101805790352 | D61: PRABHAKAR NAIKWADE | E61: HE | G61: 1 | H61: 1 | I61: 1 | J61: 1 | K61: 1 | L61: 1 | N61: 1 | O61: 1 | P61: 1 | Q61: 1 | R61: 1 | S61: 1 | U61: 1 | V61: 1 | W61: 1 | X61: 1 | AB61: 1 | AC61: 1 | AE61: 1 | AF61: 1 | AG61: 1 | AH61: 1 | AI61: 1 | AJ61: =SUM(F61:AI61) -> 23 | AK61: =VLOOKUP(C61,'Name Details'!A:C,3,0) -> Mr. PRABHAKAR BIRAPPA NAYKUDE | AL61: =VLOOKUP(B61,'[2]APRIL-2026'!$B$1:$J$65536,9,0) -> 9.4 | AM61: 9.4 | AN61: =VLOOKUP(C61,Work!D:F,3,0) -> Mr. PRABHAKAR BIRAPPA NAYKUDE | AO61: =AN61=AK61 -> TRUE | AP61: FOU38
A62: 58 | B62: FOU827 | C62: SANJAY GOPINATH BANDGAR | D62: SANJAY GOPINATH BANDGAR | E62: HE | L62: 1 | N62: 1 | O62: 1 | R62: 1 | S62: 1 | U62: 1 | V62: 1 | W62: 1 | X62: 1 | Y62: 1 | Z62: 1 | AB62: 1 | AC62: 1 | AD62: 1 | AE62: 1 | AF62: 1 | AG62: 1 | AJ62: =SUM(F62:AI62) -> 17 | AK62: =VLOOKUP(C62,'Name Details'!A:C,3,0) -> #N/A | AL62: =VLOOKUP(B62,'[2]APRIL-2026'!$B$1:$J$65536,9,0) -> 282.1 | AM62: 282.1 | AN62: =VLOOKUP(C62,Work!D:F,3,0) -> SANJAY GOPINATH BANDGAR | AO62: =AN62=AK62 -> #N/A | AP62: FOU827
A63: 59 | B63: FOU828 | C63: ARJUN HIRACHAND BANDAGAR | D63: ARJUN HIRACHAND BANDAGAR | E63: HE | K63: 1 | L63: 1 | N63: 1 | O63: 1 | P63: 1 | R63: 1 | S63: 1 | U63: 1 | W63: 1 | X63: 1 | Y63: 1 | Z63: 1 | AB63: 1 | AC63: 1 | AD63: 1 | AE63: 1 | AF63: 1 | AG63: 1 | AH63: 1 | AI63: 1 | AJ63: =SUM(F63:AI63) -> 20 | AK63: =VLOOKUP(C63,'Name Details'!A:C,3,0) -> #N/A | AL63: =VLOOKUP(B63,'[2]APRIL-2026'!$B$1:$J$65536,9,0) -> 244.5 | AM63: 244.5 | AN63: =VLOOKUP(C63,Work!D:F,3,0) -> ARJUN HIRACHAND BANDAGAR | AO63: =AN63=AK63 -> #N/A | AP63: FOU828
A64: 60 | B64: FOU881 | C64: WAGHMARE SUNIL GANPAT | D64: WAGHMARE SUNIL GANPAT | E64: HE | Y64: 1 | AJ64: =SUM(F64:AI64) -> 1 | AK64: =VLOOKUP(C64,'Name Details'!A:C,3,0) -> #N/A | AL64: =VLOOKUP(B64,'[2]APRIL-2026'!$B$1:$J$65536,9,0) -> 43.26 | AM64: 43 | AN64: =VLOOKUP(C64,Work!D:F,3,0) -> WAGHMARE SUNIL GANPAT | AO64: =AN64=AK64 -> #N/A | AP64: FOU881
A65: 60 | B65: FOU58 | C65: 101428896909 | D65: KISHOR JYOTIBA MORE | E65: SHOT BLAST | G65: 1 | H65: 1 | K65: 1 | L65: 1 | N65: 1 | O65: 1 | Q65: 1 | R65: 1 | S65: 1 | V65: 1 | X65: 2 | Y65: 1 | Z65: 1 | AB65: 1 | AC65: 1 | AD65: 1 | AE65: 1 | AF65: 1 | AG65: 1 | AI65: 1 | AJ65: =SUM(F65:AI65) -> 21 | AK65: =VLOOKUP(C65,'Name Details'!A:C,3,0) -> Mr. KISHOR JYOTIBA MORE | AL65: =VLOOKUP(B65,'[2]APRIL-2026'!$B$1:$J$65536,9,0) -> 135.44 | AM65: 135.44 | AN65: =VLOOKUP(C65,Work!D:F,3,0) -> Mr. KISHOR JYOTIBA MORE | AO65: =AN65=AK65 -> TRUE | AP65: FOU58
A66: 61 | B66: FOU52 | C66: 101951607397 | D66: LANDAGE SHAVARSIDHA KHANDAPPA | E66: SHOT BLAST | H66: 1 | I66: 1 | J66: 1 | K66: 1 | L66: 1 | N66: 1 | O66: 1 | P66: 1 | Q66: 1 | R66: 1 | S66: 1 | U66: 1 | V66: 1 | W66: 1 | AB66: 1 | AC66: 1 | AD66: 1 | AE66: 1 | AG66: 1 | AH66: 1 | AI66: 1 | AJ66: =SUM(F66:AI66) -> 21 | AK66: =VLOOKUP(C66,'Name Details'!A:C,3,0) -> Mr. SHAVRSIDDHA KHANDAPPA LANDAGE | AL66: =VLOOKUP(B66,'[2]APRIL-2026'!$B$1:$J$65536,9,0) -> 443 | AM66: 443 | AN66: =VLOOKUP(C66,Work!D:F,3,0) -> Mr. SHAVRSIDDHA KHANDAPPA LANDAGE | AO66: =AN66=AK66 -> TRUE | AP66: FOU52
A67: 62 | B67: FOU72 | C67: 101976571122 | D67: DNYANESHWAR BHAGVANT WAGHMARE | E67: SHOT BLAST | F67: 1 | I67: 1 | J67: 1 | K67: 1 | L67: 1 | N67: 1 | O67: 1 | Q67: 1 | R67: 1 | S67: 1 | T67: 1 | W67: 1 | Y67: 1 | Z67: 1 | AB67: 1 | AC67: 1 | AD67: 1 | AE67: 1 | AF67: 1 | AG67: 1 | AI67: 1 | AJ67: =SUM(F67:AI67) -> 21 | AK67: =VLOOKUP(C67,'Name Details'!A:C,3,0) -> Mr. DNYANESHWAR BHAGAVANT WAGHAMARE | AL67: =VLOOKUP(B67,'[2]APRIL-2026'!$B$1:$J$65536,9,0) -> 244.72 | AM67: 244.72 | AN67: =VLOOKUP(C67,Work!D:F,3,0) -> Mr. DNYANESHWAR BHAGAVANT WAGHAMARE | AO67: =AN67=AK67 -> TRUE | AP67: FOU72
A68: 63 | B68: FOU49 | C68: 101447270865 | D68: ABHIJEET PIRAPPA WAGHMARE | E68: SHOT BLAST | F68: 1 | G68: 1 | H68: 1 | I68: 1 | J68: 1 | K68: 1 | L68: 1 | N68: 1 | O68: 1 | P68: 1 | Q68: 1 | R68: 1 | S68: 1 | T68: 1 | U68: 1 | V68: 1 | W68: 1 | X68: 1 | AC68: 1 | AD68: 1 | AE68: 1 | AF68: 1 | AG68: 1 | AH68: 2 | AI68: 1 | AJ68: =SUM(F68:AI68) -> 26 | AK68: =VLOOKUP(C68,'Name Details'!A:C,3,0) -> Mr. ABHIJIT PIRAPPA WAGHMARE | AL68: =VLOOKUP(B68,'[2]APRIL-2026'!$B$1:$J$65536,9,0) -> 439.21 | AM68: 439.21 | AN68: =VLOOKUP(C68,Work!D:F,3,0) -> Mr. ABHIJIT PIRAPPA WAGHMARE | AO68: =AN68=AK68 -> TRUE | AP68: FOU49
A69: 64 | B69: FOU113 | C69: 101931400073 | D69: PATHAN SHAHNAVAJ MURTUJ | E69: SHOT BLAST | G69: 1 | H69: 1 | I69: 1 | J69: 1 | K69: 1 | L69: 1 | N69: 1 | O69: 1 | P69: 1 | Q69: 1 | R69: 1 | S69: 1 | U69: 1 | V69: 1 | W69: 1 | Y69: 1 | Z69: 1 | AB69: 1 | AC69: 1 | AD69: 1 | AE69: 1 | AF69: 1 | AG69: 1 | AH69: 1 | AI69: 1 | AJ69: =SUM(F69:AI69) -> 25 | AK69: =VLOOKUP(C69,'Name Details'!A:C,3,0) -> Mr. SHAHANVAJ MURTUJ PATHAN | AL69: =VLOOKUP(B69,'[2]APRIL-2026'!$B$1:$J$65536,9,0) -> 451.4 | AM69: 451.4 | AN69: =VLOOKUP(C69,Work!D:F,3,0) -> Mr. SHAHANVAJ MURTUJ PATHAN | AO69: =AN69=AK69 -> TRUE | AP69: FOU113
A70: 65 | B70: FOU87 | C70: 101868848739 | D70: BASVRAJ SOMNATH KARKALE | E70: SHOT BLAST | G70: 1 | H70: 1 | I70: 1 | J70: 1 | K70: 1 | L70: 1 | N70: 1 | O70: 1 | P70: 1 | Q70: 1 | R70: 1 | S70: 1 | U70: 1 | V70: 1 | W70: 1 | X70: 1 | Y70: 1 | Z70: 1 | AB70: 1 | AC70: 1 | AD70: 1 | AE70: 1 | AF70: 1 | AG70: 1 | AH70: 1 | AI70: 1 | AJ70: =SUM(F70:AI70) -> 26 | AK70: =VLOOKUP(C70,'Name Details'!A:C,3,0) -> Mr. BASAVRAJ SOMNATH KARKALE | AL70: =VLOOKUP(B70,'[2]APRIL-2026'!$B$1:$J$65536,9,0) -> 436.34 | AM70: 436.34 | AN70: =VLOOKUP(C70,Work!D:F,3,0) -> Mr. BASAVRAJ SOMNATH KARKALE | AO70: =AN70=AK70 -> TRUE | AP70: FOU87
A71: 66 | B71: FOU314 | C71: 102125816854 | D71: SUFIYAN FULARI | E71: SHOT BLAST | F71: 1 | G71: 1 | I71: 1 | J71: 1 | K71: 1 | L71: 1 | N71: 1 | O71: 1 | P71: 1 | Q71: 1 | R71: 1 | S71: 2 | T71: 1 | U71: 1 | V71: 1 | Y71: 1 | Z71: 1 | AB71: 1 | AC71: 1 | AD71: 1 | AE71: 1 | AF71: 1 | AG71: 0.5 | AH71: 1 | AI71: 1 | AJ71: =SUM(F71:AI71) -> 25.5 | AK71: =VLOOKUP(C71,'Name Details'!A:C,3,0) -> Mr. SUFIYAN SHEKULAL FULARI | AL71: =VLOOKUP(B71,'[2]APRIL-2026'!$B$1:$J$65536,9,0) -> 35.73 | AM71: 35.73 | AN71: =VLOOKUP(C71,Work!D:F,3,0) -> Mr. SUFIYAN SHEKULAL FULARI | AO71: =AN71=AK71 -> TRUE | AP71: FOU314
A72: 67 | B72: FOU39 | C72: 101821692693 | D72: SAGAR BASVRAJ ARJUN | E72: REWORK | I72: 1 | J72: 1 | N72: 1 | O72: 1 | P72: 1 | S72: 1 | U72: 1 | V72: 1 | W72: 1 | Y72: 1 | AJ72: =SUM(F72:AI72) -> 10 | AK72: =VLOOKUP(C72,'Name Details'!A:C,3,0) -> Mr. SAGAR BASAVRAJ ARJUN | AL72: =VLOOKUP(B72,'[2]APRIL-2026'!$B$1:$J$65536,9,0) -> #N/A | AN72: =VLOOKUP(C72,Work!D:F,3,0) -> Mr. SAGAR BASAVRAJ ARJUN | AO72: =AN72=AK72 -> TRUE | AP72: FOU39
A73: 68 | B73: FOU67 | C73: 100450352070 | D73: GHANTE SACHIN BHAGWAN | E73: REWORK | F73: 1 | G73: 1 | H73: 1 | I73: 1 | J73: 1 | K73: 1 | L73: 1 | N73: 1 | O73: 1 | P73: 1 | Q73: 2 | R73: 1 | S73: 1 | U73: 1 | V73: 1 | W73: 1 | X73: 1 | Y73: 1 | Z73: 1 | AB73: 1 | AC73: 1 | AD73: 1 | AE73: 1 | AF73: 1 | AG73: 1 | AH73: 1 | AI73: 1 | AJ73: =SUM(F73:AI73) -> 28 | AK73: =VLOOKUP(C73,'Name Details'!A:C,3,0) -> Mr. SACHIN BHAGWAN GHANTE | AL73: =VLOOKUP(B73,'[2]APRIL-2026'!$B$1:$J$65536,9,0) -> 171.17 | AM73: 171.17 | AN73: =VLOOKUP(C73,Work!D:F,3,0) -> Mr. SACHIN BHAGWAN GHANTE | AO73: =AN73=AK73 -> TRUE | AP73: FOU67
A74: 69 | B74: FOU47 | C74: 101388345766 | D74: CHOUGULE HRUSHIKESH CHANDRAKANT | E74: REWORK | H74: 1 | I74: 1 | J74: 1 | K74: 1 | L74: 1 | M74: 1 | N74: 1 | O74: 1 | Q74: 1 | T74: 1 | V74: 1 | W74: 1 | X74: 1 | Y74: 1 | Z74: 1 | AA74: 1 | AB74: 1 | AC74: 1 | AD74: 1 | AE74: 1 | AF74: 1 | AG74: 1 | AH74: 0.5 | AJ74: =SUM(F74:AI74) -> 22.5 | AK74: =VLOOKUP(C74,'Name Details'!A:C,3,0) -> Mr. RUSHIKESH CHANDRAKANT CHOUGULE | AL74: =VLOOKUP(B74,'[2]APRIL-2026'!$B$1:$J$65536,9,0) -> 246.42 | AM74: 246.42 | AN74: =VLOOKUP(C74,Work!D:F,3,0) -> Mr. RUSHIKESH CHANDRAKANT CHOUGULE | AO74: =AN74=AK74 -> TRUE | AP74: FOU47
A75: 70 | B75: FOU68 | C75: 101902123648 | D75: MUSTAK RASHID SHAIKH | E75: REWORK | G75: 1 | H75: 1 | I75: 1 | J75: 1 | K75: 1 | N75: 1 | O75: 1 | P75: 1 | Q75: 1 | R75: 1 | S75: 1 | V75: 1 | W75: 1 | X75: 1 | Y75: 0.5 | Z75: 1 | AB75: 0.5 | AC75: 1 | AD75: 1 | AE75: 1 | AF75: 1 | AH75: 1 | AI75: 1 | AJ75: =SUM(F75:AI75) -> 22 | AK75: =VLOOKUP(C75,'Name Details'!A:C,3,0) -> Mr. MUSHTAK RASHID SHAIKH | AL75: =VLOOKUP(B75,'[2]APRIL-2026'!$B$1:$J$65536,9,0) -> 393.13 | AM75: 393.13 | AN75: =VLOOKUP(C75,Work!D:F,3,0) -> Mr. MUSHTAK RASHID SHAIKH | AO75: =AN75=AK75 -> TRUE | AP75: FOU68
A76: 71 | B76: FOU54 | C76: 101909060608 | D76: SOHEL SAHEBLAL JAMADAR | E76: REWORK | G76: 1 | H76: 1 | I76: 1 | J76: 1 | K76: 1 | L76: 1 | N76: 1 | O76: 1 | P76: 1 | Q76: 1 | R76: 1 | U76: 1 | V76: 1 | W76: 1 | X76: 1 | Y76: 1 | Z76: 1 | AD76: 1 | AE76: 1 | AF76: 1 | AG76: 0.5 | AH76: 1 | AI76: 0.5 | AJ76: =SUM(F76:AI76) -> 22 | AK76: =VLOOKUP(C76,'Name Details'!A:C,3,0) -> Mr. SOHEL SAHEBLAL JAMADAR | AL76: =VLOOKUP(B76,'[2]APRIL-2026'!$B$1:$J$65536,9,0) -> 287.81 | AM76: 287.81 | AN76: =VLOOKUP(C76,Work!D:F,3,0) -> Mr. SOHEL SAHEBLAL JAMADAR | AO76: =AN76=AK76 -> TRUE | AP76: FOU54
A77: 72 | B77: FOU81 | C77: 102025154331 | D77: ARBAJ AMIN JAMADAR | E77: REWORK | G77: 1 | H77: 1 | I77: 1 | J77: 1 | K77: 1 | L77: 1 | M77: 1 | N77: 1 | U77: 1 | V77: 1 | W77: 1 | X77: 1 | Y77: 1 | Z77: 1 | AA77: 1 | AB77: 1 | AC77: 1 | AD77: 1 | AE77: 1 | AG77: 1 | AH77: 1 | AI77: 1 | AJ77: =SUM(F77:AI77) -> 22 | AK77: =VLOOKUP(C77,'Name Details'!A:C,3,0) -> Mr. ARBAJ AMIN JAMADAR | AL77: =VLOOKUP(B77,'[2]APRIL-2026'!$B$1:$J$65536,9,0) -> 378.07 | AM77: 378.07 | AN77: =VLOOKUP(C77,Work!D:F,3,0) -> Mr. ARBAJ AMIN JAMADAR | AO77: =AN77=AK77 -> TRUE | AP77: FOU81
A78: 73 | B78: FOU653 | C78: 102245251075 | D78: HIREMATH MANIK GURULINGAYA | E78: REWORK | G78: 1 | I78: 1 | J78: 1 | K78: 1 | L78: 1 | N78: 1 | O78: 1 | P78: 1 | Q78: 1 | R78: 1 | S78: 1 | U78: 1 | V78: 1 | W78: 1 | X78: 1 | Y78: 1 | Z78: 1 | AB78: 1 | AC78: 1 | AD78: 1 | AE78: 1 | AF78: 1 | AG78: 1 | AH78: 1 | AI78: 1 | AJ78: =SUM(F78:AI78) -> 25 | AK78: =VLOOKUP(C78,'Name Details'!A:C,3,0) -> Mr. MANIK GURULINGAYA HIREMATH | AL78: =VLOOKUP(B78,'[2]APRIL-2026'!$B$1:$J$65536,9,0) -> 382.42 | AM78: 382.42 | AN78: =VLOOKUP(C78,Work!D:F,3,0) -> Mr. MANIK GURULINGAYA HIREMATH | AO78: =AN78=AK78 -> TRUE | AP78: FOU653
A79: 74 | B79: FOU222 | C79: 102081665259 | D79: DOMBE SIDRAM | E79: REWORK | P79: 1 | Q79: 1 | R79: 1 | S79: 1 | U79: 1 | V79: 1 | W79: 1 | X79: 1 | Y79: 1 | Z79: 1 | AB79: 1 | AC79: 1 | AD79: 1 | AE79: 1 | AF79: 1 | AG79: 1 | AH79: 1 | AI79: 1 | AJ79: =SUM(F79:AI79) -> 18 | AK79: =VLOOKUP(C79,'Name Details'!A:C,3,0) -> Mr. SIDDHRAM MAHANINGAPPA DOMBE | AL79: =VLOOKUP(B79,'[2]APRIL-2026'!$B$1:$J$65536,9,0) -> 324.54 | AM79: 324.54 | AN79: =VLOOKUP(C79,Work!D:F,3,0) -> Mr. SIDDHRAM MAHANINGAPPA DOMBE | AO79: =AN79=AK79 -> TRUE | AP79: FOU222
A80: 75 | B80: FOU80 | C80: 101235372414 | D80: VISHAL MOHAN MANE | E80: REWORK | F80: 1 | G80: 1 | H80: 1 | I80: 1 | J80: 1 | K80: 0.5 | Q80: 1 | S80: 1 | T80: 1 | W80: 1 | X80: 1 | Z80: 1 | AC80: 1 | AD80: 1 | AJ80: =SUM(F80:AI80) -> 13.5 | AK80: =VLOOKUP(C80,'Name Details'!A:C,3,0) -> Mr. VISHAL MOHAN MANE | AL80: =VLOOKUP(B80,'[2]APRIL-2026'!$B$1:$J$65536,9,0) -> 152.54 | AM80: 152.54 | AN80: =VLOOKUP(C80,Work!D:F,3,0) -> Mr. VISHAL MOHAN MANE | AO80: =AN80=AK80 -> TRUE | AP80: FOU80
A81: 76 | B81: FOU26 | C81: 101486099649 | D81: JADHAV PUNDLIK C | E81: REWORK | F81: 1 | G81: 1 | H81: 2 | J81: 1 | L81: 1 | N81: 1 | O81: 1 | P81: 1 | R81: 1 | S81: 1 | U81: 1 | V81: 0.5 | AB81: 1 | AC81: 1 | AE81: 2 | AF81: 1 | AG81: 1 | AH81: 2 | AJ81: =SUM(F81:AI81) -> 20.5 | AK81: =VLOOKUP(C81,'Name Details'!A:C,3,0) -> Mr. PUNDALIK CHANDU JADHAV | AL81: =VLOOKUP(B81,'[2]APRIL-2026'!$B$1:$J$65536,9,0) -> 36.12 | AM81: 36.12 | AN81: =VLOOKUP(C81,Work!D:F,3,0) -> Mr. PUNDALIK CHANDU JADHAV | AO81: =AN81=AK81 -> TRUE | AP81: FOU26
A82: 77 | B82: FOU64 | C82: 101972731570 | D82: BHARAT SANTOSH SARADE | E82: PAINTER | F82: 1 | G82: 1 | H82: 1 | I82: 1 | J82: 1 | K82: 1 | L82: 1 | N82: 1 | O82: 2 | P82: 1 | Q82: 2 | R82: 1 | S82: 1 | T82: 1 | U82: 1 | V82: 1 | W82: 1 | X82: 1 | Y82: 1 | Z82: 1 | AC82: 1 | AD82: 1 | AE82: 1 | AF82: 1 | AG82: 1 | AH82: 1 | AI82: 1 | AJ82: =SUM(F82:AI82) -> 29 | AK82: =VLOOKUP(C82,'Name Details'!A:C,3,0) -> Mr. BHARAT SANTOSH SARADE | AL82: =VLOOKUP(B82,'[2]APRIL-2026'!$B$1:$J$65536,9,0) -> 314.09 | AM82: 314.09 | AN82: =VLOOKUP(C82,Work!D:F,3,0) -> Mr. BHARAT SANTOSH SARADE | AO82: =AN82=AK82 -> TRUE | AP82: FOU64
A83: 78 | B83: FOU74 | C83: 101396804599 | D83: SHARNAPPA KHEDAGIKAR | E83: PAINTER | F83: 1 | G83: 1 | I83: 1 | J83: 1 | K83: 1 | L83: 1 | N83: 1 | O83: 1 | P83: 1 | Q83: 1 | R83: 1 | S83: 1 | U83: 1 | V83: 1 | W83: 1 | X83: 1 | Y83: 1 | Z83: 1 | AB83: 1 | AC83: 1 | AD83: 1 | AE83: 1 | AF83: 1 | AG83: 1 | AH83: 1 | AI83: 1 | AJ83: =SUM(F83:AI83) -> 26 | AK83: =VLOOKUP(C83,'Name Details'!A:C,3,0) -> Mr. SHARANAPPA KHEDAGIKAR | AL83: =VLOOKUP(B83,'[2]APRIL-2026'!$B$1:$J$65536,9,0) -> 315.96 | AM83: 315.96 | AN83: =VLOOKUP(C83,Work!D:F,3,0) -> Mr. SHARANAPPA KHEDAGIKAR | AO83: =AN83=AK83 -> TRUE | AP83: FOU74
A84: 79 | B84: FOU114 | C84: 102067179570 | D84: SONAWANE NAGNATH KASHINATH | E84: PAINTER | G84: 1 | H84: 1 | I84: 1 | J84: 1 | L84: 1 | N84: 1 | O84: 2 | P84: 1 | Q84: 1 | R84: 2 | S84: 1 | T84: 1 | U84: 1 | V84: 1 | W84: 1 | X84: 1 | Y84: 1 | Z84: 1 | AB84: 1 | AC84: 1 | AD84: 1 | AE84: 1 | AF84: 1 | AG84: 1 | AH84: 1 | AI84: 1 | AJ84: =SUM(F84:AI84) -> 28 | AK84: =VLOOKUP(C84,'Name Details'!A:C,3,0) -> Mr. NAGANATH KASHINATH SONWANE | AL84: =VLOOKUP(B84,'[2]APRIL-2026'!$B$1:$J$65536,9,0) -> 450.61 | AM84: 450.61 | AN84: =VLOOKUP(C84,Work!D:F,3,0) -> Mr. NAGANATH KASHINATH SONWANE | AO84: =AN84=AK84 -> TRUE | AP84: FOU114
A85: 80 | B85: FOU209 | C85: 102086487131 | D85: SUDHAKAR BHIMASHANKAR KOGANURE | E85: PAINTER | I85: 1 | J85: 1 | O85: 1 | P85: 1 | Q85: 1 | R85: 1 | S85: 1 | U85: 1 | V85: 1 | W85: 1 | X85: 1 | Y85: 1 | Z85: 1 | AB85: 1 | AC85: 1 | AD85: 1 | AE85: 1 | AF85: 1 | AG85: 1 | AH85: 1 | AI85: 1 | AJ85: =SUM(F85:AI85) -> 21 | AK85: =VLOOKUP(C85,'Name Details'!A:C,3,0) -> Mr. SUDHAKAR BHIMASHANKAR KOGANURE | AL85: =VLOOKUP(B85,'[2]APRIL-2026'!$B$1:$J$65536,9,0) -> 402.39 | AM85: 402.39 | AN85: =VLOOKUP(C85,Work!D:F,3,0) -> Mr. SUDHAKAR BHIMASHANKAR KOGANURE | AO85: =AN85=AK85 -> TRUE | AP85: FOU209
A86: 81 | B86: FOU105 | C86: 102062761038 | D86: BASAVRAJ SHIVANNA KOLI | E86: PAINTER | G86: 1 | H86: 1 | I86: 1 | J86: 1 | K86: 1 | L86: 1 | N86: 1 | O86: 1 | P86: 1 | Q86: 1 | R86: 1 | S86: 1 | U86: 1 | V86: 1 | W86: 1 | X86: 1 | Y86: 1 | Z86: 1 | AB86: 1 | AC86: 1 | AD86: 1 | AE86: 1 | AG86: 1 | AH86: 1 | AI86: 1 | AJ86: =SUM(F86:AI86) -> 25 | AK86: =VLOOKUP(C86,'Name Details'!A:C,3,0) -> Mr. BASAVRAJ SHIVANNA KOLI | AL86: =VLOOKUP(B86,'[2]APRIL-2026'!$B$1:$J$65536,9,0) -> 357.04 | AM86: 357.04 | AN86: =VLOOKUP(C86,Work!D:F,3,0) -> Mr. BASAVRAJ SHIVANNA KOLI | AO86: =AN86=AK86 -> TRUE | AP86: FOU105
A87: 82 | B87: FOU375 | C87: 102032852951 | D87: KUMBHAR PRAKASH SHEMNIG | E87: PAINTER | F87: 1 | G87: 1 | H87: 1 | I87: 1 | J87: 1 | K87: 1 | L87: 1 | N87: 1 | O87: 1 | Q87: 1 | U87: 1 | V87: 1 | W87: 1 | X87: 1 | Y87: 1 | Z87: 1 | AB87: 1 | AC87: 1 | AD87: 1 | AE87: 1 | AF87: 1 | AG87: 1 | AH87: 1 | AI87: 1 | AJ87: =SUM(F87:AI87) -> 24 | AK87: =VLOOKUP(C87,'Name Details'!A:C,3,0) -> Mr. PRAKASH | AL87: =VLOOKUP(B87,'[2]APRIL-2026'!$B$1:$J$65536,9,0) -> 449.22 | AM87: 449.22 | AN87: =VLOOKUP(C87,Work!D:F,3,0) -> Mr. PRAKASH | AO87: =AN87=AK87 -> TRUE | AP87: FOU375
A88: 83 | B88: FOU461 | C88: 101678665637 | D88: GENSIDHHA AMASIDHHA VAMANE | E88: PAINTER | I88: 1 | K88: 1 | L88: 1 | M88: 1 | N88: 1 | O88: 1 | Q88: 1 | R88: 1 | S88: 1 | U88: 2 | W88: 1 | Y88: 1 | AB88: 1 | AC88: 1 | AD88: 1 | AE88: 1 | AF88: 1 | AG88: 1 | AJ88: =SUM(F88:AI88) -> 19 | AK88: =VLOOKUP(C88,'Name Details'!A:C,3,0) -> Mr. GHENSIDDHA AMASIDHDA VANAMANE | AL88: =VLOOKUP(B88,'[2]APRIL-2026'!$B$1:$J$65536,9,0) -> 49.09 | AM88: 49.09 | AN88: =VLOOKUP(C88,Work!D:F,3,0) -> Mr. GHENSIDDHA AMASIDHDA VANAMANE | AO88: =AN88=AK88 -> TRUE | AP88: FOU461
A89: 84 | B89: FOU60 | C89: 101966176359 | D89: BASVRAJ SHRISHAIL SODDE | E89: PAINTER | G89: 2 | H89: 2 | I89: 1 | J89: 1 | K89: 1 | L89: 2 | M89: 1 | N89: 1 | O89: 1 | R89: 1 | S89: 1 | V89: 1 | W89: 1 | X89: 1 | Z89: 1 | AA89: 1 | AB89: 1 | AC89: 1 | AD89: 1 | AE89: 1 | AF89: 1 | AG89: 1 | AJ89: =SUM(F89:AI89) -> 25 | AK89: =VLOOKUP(C89,'Name Details'!A:C,3,0) -> Mr. BASAVARAJ SHRISHAIL SODDE | AL89: =VLOOKUP(B89,'[2]APRIL-2026'!$B$1:$J$65536,9,0) -> 535.04 | AM89: 535.04 | AN89: =VLOOKUP(C89,Work!D:F,3,0) -> Mr. BASAVARAJ SHRISHAIL SODDE | AO89: =AN89=AK89 -> TRUE | AP89: FOU60
A90: 85 | B90: FOU685 | C90: 102261619396 | D90: TOLNURE KASHINATH SIDHRAM | E90: PAINTER | G90: 1 | H90: 1 | I90: 1 | J90: 1 | K90: 2 | L90: 1 | O90: 1 | P90: 1 | Q90: 1 | R90: 1 | S90: 1 | U90: 1 | V90: 1 | W90: 1 | X90: 1 | Y90: 1 | Z90: 1 | AA90: 1 | AB90: 1 | AC90: 1 | AD90: 1 | AJ90: =SUM(F90:AI90) -> 22 | AK90: =VLOOKUP(C90,'Name Details'!A:C,3,0) -> Mr. KASHINATH SIDHARAM TOLANURE | AL90: =VLOOKUP(B90,'[2]APRIL-2026'!$B$1:$J$65536,9,0) -> 441.69 | AM90: 441.69 | AN90: =VLOOKUP(C90,Work!D:F,3,0) -> Mr. KASHINATH SIDHARAM TOLANURE | AO90: =AN90=AK90 -> TRUE | AP90: FOU685
A91: 86 | B91: FOU674 | C91: 102260241245 | D91: DHANRAJ DATTATRAY SHINDE | E91: GENERAL | G91: 1 | H91: 1 | I91: 1 | J91: 1 | K91: 1 | N91: 1 | O91: 1 | P91: 1 | Q91: 1 | R91: 1 | V91: 1 | W91: 1 | Y91: 1 | Z91: 1 | AB91: 1 | AC91: 1 | AD91: 1 | AE91: 1 | AF91: 1 | AG91: 1 | AH91: 1 | AJ91: =SUM(F91:AI91) -> 21 | AK91: =VLOOKUP(C91,'Name Details'!A:C,3,0) -> Mr. DHANRAJ DATTATRAY SHINDE | AL91: =VLOOKUP(B91,'[2]APRIL-2026'!$B$1:$J$65536,9,0) -> 549.97 | AM91: 549.97 | AN91: =VLOOKUP(C91,Work!D:F,3,0) -> Mr. DHANRAJ DATTATRAY SHINDE | AO91: =AN91=AK91 -> TRUE | AP91: FOU674
A92: 87 | B92: FOU677 | C92: 102259643488 | D92: KATAKAR SAI MAHESH | E92: GENERAL | H92: 1 | I92: 1 | J92: 1 | K92: 1 | L92: 1 | N92: 1 | O92: 1 | P92: 1 | Q92: 1 | R92: 1 | S92: 1 | V92: 1 | W92: 1 | X92: 1 | Y92: 1 | Z92: 1 | AB92: 1 | AC92: 1 | AD92: 1 | AE92: 1 | AF92: 1 | AG92: 1 | AH92: 1 | AI92: 1 | AJ92: =SUM(F92:AI92) -> 24 | AK92: =VLOOKUP(C92,'Name Details'!A:C,3,0) -> Mr. SAI MAHESH KATKAR | AL92: =VLOOKUP(B92,'[2]APRIL-2026'!$B$1:$J$65536,9,0) -> 551.67 | AM92: 551.67 | AN92: =VLOOKUP(C92,Work!D:F,3,0) -> Mr. SAI MAHESH KATKAR | AO92: =AN92=AK92 -> TRUE | AP92: FOU677
A93: 89 | B93: FOU817 | C93: RAHUL BALU CHAVHAN | D93: RAHUL BALU CHAVAN | E93: GENERAL | H93: 1 | I93: 1 | J93: 1 | K93: 1 | L93: 1 | N93: 1 | O93: 1 | Q93: 1 | R93: 1 | S93: 1 | U93: 1 | V93: 1 | W93: 1 | X93: 1 | Y93: 1 | Z93: 1 | AB93: 1 | AC93: 1 | AD93: 1 | AE93: 1 | AI93: 1 | AJ93: =SUM(F93:AI93) -> 21 | AK93: =VLOOKUP(C93,'Name Details'!A:C,3,0) -> #N/A | AL93: =VLOOKUP(B93,'[2]APRIL-2026'!$B$1:$J$65536,9,0) -> 221.96 | AM93: 221.96 | AN93: =VLOOKUP(C93,Work!D:F,3,0) -> RAHUL BALU CHAVHAN | AO93: =AN93=AK93 -> #N/A | AP93: FOU817
A94: 91 | B94: FOU849 | C94: NAGESG REVANSIDHHA BIRAJDAR | D94: NAGESG REVANSIDHHA BIRAJDAR | E94: GENERAL | G94: 1 | H94: 1 | I94: 1 | J94: 1 | K94: 1 | L94: 1 | N94: 1 | O94: 1 | Q94: 1 | R94: 1 | S94: 1 | U94: 1 | V94: 1 | W94: 1 | Y94: 1 | Z94: 1 | AE94: 1 | AF94: 1 | AG94: 1 | AH94: 1 | AI94: 1 | AJ94: =SUM(F94:AI94) -> 21 | AK94: =VLOOKUP(C94,'Name Details'!A:C,3,0) -> #N/A | AL94: =VLOOKUP(B94,'[2]APRIL-2026'!$B$1:$J$65536,9,0) -> 84.65 | AM94: 84 | AN94: =VLOOKUP(C94,Work!D:F,3,0) -> NAGESG REVANSIDHHA BIRAJDAR | AO94: =AN94=AK94 -> #N/A | AP94: FOU849
A95: 92 | B95: FOU851 | C95: SHANKAR GIRMAL MALI | D95: SHANKAR GIRMAL MALI | E95: GENERAL | G95: 1 | H95: 1 | I95: 1 | J95: 1 | K95: 1 | L95: 1 | N95: 1 | O95: 1 | P95: 1 | Q95: 1 | R95: 1 | S95: 1 | U95: 1 | V95: 1 | W95: 1 | X95: 1 | Y95: 1 | Z95: 1 | AB95: 1 | AJ95: =SUM(F95:AI95) -> 19 | AK95: =VLOOKUP(C95,'Name Details'!A:C,3,0) -> #N/A | AL95: =VLOOKUP(B95,'[2]APRIL-2026'!$B$1:$J$65536,9,0) -> 296.29 | AM95: 296.29 | AN95: =VLOOKUP(C95,Work!D:F,3,0) -> SHANKAR GIRMAL MALI | AO95: =AN95=AK95 -> #N/A | AP95: FOU851
A96: 95 | B96: FOU855 | C96: 102004403215 | D96: KUSHAL PRASAD | E96: GENERAL | G96: 1 | H96: 1 | I96: 1 | L96: 1 | N96: 1 | Q96: 1 | AJ96: =SUM(F96:AI96) -> 6 | AK96: =VLOOKUP(C96,'Name Details'!A:C,3,0) -> #N/A | AL96: =VLOOKUP(B96,'[2]APRIL-2026'!$B$1:$J$65536,9,0) -> 107.8 | AM96: 107.8 | AN96: =VLOOKUP(C96,Work!D:F,3,0) -> KUSHAL PRASAD | AO96: =AN96=AK96 -> #N/A | AP96: FOU855
A97: 96 | B97: FOU856 | C97: 102315753105 | D97: CHANDRABHAN SINGH | E97: GENERAL | H97: 1 | I97: 1 | J97: 1 | N97: 1 | O97: 1 | Q97: 1 | R97: 1 | AJ97: =SUM(F97:AI97) -> 7 | AK97: =VLOOKUP(C97,'Name Details'!A:C,3,0) -> #N/A | AL97: =VLOOKUP(B97,'[2]APRIL-2026'!$B$1:$J$65536,9,0) -> 150.67 | AM97: 150.67 | AN97: =VLOOKUP(C97,Work!D:F,3,0) -> CHANDRABHAN SINGH | AO97: =AN97=AK97 -> #N/A | AP97: FOU856
A98: 97 | B98: FOU857 | C98: 101811097763 | D98: YUPENDRA KUMAR SANT | E98: GENERAL | G98: 1 | H98: 1 | I98: 1 | J98: 1 | K98: 1 | L98: 1 | N98: 1 | O98: 1 | Q98: 1 | R98: 1 | S98: 1 | T98: 1 | V98: 1 | W98: 1 | X98: 2 | Y98: 1 | Z98: 1 | AA98: 1 | AB98: 1 | AC98: 1 | AD98: 1 | AE98: 1 | AF98: 1 | AG98: 1 | AH98: 1 | AI98: 1 | AJ98: =SUM(F98:AI98) -> 27 | AK98: =VLOOKUP(C98,'Name Details'!A:C,3,0) -> Mr. YUPENDRA KUMAR SANT | AL98: =VLOOKUP(B98,'[2]APRIL-2026'!$B$1:$J$65536,9,0) -> 718.26 | AM98: 718.26 | AN98: =VLOOKUP(C98,Work!D:F,3,0) -> YUPENDRA KUMAR SINGH | AO98: =AN98=AK98 -> FALSE | AP98: FOU857
A99: 99 | B99: FOU859 | C99: 102315791438 | D99: RAGHVENDRA SINGH | E99: GENERAL | I99: 1 | J99: 1 | K99: 1 | L99: 1 | N99: 1 | O99: 1 | P99: 1 | Q99: 1 | R99: 1 | AJ99: =SUM(F99:AI99) -> 9 | AK99: =VLOOKUP(C99,'Name Details'!A:C,3,0) -> Mr. RAGHVENDRA SINGH | AL99: =VLOOKUP(B99,'[2]APRIL-2026'!$B$1:$J$65536,9,0) -> 107.41 | AM99: 107.41 | AN99: =VLOOKUP(C99,Work!D:F,3,0) -> RAGHVENDRA SINGH | AO99: =AN99=AK99 -> FALSE | AP99: FOU859
A100: 100 | B100: FOU860 | C100: 101938681040 | D100: CHAINSINGH CHINTASINGH MASARAM | E100: GENERAL | I100: 1 | J100: 1 | K100: 1 | L100: 1 | O100: 1 | P100: 1 | AJ100: =SUM(F100:AI100) -> 6 | AK100: =VLOOKUP(C100,'Name Details'!A:C,3,0) -> Mr. CHAIN SINGH | AL100: =VLOOKUP(B100,'[2]APRIL-2026'!$B$1:$J$65536,9,0) -> 43.26 | AM100: 43.26 | AN100: =VLOOKUP(C100,Work!D:F,3,0) -> CHAINSINGH CHINTASINGH MASARAM | AO100: =AN100=AK100 -> FALSE | AP100: FOU860
...

Sheet line-01 cupan
A1: sl_employee_code | B1: sl_employee_name | C1: Sum of Tea | D1: Sum of snack | E1: Sum of lunch | F1: Sum of TeaE | G1: Sum of snacks | H1: Sum of dinner | I1: Sum of empl_cost
A2: FOU67 | B2: SACHIN BHAGWAN GHANTE | C2: 0 | D2: 2 | E2: 6 | F2: 0 | G2: 0 | H2: 3 | I2: 171.17 | K2: =VLOOKUP(A2,'Google attandance April -26'!B:C,2,0) -> 100450352070 | L2: Line-01
A3: FOU61 | B3: DARGAPPA SHIVANAND ARWAT | C3: 0 | D3: 0 | E3: 0 | F3: 3 | G3: 6 | H3: 7 | I3: 186.79 | K3: =VLOOKUP(A3,'Google attandance April -26'!B:C,2,0) -> 100590315745 | L3: Line-01
A4: FOU514 | B4: MANGESH NAVNATH ANKUSHRAO_x000D_ | C4: 6 | D4: 8 | E4: 6 | F4: 0 | G4: 1 | H4: 0 | I4: 209.94 | K4: =VLOOKUP(A4,'Google attandance April -26'!B:C,2,0) -> 101084612898 | L4: Line-01
A5: FOU35 | B5: SAGAR RAMESH GHARSANGI | C5: 0 | D5: 0 | E5: 3 | F5: 0 | G5: 2 | H5: 0 | I5: 69.59 | K5: =VLOOKUP(A5,'Google attandance April -26'!B:C,2,0) -> 101154454730 | L5: Line-01
A6: FOU80 | B6: VISHAL MOHAN MANE | C6: 1 | D6: 2 | E6: 3 | F6: 0 | G6: 3 | H6: 3 | I6: 152.54 | K6: =VLOOKUP(A6,'Google attandance April -26'!B:C,2,0) -> 101235372414 | L6: Line-01
A7: FOU741 | B7: ANILKUMAR RAMLAL RAWAT_x000D_ | C7: 0 | D7: 4 | E7: 11 | F7: 1 | G7: 1 | H7: 7 | I7: 355.7 | K7: =VLOOKUP(A7,'Google attandance April -26'!B:C,2,0) -> 101241926666 | L7: Line-01
A8: FOU79 | B8: AVINASH NILKANTH PATANGE | C8: 0 | D8: 3 | E8: 7 | F8: 0 | G8: 0 | H8: 0 | I8: 146.71 | K8: =VLOOKUP(A8,'Google attandance April -26'!B:C,2,0) -> 101281737627 | L8: Line-01
A9: FOU27 | B9: KHALID ILAHI SHAIKH | C9: 0 | D9: 2 | E9: 1 | F9: 0 | G9: 3 | H9: 0 | I9: 63.93 | K9: =VLOOKUP(A9,'Google attandance April -26'!B:C,2,0) -> 101373078654 | L9: Line-01
A10: FOU47 | B10: RUSHIKESH CHANDRAKANT CHOUGULE | C10: 0 | D10: 1 | E10: 14 | F10: 0 | G10: 0 | H10: 0 | I10: 246.42 | K10: =VLOOKUP(A10,'Google attandance April -26'!B:C,2,0) -> 101388345766 | L10: Line-01
A11: FOU20 | B11: DATTATRAY ASHOK WAGHMODE | C11: 3 | D11: 9 | E11: 9 | F11: 1 | G11: 9 | H11: 0 | I11: 337.41 | K11: =VLOOKUP(A11,'Google attandance April -26'!B:C,2,0) -> 101391642731 | L11: Line-01
A12: FOU74 | B12: SHARANAPPA KHEDAGIKAR | C12: 0 | D12: 7 | E12: 7 | F12: 0 | G12: 5 | H12: 5 | I12: 315.96 | K12: =VLOOKUP(A12,'Google attandance April -26'!B:C,2,0) -> 101396804599 | L12: Line-01
A13: FOU19 | B13: NAMDEV BANDGAR | C13: 1 | D13: 11 | E13: 9 | F13: 0 | G13: 7 | H13: 10 | I13: 494.83 | K13: =VLOOKUP(A13,'Google attandance April -26'!B:C,2,0) -> 101407413648 | L13: Line-01
... A90: FOU852 | B90: YASH LAVHU KUMBHAR_x000D_ | C90: 0 | D90: 0 | E90: 0 | F90: 0 | G90: 1 | H90: 1 | I90: 26.33 | K90: =VLOOKUP(A90,'Google attandance April -26'!B:C,2,0) -> YASH LAVHU KUMBHAR | L90: Line-01
A91: FOU849 | B91: NAGESH REVANSIDDHA BIRAJDAR_x000D_ | C91: 0 | D91: 0 | E91: 0 | F91: 0 | G91: 0 | H91: 5 | I91: 84.65 | K91: =VLOOKUP(A91,'Google attandance April -26'!B:C,2,0) -> NAGESG REVANSIDHHA BIRAJDAR | L91: =VLOOKUP(A91,'[3]Attandance April-26'!C:D,2,0) -> #N/A | M91: =VLOOKUP(A91,#REF!,2,0) -> #REF!
A92: FOU881 | B92: SUNIL GANPAT WAGHMARE_x000D_ | C92: 0 | D92: 1 | E92: 2 | F92: 0 | G92: 0 | H92: 0 | I92: 43.26 | K92: =VLOOKUP(A92,'Google attandance April -26'!B:C,2,0) -> WAGHMARE SUNIL GANPAT | L92: =VLOOKUP(A92,'[3]Attandance April-26'!C:D,2,0) -> #N/A | M92: =VLOOKUP(A92,#REF!,2,0) -> #REF!
A93: FOU75 | B93: SAKIB SALIM SAYYED | C93: 0 | D93: 0 | E93: 20 | F93: 0 | G93: 0 | H93: 5 | I93: 423.25 | K93: =VLOOKUP(A93,'Google attandance April -26'!B:C,2,0) -> SAQIB SAYYAD | L93: =VLOOKUP(A93,'[3]Attandance April-26'!C:D,2,0) -> #N/A | M93: =VLOOKUP(A93,#REF!,2,0) -> #REF!
I94: =SUM(I2:I90) -> 25403.26
A96: FOU882 | B96: ABHISHEK SAYBANNA SARSAMBI_x000D_ | C96: 0 | D96: 0 | E96: 2 | F96: 0 | G96: 0 | H96: 2 | I96: 67.72 | K96: =VLOOKUP(A96,'Google attandance April -26'!B:C,2,0) -> #N/A | L96: =VLOOKUP(A96,'[3]Attandance April-26'!C:D,2,0) -> #N/A | M96: =VLOOKUP(A96,#REF!,2,0) -> #REF!
A97: FOU867 | B97: AKASH RAJSHEKHAR HADAPAD_x000D_ | C97: 0 | D97: 3 | E97: 4 | F97: 0 | G97: 0 | H97: 0 | I97: 95.92 | K97: =VLOOKUP(A97,'Google attandance April -26'!B:C,2,0) -> #N/A | L97: =VLOOKUP(A97,'[3]Attandance April-26'!C:D,2,0) -> #N/A | M97: =VLOOKUP(A97,#REF!,2,0) -> #REF!
A98: FOU267 | B98: AKASH RUDARPPA KOLI | C98: 1 | D98: 9 | E98: 15 | F98: 0 | G98: 0 | H98: 0 | I98: 342.51 | K98: =VLOOKUP(A98,'Google attandance April -26'!B:C,2,0) -> #N/A | L98: =VLOOKUP(A98,'[3]Attandance April-26'!C:D,2,0) -> #N/A | M98: =VLOOKUP(A98,#REF!,2,0) -> #REF!
A99: FOU868 | B99: AMIR SOHEL SHAKIL SHAIKH_x000D_ | C99: 0 | D99: 0 | E99: 1 | F99: 0 | G99: 0 | H99: 0 | I99: 16.93 | K99: =VLOOKUP(A99,'Google attandance April -26'!B:C,2,0) -> #N/A | L99: =VLOOKUP(A99,'[3]Attandance April-26'!C:D,2,0) -> #N/A | M99: =VLOOKUP(A99,#REF!,2,0) -> #REF!
A100: FOU792 | B100: ANIKET VIJAY DESHPANDE_x000D_ | C100: 9 | D100: 13 | E100: 13 | F100: 1 | G100: 2 | H100: 6 | I100: 502.27 | K100: =VLOOKUP(A100,'Google attandance April -26'!B:C,2,0) -> #N/A | L100: =VLOOKUP(A100,'[3]Attandance April-26'!C:D,2,0) -> #N/A | M100: =VLOOKUP(A100,#REF!,2,0) -> #REF!
A101: FOU883 | B101: ANIL SHILSIDDHA DESHMUKH_x000D_ | C101: 0 | D101: 1 | E101: 4 | F101: 0 | G101: 0 | H101: 0 | I101: 77.12 | K101: =VLOOKUP(A101,'Google attandance April -26'!B:C,2,0) -> #N/A | L101: =VLOOKUP(A101,'[3]Attandance April-26'!C:D,2,0) -> #N/A | M101: =VLOOKUP(A101,#REF!,2,0) -> #REF!
A102: FOU774 | B102: ASHISH JAGAN THAKARE_x000D_ | C102: 4 | D102: 6 | E102: 7 | F102: 1 | G102: 0 | H102: 3 | I102: 245.5 | K102: =VLOOKUP(A102,'Google attandance April -26'!B:C,2,0) -> #N/A | L102: =VLOOKUP(A102,'[3]Attandance April-26'!C:D,2,0) -> #N/A | M102: =VLOOKUP(A102,#REF!,2,0) -> #REF!
A103: FOU749 | B103: ATIK MEHABUB SHAIKH_x000D_ | C103: 0 | D103: 0 | E103: 20 | F103: 0 | G103: 0 | H103: 0 | I103: 338.6 | K103: =VLOOKUP(A103,'Google attandance April -26'!B:C,2,0) -> #N/A | L103: =VLOOKUP(A103,'[3]Attandance April-26'!C:D,2,0) -> #N/A | M103: =VLOOKUP(A103,#REF!,2,0) -> #REF!
A104: FOU182 | B104: DAMODAR MOHAN RATHOD | C104: 0 | D104: 0 | E104: 1 | F104: 0 | G104: 0 | H104: 0 | I104: 16.93 | K104: =VLOOKUP(A104,'Google attandance April -26'!B:C,2,0) -> #N/A | L104: =VLOOKUP(A104,'[3]Attandance April-26'!C:D,2,0) -> #N/A | M104: =VLOOKUP(A104,#REF!,2,0) -> #REF!
A105: FOU471 | B105: DIPAK DADARAO GHODAKE_x000D_ | C105: 2 | D105: 8 | E105: 18 | F105: 0 | G105: 0 | H105: 0 | I105: 387.86 | K105: =VLOOKUP(A105,'Google attandance April -26'!B:C,2,0) -> #N/A | L105: =VLOOKUP(A105,'[3]Attandance April-26'!C:D,2,0) -> #N/A | M105: =VLOOKUP(A105,#REF!,2,0) -> #REF!
A106: FOU870 | B106: DIPAK RAJKUMAR PATIL_x000D_ | C106: 0 | D106: 0 | E106: 1 | F106: 0 | G106: 0 | H106: 0 | I106: 16.93 | K106: =VLOOKUP(A106,'Google attandance April -26'!B:C,2,0) -> #N/A | L106: =VLOOKUP(A106,'[3]Attandance April-26'!C:D,2,0) -> #N/A | M106: =VLOOKUP(A106,#REF!,2,0) -> #REF!
A107: FOU512 | B107: FOU512 | C107: 0 | D107: 1 | E107: 5 | F107: 2 | G107: 1 | H107: 2 | I107: 145.23 | K107: =VLOOKUP(A107,'Google attandance April -26'!B:C,2,0) -> #N/A | L107: =VLOOKUP(A107,'[3]Attandance April-26'!C:D,2,0) -> #N/A | M107: =VLOOKUP(A107,#REF!,2,0) -> #REF!
... A135: FOU863 | B135: ZAFAR TAJODDIN SHAIKH_x000D_ | C135: 0 | D135: 0 | E135: 26 | F135: 0 | G135: 0 | H135: 0 | I135: 440.18 | K135: =VLOOKUP(A135,'Google attandance April -26'!B:C,2,0) -> #N/A | L135: =VLOOKUP(A135,'[3]Attandance April-26'!C:D,2,0) -> #N/A | M135: =VLOOKUP(A135,#REF!,2,0) -> #REF!

Sheet Name Details
A1: UAN | B1: Member ID | C1: Name | D1: Gender | E1: DoB | F1: DoJ | G1: Father's/Husband's Name | H1: Relation | I1: Marital Status | J1: Mobile | K1: Email ID | L1: AADHAAR | M1: PAN | N1: Bank Account No, IFSC Code | O1: Nomination Filed | P1: Is AADHAAR Verified | Q1: Face Auth Status
A2: 102161560824 | B2: PUPUN03049230000017645 | C2: Mr. OMPRAKASH YADAV | D2: MALE | E2: 37257 | F2: 46122 | G2: HARE KRISHNA YADAV | H2: FATHER | I2: UN-MARRIED | J2: 9973335319 | K2: NOT AVAILABLE | L2: XXXX XXXX 0028 | M2: XXKPY732XX | N2: NOT AVAILABLE | O2: NO | P2: YES | Q2: NO
A3: 102279600512 | B3: PUPUN03049230000017646 | C3: Mr. SUJIT KUMAR | D3: MALE | E3: 37397 | F3: 46122 | G3: SADHU YADAV | H3: FATHER | I3: UN-MARRIED | J3: 7970814249 | K3: NOT AVAILABLE | L3: XXXX XXXX 0339 | M3: NOT AVAILABLE | N3: NOT AVAILABLE | O3: NO | P3: YES | Q3: YES
A4: 100412248357 | B4: PUPUN03049230000017644 | C4: Mr. VIDWAN MANIK GAIKWAD | D4: MALE | E4: 25968 | F4: 46122 | G4: MANIK BHIVAJI GAIKWAD | H4: FATHER | I4: MARRIED | J4: 9860994251 | K4: vidwan1972@hotmail.com | L4: XXXX XXXX 5411 | M4: XXDPG469XX | N4: 397400040006XXXX,IFSC:PUNB0397400 | O4: NO | P4: YES | Q4: NO
A5: 101774109561 | B5: PUPUN03049230000017643 | C5: Mr. SATYENDRA KUMAR SAH | D5: MALE | E5: 36558 | F5: 46122 | G5: JAYPAL SAH | H5: FATHER | I5: UN-MARRIED | J5: 8521804335 | K5: NOT AVAILABLE | L5: XXXX XXXX 4488 | M5: NOT AVAILABLE | N5: NOT AVAILABLE | O5: NO | P5: YES | Q5: NO
A6: 102194831292 | B6: PUPUN03049230000017647 | C6: Mr. MUKESH KUMAR CHAUHAN | D6: MALE | E6: 36260 | F6: 46122 | G6: HARIBADAN CHAUHAN | H6: FATHER | I6: UN-MARRIED | J6: 9839688319 | K6: NOT AVAILABLE | L6: XXXX XXXX 4886 | M6: XXKPC078XX | N6: 4183639XXXX,IFSC:SBIN0011202 | O6: NO | P6: YES | Q6: YES
A7: 102320395682 | B7: PUPUN03049230000017642 | C7: Mr. NASEEM ANSARI | D7: MALE | E7: 38903 | F7: 46115 | G7: HASHIM ANSARI | H7: FATHER | I7: UN-MARRIED | J7: 7565956756 | K7: NOT AVAILABLE | L7: XXXX XXXX 0851 | M7: NOT AVAILABLE | N7: NOT AVAILABLE | O7: NO | P7: YES | Q7: YES
A8: 102269192148 | B8: PUPUN03049230000017635 | C8: Mr. SANJOY MAJI | D8: MALE | E8: 33507 | F8: 46097 | G8: JATINDRANATH MAJI | H8: FATHER | I8: MARRIED | J8: 9156038859 | K8: NOT AVAILABLE | L8: XXXX XXXX 2586 | M8: NOT AVAILABLE | N8: NOT AVAILABLE | O8: NO | P8: YES | Q8: YES
A9: 100542709791 | B9: PUPUN03049230000017648 | C9: Mr. SHRINIWAS AMBAJI MADGUNDI | D9: MALE | E9: 33414 | F9: 46097 | G9: AMBAJI | H9: FATHER | I9: MARRIED | J9: 9325655899 | K9: shrimadgundi7241@gmail.com | L9: XXXX XXXX 7002 | M9: XXRPM617XX | N9: 587004200003XXXX,IFSC:SJSB0000004 | O9: YES | P9: YES | Q9: NO
A10: 102315785207 | B10: PUPUN03049230000017640 | C10: Mr. KHELAVAN SINGH | D10: MALE | E10: 38718 | F10: 46082 | G10: BIHARI SINGH | H10: FATHER | I10: MARRIED | J10: 9175414038 | K10: NOT AVAILABLE | L10: XXXX XXXX 6713 | M10: NOT AVAILABLE | N10: NOT AVAILABLE | O10: NO | P10: YES | Q10: YES
A11: 101938681040 | B11: PUPUN03049230000017637 | C11: Mr. CHAIN SINGH | D11: MALE | E11: 37300 | F11: 46082 | G11: CHINTA SINGH | H11: FATHER | I11: MARRIED | J11: NOT AVAILABLE | K11: NOT AVAILABLE | L11: XXXX XXXX 5983 | M11: NOT AVAILABLE | N11: NOT AVAILABLE | O11: NO | P11: YES | Q11: NO
A12: 102315791438 | B12: PUPUN03049230000017638 | C12: Mr. RAGHVENDRA SINGH | D12: MALE | E12: 38523 | F12: 46082 | G12: DURVENDRA SINGH | H12: FATHER | I12: UN-MARRIED | J12: 6261472402 | K12: NOT AVAILABLE | L12: XXXX XXXX 6223 | M12: NOT AVAILABLE | N12: NOT AVAILABLE | O12: NO | P12: YES | Q12: YES
A13: 101811097763 | B13: PUPUN03049230000017639 | C13: Mr. YUPENDRA KUMAR SANT | D13: MALE | E13: 36036 | F13: 46082 | G13: ANAND KUMAR SANT | H13: FATHER | I13: UN-MARRIED | J13: 7974857512 | K13: raudiravansant@gmail.com | L13: XXXX XXXX 3983 | M13: XXBPS911XX | N13: 725700010006XXXX,IFSC:PUNB0725700 | O13: NO | P13: YES | Q13: NO
A14: 102315781772 | B14: PUPUN03049230000017641 | C14: Mr. INDARPAL SINGH | D14: MALE | E14: 38530 | F14: 46082 | G14: SOHAN SINGH | H14: FATHER | I14: UN-MARRIED | J14: 9244319045 | K14: NOT AVAILABLE | L14: XXXX XXXX 4972 | M14: NOT AVAILABLE | N14: NOT AVAILABLE | O14: NO | P14: YES | Q14: YES
A15: 102199452069 | B15: PUPUN03049230000017631 | C15: Mr. ASHOK KUMAR | D15: MALE | E15: 25674 | F15: 46071 | G15: SHITLA | H15: FATHER | I15: MARRIED | J15: 8007632015 | K15: NOT AVAILABLE | L15: XXXX XXXX 3170 | M15: XXOPK863XX | N15: 03421081XXXX,IFSC:IPOS0000001 | O15: YES | P15: YES | Q15: YES
A16: 102292277476 | B16: PUPUN03049230000017633 | C16: Mr. ASHISH KUMAR | D16: MALE | E16: 38518 | F16: 46068 | G16: VIJAY RAM | H16: FATHER | I16: UN-MARRIED | J16: 8168715981 | K16: NOT AVAILABLE | L16: XXXX XXXX 2200 | M16: NOT AVAILABLE | N16: NOT AVAILABLE | O16: NO | P16: YES | Q16: YES
A17: 102099259275 | B17: PUPUN03049230000017629 | C17: Mr. CHANDAN KUMAR | D17: MALE | E17: 36526 | F17: 46068 | G17: MANOJ SAHANI | H17: FATHER | I17: UN-MARRIED | J17: 7480035022 | K17: NOT AVAILABLE | L17: XXXX XXXX 3341 | M17: XXUPK071XX | N17: 391600040003XXXX,IFSC:PUNB0391600 | O17: NO | P17: YES | Q17: NO
A18: 102302651763 | B18: PUPUN03049230000017630 | C18: Mr. SACHIN MANDAL | D18: MALE | E18: 30317 | F18: 46068 | G18: PREMKUMAR MANDAL | H18: FATHER | I18: MARRIED | J18: 6203491843 | K18: NOT AVAILABLE | L18: XXXX XXXX 1694 | M18: NOT AVAILABLE | N18: NOT AVAILABLE | O18: NO | P18: YES | Q18: YES
A19: 102118237721 | B19: PUPUN03049230000017632 | C19: Mr. NASIR KHAN | D19: MALE | E19: 37987 | F19: 46068 | G19: MD CHHOTAN | H19: FATHER | I19: MARRIED | J19: 6207509485 | K19: NOT AVAILABLE | L19: XXXX XXXX 0726 | M19: NOT AVAILABLE | N19: NOT AVAILABLE | O19: NO | P19: YES | Q19: YES
A20: 102267273482 | B20: PUPUN03049230000017628 | C20: Mr. RAJA RAM | D20: MALE | E20: 38353 | F20: 46068 | G20: RAJESH RAM | H20: FATHER | I20: UN-MARRIED | J20: 9661108945 | K20: NOT AVAILABLE | L20: XXXX XXXX 3114 | M20: NOT AVAILABLE | N20: NOT AVAILABLE | O20: NO | P20: YES | Q20: YES
A21: 102246450834 | B21: PUPUN03049230000017627 | C21: Mr. SONU KUMAR | D21: MALE | E21: 39200 | F21: 46068 | G21: MUNNA SHAH | H21: FATHER | I21: UN-MARRIED | J21: 7666157554 | K21: NOT AVAILABLE | L21: XXXX XXXX 5756 | M21: NOT AVAILABLE | N21: 3687516XXXX,IFSC:SBIN0017474 | O21: NO | P21: YES | Q21: YES
A22: 101380526986 | B22: PUPUN03049230000017616 | C22: Mr. SAMAYLAL LONI | D22: MALE | E22: 31660 | F22: 46066 | G22: SREE RAMKRIPAL LONI | H22: FATHER | I22: UN-MARRIED | J22: NOT AVAILABLE | K22: NOT AVAILABLE | L22: XXXX XXXX 7683 | M22: NOT AVAILABLE | N22: NOT AVAILABLE | O22: NO | P22: YES | Q22: NO
A23: 101792182254 | B23: PUPUN03049230000017617 | C23: Mr. PRADEEP PARASRAM BHAMBAL | D23: MALE | E23: 35376 | F23: 46066 | G23: PARASRAM | H23: FATHER | I23: UN-MARRIED | J23: 7028230282 | K23: NOT AVAILABLE | L23: XXXX XXXX 6980 | M23: NOT AVAILABLE | N23: NOT AVAILABLE | O23: NO | P23: YES | Q23: NO
A24: 101816030649 | B24: PUPUN03049230000017615 | C24: Mr. SURAJ PINTU SARODE | D24: MALE | E24: 38049 | F24: 46065 | G24: PINTU SARODE | H24: FATHER | I24: UN-MARRIED | J24: 9960614508 | K24: NOT AVAILABLE | L24: XXXX XXXX 9876 | M24: NOT AVAILABLE | N24: NOT AVAILABLE | O24: NO | P24: YES | Q24: NO
A25: 102295910039 | B25: PUPUN03049230000017614 | C25: Mr. AFATAB HUSAIN | D25: MALE | E25: 28856 | F25: 46055 | G25: FAJAL MANSOORI | H25: FATHER | I25: MARRIED | J25: 8115847878 | K25: NOT AVAILABLE | L25: XXXX XXXX 9637 | M25: NOT AVAILABLE | N25: NOT AVAILABLE | O25: NO | P25: YES | Q25: YES
A26: 102268839888 | B26: PUPUN03049230000017636 | C26: Mr. AMAN RAMAYAN CHAUDHARI | D26: MALE | E26: 38553 | F26: 46054 | G26: RAMAYAN | H26: FATHER | I26: UN-MARRIED | J26: 7066139711 | K26: amanchaudhari706@gmail.com | L26: XXXX XXXX 9758 | M26: NOT AVAILABLE | N26: 4407095XXXX,IFSC:SBIN0018913 | O26: YES | P26: YES | Q26: YES
A27: 102295791735 | B27: PUPUN03049230000017613 | C27: Mr. SADDAM HUSEN | D27: MALE | E27: 33573 | F27: 46053 | G27: MOHMMAD IBRAHEEM | H27: FATHER | I27: MARRIED | J27: 8932895896 | K27: NOT AVAILABLE | L27: XXXX XXXX 3876 | M27: NOT AVAILABLE | N27: NOT AVAILABLE | O27: NO | P27: YES | Q27: YES
A28: 101849583125 | B28: PUPUN03049230000017612 | C28: Mr. SAHEVAJ | D28: MALE | E28: 37622 | F28: 46052 | G28: CHOTE KHAN | H28: FATHER | I28: UN-MARRIED | J28: 8291283301 | K28: NOT AVAILABLE | L28: XXXX XXXX 2345 | M28: XXYPS343XX | N28: 804911XXXX,IFSC:KKBK0000635 | O28: NO | P28: YES | Q28: NO
A29: 101734395186 | B29: PUPUN03049230000017624 | C29: Mr. BILAL NADAF | D29: MALE | E29: 37087 | F29: 46051 | G29: LADALEMASHK | H29: FATHER | I29: UN-MARRIED | J29: NOT AVAILABLE | K29: NOT AVAILABLE | L29: XXXX XXXX 1618 | M29: NOT AVAILABLE | N29: NOT AVAILABLE | O29: NO | P29: YES | Q29: NO
A30: 102004752885 | B30: PUPUN03049230000017611 | C30: Mr. MD SOHAIL | D30: MALE | E30: 38518 | F30: 46049 | G30: MOHAMMAD JIYAUDDIN | H30: FATHER | I30: UN-MARRIED | J30: 8401635622 | K30: NOT AVAILABLE | L30: XXXX XXXX 9979 | M30: XXFPS995XX | N30: 4427810000XXXX,IFSC:BARB0SARAIY | O30: NO | P30: YES | Q30: NO
A31: 101931792845 | B31: PUPUN03049230000017625 | C31: Mr. SHRIKANT BHIMRAO JAVIR | D31: MALE | E31: 36124 | F31: 46044 | G31: BHIMRAO | H31: FATHER | I31: MARRIED | J31: 9552516461 | K31: NOT AVAILABLE | L31: XXXX XXXX 4078 | M31: XXJPJ545XX | N31: 132610010000XXXX,IFSC:PUNB0132610 | O31: NO | P31: YES | Q31: YES
A32: 102290842339 | B32: PUPUN03049230000017610 | C32: Mr. SHIVAM MAURYA | D32: MALE | E32: 39142 | F32: 46040 | G32: SETU BANDH | H32: FATHER | I32: UN-MARRIED | J32: 9175303248 | K32: NOT AVAILABLE | L32: XXXX XXXX 4725 | M32: NOT AVAILABLE | N32: NOT AVAILABLE | O32: NO | P32: YES | Q32: YES
A33: 102290400560 | B33: PUPUN03049230000017609 | C33: Mr. BHAGWANDAS | D33: MALE | E33: 33970 | F33: 46038 | G33: MANSINGH | H33: FATHER | I33: MARRIED | J33: 8815555028 | K33: NOT AVAILABLE | L33: XXXX XXXX 1583 | M33: NOT AVAILABLE | N33: NOT AVAILABLE | O33: NO | P33: YES | Q33: YES
A34: 101638206486 | B34: PUPUN03049230000017608 | C34: Mr. AMRAT LODHI | D34: MALE | E34: 34844 | F34: 46037 | G34: MANKA | H34: FATHER | I34: UN-MARRIED | J34: 7470607664 | K34: NOT AVAILABLE | L34: XXXX XXXX 9187 | M34: NOT AVAILABLE | N34: NOT AVAILABLE | O34: NO | P34: YES | Q34: NO
A35: 101749732383 | B35: PUPUN03049230000017607 | C35: Mr. ROHAN SANJAY PAWAR | D35: MALE | E35: 37842 | F35: 46033 | G35: SANJAY PAWAR | H35: FATHER | I35: UN-MARRIED | J35: 7620208336 | K35: NOT AVAILABLE | L35: XXXX XXXX 4517 | M35: NOT AVAILABLE | N35: 07591821000XXXX,IFSC:BKID0000759 | O35: NO | P35: YES | Q35: NO
A36: 102268259486 | B36: PUPUN03049230000017619 | C36: Mr. AMOL VASANTRAO RAUT | D36: MALE | E36: 33281 | F36: 46030 | G36: VASANTRAO RAUT | H36: FATHER | I36: UN-MARRIED | J36: 9373470212 | K36: NOT AVAILABLE | L36: XXXX XXXX 3509 | M36: NOT AVAILABLE | N36: NOT AVAILABLE | O36: NO | P36: YES | Q36: YES
A37: 101822267804 | B37: PUPUN03049230000017622 | C37: Mr. SHUBHAM ASHOKRAO TALAN | D37: MALE | E37: 35065 | F37: 46030 | G37: ASHOKRAO TALAN | H37: FATHER | I37: UN-MARRIED | J37: 9529372469 | K37: NOT AVAILABLE | L37: XXXX XXXX 3512 | M37: XXVPT558XX | N37: 11004180XXXX,IFSC:CNRB0007830 | O37: NO | P37: YES | Q37: YES
A38: 101521189710 | B38: PUPUN03049230000017618 | C38: Mr. DEVANAND NARENDRA SHINDE | D38: MALE | E38: 35797 | F38: 46030 | G38: NARENDRA | H38: FATHER | I38: UN-MARRIED | J38: 8799846077 | K38: NOT AVAILABLE | L38: XXXX XXXX 2665 | M38: XXPPS485XX | N38: 03121019XXXX,IFSC:IPOS0000001 | O38: NO | P38: YES | Q38: NO
A39: 101117552862 | B39: PUPUN03049230000017620 | C39: Mr. ASHISH JAGAN THAKARE | D39: MALE | E39: 34794 | F39: 46029 | G39: JAGAN | H39: FATHER | I39: UN-MARRIED | J39: 9834711938 | K39: NOT AVAILABLE | L39: XXXX XXXX 9022 | M39: NOT AVAILABLE | N39: NOT AVAILABLE | O39: NO | P39: YES | Q39: YES
A40: 102286814849 | B40: PUPUN03049230000017604 | C40: Mr. AKASH | D40: MALE | E40: 39449 | F40: 46029 | G40: NANDLAL | H40: FATHER | I40: UN-MARRIED | J40: 8200872750 | K40: NOT AVAILABLE | L40: XXXX XXXX 9941 | M40: NOT AVAILABLE | N40: NOT AVAILABLE | O40: NO | P40: YES | Q40: YES
A41: 102216171955 | B41: PUPUN03049230000017634 | C41: Mr. RAMESHWAR YADUNAT LANJE | D41: MALE | E41: 38463 | F41: 46027 | G41: YADUNAT | H41: FATHER | I41: UN-MARRIED | J41: 8149145698 | K41: NOT AVAILABLE | L41: XXXX XXXX 7379 | M41: XXXPL965XX | N41: 4163810000XXXX,IFSC:BARB0TUMSAR | O41: NO | P41: YES | Q41: YES
... A45: 100416179810 | B45: PUPUN03049230000017623 | C45: Mr. YOGINATH TUKARAM GHODAKE | D45: MALE | E45: 31266 | F45: 46024 | G45: TUKARAM | H45: FATHER | I45: MARRIED | J45: 9158258883 | K45: yoginathg@gmail.com | L45: XXXX XXXX 8492 | M45: XXDPG485XX | N45: 067710400003XXXX,IFSC:IBKL0000677 | O45: NO | P45: YES | Q45: YES
A46: 101595174770 | B46: PUPUN03049230000017606 | C46: Mr. SHAKIL SALIM SHAIKH | D46: MALE | E46: 37124 | F46: 46023 | G46: SALIM | H46: FATHER | I46: UN-MARRIED | J46: NOT AVAILABLE | K46: NOT AVAILABLE | L46: XXXX XXXX 8998 | M46: NOT AVAILABLE | N46: NOT AVAILABLE | O46: NO | P46: YES | Q46: NO
A47: 102284116707 | B47: PUPUN03049230000017601 | C47: Mr. LAKSHMAN VARMA | D47: MALE | E47: 29822 | F47: 46021 | G47: BAIJNATH RAM | H47: FATHER | I47: MARRIED | J47: 6205420657 | K47: NOT AVAILABLE | L47: XXXX XXXX 0670 | M47: NOT AVAILABLE | N47: NOT AVAILABLE | O47: NO | P47: YES | Q47: YES
A48: 102284112416 | B48: PUPUN03049230000017600 | C48: Mr. SANTOSH PASWAN | D48: MALE | E48: 30682 | F48: 46021 | G48: MANIK PASWAN | H48: FATHER | I48: MARRIED | J48: 8340310400 | K48: NOT AVAILABLE | L48: XXXX XXXX 2640 | M48: NOT AVAILABLE | N48: NOT AVAILABLE | O48: NO | P48: YES | Q48: YES
A49: 102284274852 | B49: PUPUN03049230000017598 | C49: Mr. VISHWA BHANUDAS VIDYAGAR | D49: MALE | E49: 32013 | F49: 46021 | G49: BHANUDAS VIDYAGAR | H49: FATHER | I49: MARRIED | J49: 9096984514 | K49: NOT AVAILABLE | L49: XXXX XXXX 2315 | M49: NOT AVAILABLE | N49: NOT AVAILABLE | O49: NO | P49: YES | Q49: YES
A50: 102284114600 | B50: PUPUN03049230000017602 | C50: Mr. SHASHI KUMAR PASWAN | D50: MALE | E50: 29569 | F50: 46021 | G50: GOPI RAM | H50: FATHER | I50: MARRIED | J50: 7903827373 | K50: NOT AVAILABLE | L50: XXXX XXXX 7940 | M50: NOT AVAILABLE | N50: NOT AVAILABLE | O50: NO | P50: YES | Q50: YES
A51: 101335603244 | B51: PUPUN03049230000017596 | C51: Mr. PRAKASH SIDRAM JAUNJI | D51: MALE | E51: 35023 | F51: 46020 | G51: SIDRAM JAUNJI | H51: FATHER | I51: UN-MARRIED | J51: 8806945143 | K51: NOT AVAILABLE | L51: XXXX XXXX 1349 | M51: XXNPJ670XX | N51: 4526810000XXXX,IFSC:BARB0HOTAGI | O51: NO | P51: YES | Q51: NO
A52: 101893899863 | B52: PUPUN03049230000017593 | C52: Mr. SAINATH MOHAN FALAKE | D52: MALE | E52: 37595 | F52: 46018 | G52: MOHAN | H52: FATHER | I52: UN-MARRIED | J52: 8600197565 | K52: NOT AVAILABLE | L52: XXXX XXXX 7856 | M52: XXWPF735XX | N52: 1014010001XXXX,IFSC:BARB0RAISHO | O52: YES | P52: YES | Q52: NO
A53: 101136852910 | B53: PUPUN03049230000017595 | C53: Mr. YOGIRAJ BASAVRAJ KINAGI | D53: MALE | E53: 35363 | F53: 46018 | G53: BASAVRAJ | H53: FATHER | I53: UN-MARRIED | J53: 7020945495 | K53: NOT AVAILABLE | L53: XXXX XXXX 8375 | M53: XXJPK502XX | N53: 0437810001XXXX,IFSC:BARB0SHOLAP | O53: NO | P53: YES | Q53: NO
A54: 101861852981 | B54: PUPUN03049230000017594 | C54: Mr. VICKY AADINATH PAWAR | D54: MALE | E54: 37187 | F54: 46018 | G54: AADINATH | H54: FATHER | I54: UN-MARRIED | J54: 7620332625 | K54: NOT AVAILABLE | L54: XXXX XXXX 8335 | M54: XXLPP746XX | N54: 1014010001XXXX,IFSC:BARB0RAISHO | O54: NO | P54: YES | Q54: NO
A55: 102282679897 | B55: PUPUN03049230000017591 | C55: Mr. HUKUM SINGH | D55: MALE | E55: 37073 | F55: 46017 | G55: RAJ BAHADUR SHIGH | H55: FATHER | I55: UN-MARRIED | J55: 8815046349 | K55: NOT AVAILABLE | L55: XXXX XXXX 1319 | M55: NOT AVAILABLE | N55: NOT AVAILABLE | O55: NO | P55: YES | Q55: YES
A56: 102014097019 | B56: PUPUN03049230000017592 | C56: Mr. PANNALAL | D56: MALE | E56: 38535 | F56: 46017 | G56: MOHANLAL | H56: FATHER | I56: UN-MARRIED | J56: 9306705876 | K56: NOT AVAILABLE | L56: XXXX XXXX 0906 | M56: NOT AVAILABLE | N56: NOT AVAILABLE | O56: NO | P56: YES | Q56: NO
A57: 101324033174 | B57: PUPUN03049230000017626 | C57: Mr. ATIK MEHABUB SHAIKH | D57: MALE | E57: 34869 | F57: 46017 | G57: MEHABUB SHAIKH | H57: FATHER | I57: UN-MARRIED | J57: 8007461520 | K57: NOT AVAILABLE | L57: XXXX XXXX 6957 | M57: XXPPS314XX | N57: 0437010001XXXX,IFSC:BARB0SHOLAP | O57: YES | P57: YES | Q57: NO
A58: 102281497418 | B58: PUPUN03049230000017588 | C58: Mr. MANMATH SUDHAKAR RAJURE | D58: MALE | E58: 32143 | F58: 46014 | G58: SUDHAKAR RAJURE | H58: FATHER | I58: MARRIED | J58: 8010564451 | K58: NOT AVAILABLE | L58: XXXX XXXX 9582 | M58: NOT AVAILABLE | N58: NOT AVAILABLE | O58: NO | P58: YES | Q58: YES
... A87: 101104779218 | B87: PUPUN03049230000017550 | C87: Mr. SADANAND GURUNATH JEURE | D87: MALE | E87: 36088 | F87: 45988 | G87: GURUNATH | H87: FATHER | I87: UN-MARRIED | J87: 9765533672 | K87: NOT AVAILABLE | L87: XXXX XXXX 3697 | M87: XXIPJ684XX | N87: 1014810001XXXX,IFSC:BARB0RAISHO | O87: YES | P87: YES | Q87: NO
A88: 101567205168 | B88: PUPUN03049230000017597 | C88: Mr. AMOL SIDDHU MENGLE | D88: MALE | E88: 35431 | F88: 45988 | G88: SIDDHU MENGLE | H88: FATHER | I88: UN-MARRIED | J88: NOT AVAILABLE | K88: NOT AVAILABLE | L88: XXXX XXXX 8058 | M88: NOT AVAILABLE | N88: NOT AVAILABLE | O88: NO | P88: YES | Q88: NO
A89: 102269991035 | B89: PUPUN03049230000017548 | C89: Mr. MOHAMMADYASIN FARUK ANSARI | D89: MALE | E89: 34224 | F89: 45986 | G89: FARUK | H89: FATHER | I89: UN-MARRIED | J89: 9860308259 | K89: NOT AVAILABLE | L89: XXXX XXXX 0596 | M89: NOT AVAILABLE | N89: NOT AVAILABLE | O89: NO | P89: YES | Q89: YES
A90: 101956422754 | B90: PUPUN03049230000017547 | C90: Mr. FAZAL RAFIK JAHAGIRDAR | D90: MALE | E90: 38112 | F90: 45986 | G90: RAFIK JAHAGIRDAR | H90: FATHER | I90: UN-MARRIED | J90: NOT AVAILABLE | K90: NOT AVAILABLE | L90: XXXX XXXX 0407 | M90: NOT AVAILABLE | N90: NOT AVAILABLE | O90: NO | P90: YES | Q90: NO
A91: 102269989477 | B91: PUPUN03049230000017549 | C91: Mr. IQBAL JAINODDIN SHAIKH | D91: MALE | E91: 37791 | F91: 45986 | G91: JAINODDIN | H91: FATHER | I91: UN-MARRIED | J91: 7721966159 | K91: NOT AVAILABLE | L91: XXXX XXXX 9872 | M91: NOT AVAILABLE | N91: NOT AVAILABLE | O91: NO | P91: YES | Q91: YES
A92: 102269815358 | B92: PUPUN03049230000017546 | C92: Mr. FAZLE HAQ | D92: MALE | E92: 38170 | F92: 45985 | G92: MOHAMMAD MUSTAQEEM | H92: FATHER | I92: UN-MARRIED | J92: 7709372142 | K92: NOT AVAILABLE | L92: XXXX XXXX 3998 | M92: NOT AVAILABLE | N92: NOT AVAILABLE | O92: NO | P92: YES | Q92: YES
A93: 102269618576 | B93: PUPUN03049230000017545 | C93: Mr. RAJESH PATEL | D93: MALE | E93: 33756 | F93: 45984 | G93: PANCHAM PATEL | H93: FATHER | I93: MARRIED | J93: 8623061848 | K93: NOT AVAILABLE | L93: XXXX XXXX 6420 | M93: NOT AVAILABLE | N93: NOT AVAILABLE | O93: NO | P93: YES | Q93: YES
A94: 100268415748 | B94: PUPUN03049230000017543 | C94: Mr. PARMESHWAR KASHINATH BHOPALE | D94: MALE | E94: 32143 | F94: 45982 | G94: KASHINATH | H94: FATHER | I94: UN-MARRIED | J94: 9823444605 | K94: NOT AVAILABLE | L94: XXXX XXXX 3548 | M94: XXBPB924XX | N94: 07011011000XXXX,IFSC:BKID0000701 | O94: YES | P94: YES | Q94: NO
A95: 102268893829 | B95: PUPUN03049230000017542 | C95: Mr. IMRAT | D95: MALE | E95: 39083 | F95: 45982 | G95: SHANKAR | H95: FATHER | I95: UN-MARRIED | J95: 6267989063 | K95: NOT AVAILABLE | L95: XXXX XXXX 1107 | M95: NOT AVAILABLE | N95: NOT AVAILABLE | O95: NO | P95: YES | Q95: YES
A96: 102268547543 | B96: PUPUN03049230000017539 | C96: Mr. SHRIKANT GURUNATH SHINDE | D96: MALE | E96: 33239 | F96: 45982 | G96: GURUNATH SHINDE | H96: FATHER | I96: MARRIED | J96: 9604633600 | K96: NOT AVAILABLE | L96: XXXX XXXX 2067 | M96: NOT AVAILABLE | N96: NOT AVAILABLE | O96: NO | P96: YES | Q96: YES
A97: 101977166071 | B97: PUPUN03049230000017538 | C97: Mr. DEEPAK RAJU KOLI | D97: MALE | E97: 37608 | F97: 45982 | G97: RAJU | H97: FATHER | I97: UN-MARRIED | J97: NOT AVAILABLE | K97: NOT AVAILABLE | L97: XXXX XXXX 4029 | M97: NOT AVAILABLE | N97: NOT AVAILABLE | O97: NO | P97: YES | Q97: NO
A98: 102268892746 | B98: PUPUN03049230000017541 | C98: Mr. SACHIND | D98: MALE | E98: 38574 | F98: 45982 | G98: RAMGOPAL | H98: FATHER | I98: UN-MARRIED | J98: 7974495538 | K98: NOT AVAILABLE | L98: XXXX XXXX 3885 | M98: NOT AVAILABLE | N98: 32550212002XXXX,IFSC:UBIN0532550 | O98: NO | P98: YES | Q98: YES
A99: 101808505234 | B99: PUPUN03049230000017537 | C99: Mr. VIJAYKUMAR PRABHAKAR KERE | D99: MALE | E99: 35360 | F99: 45981 | G99: PRABHAKAR | H99: FATHER | I99: MARRIED | J99: 8855088043 | K99: NOT AVAILABLE | L99: XXXX XXXX 6440 | M99: XXWPK145XX | N99: 8014810000XXXX,IFSC:BARB0VJSHOL | O99: NO | P99: YES | Q99: NO
A100: 100794399909 | B100: PUPUN03049230000017536 | C100: Mr. GAURESH SHANKAR GHODAKE | D100: MALE | E100: 33756 | F100: 45981 | G100: SHANKAR GHODKE | H100: FATHER | I100: NOT AVAILABLE | J100: 8605410259 | K100: gaureshghodake96@gmail.com | L100: XXXX XXXX 0095 | M100: XXSPG786XX | N100: 6018087XXXX,IFSC:MAHB0000265 | O100: NO | P100: YES | Q100: NO
A101: 101777870817 | B101: PUPUN03049230000017532 | C101: Mr. PRAVIN BHARATRAO ZADE | D101: MALE | E101: 30128 | F101: 45980 | G101: BHARATRAO | H101: FATHER | I101: UN-MARRIED | J101: 9175217565 | K101: NOT AVAILABLE | L101: XXXX XXXX 0178 | M101: NOT AVAILABLE | N101: NOT AVAILABLE | O101: NO | P101: YES | Q101: NO
A102: 102261865570 | B102: PUPUN03049230000017534 | C102: Mr. SHRI MITHUN | D102: MALE | E102: 36387 | F102: 45980 | G102: CHANDRAKANT KUSNOORE | H102: FATHER | I102: UN-MARRIED | J102: 9059487424 | K102: NOT AVAILABLE | L102: XXXX XXXX 9526 | M102: NOT AVAILABLE | N102: NOT AVAILABLE | O102: NO | P102: YES | Q102: YES
A103: 102265592531 | B103: PUPUN03049230000017535 | C103: Mr. GANESH DIGAMBAR RAJURE | D103: MALE | E103: 38956 | F103: 45980 | G103: DIGAMBAR | H103: FATHER | I103: UN-MARRIED | J103: 8788163430 | K103: NOT AVAILABLE | L103: XXXX XXXX 6536 | M103: NOT AVAILABLE | N103: NOT AVAILABLE | O103: NO | P103: YES | Q103: YES
A104: 102265589634 | B104: PUPUN03049230000017533 | C104: Mr. CHANDRAKANT GANPAT SHINDALKAR | D104: MALE | E104: 37987 | F104: 45980 | G104: GANPAT SHINDALKAR | H104: FATHER | I104: UN-MARRIED | J104: 9370527513 | K104: NOT AVAILABLE | L104: XXXX XXXX 1998 | M104: NOT AVAILABLE | N104: NOT AVAILABLE | O104: NO | P104: YES | Q104: YES
A105: 102207025254 | B105: PUPUN03049230000017531 | C105: Mr. RAJENDRA PRASAD | D105: MALE | E105: 32509 | F105: 45980 | G105: RAM SUNDAR | H105: FATHER | I105: MARRIED | J105: 9071235908 | K105: NOT AVAILABLE | L105: XXXX XXXX 9470 | M105: NOT AVAILABLE | N105: 1038810004XXXX,IFSC:BARB0JABMIR | O105: YES | P105: YES | Q105: YES
A106: 101648431192 | B106: PUPUN03049230000017527 | C106: Mr. NIVRUTTI BAPU WAGHE | D106: MALE | E106: 34983 | F106: 45978 | G106: WAGHE BAPU | H106: FATHER | I106: UN-MARRIED | J106: 9579414568 | K106: NOT AVAILABLE | L106: XXXX XXXX 6103 | M106: NOT AVAILABLE | N106: NOT AVAILABLE | O106: NO | P106: YES | Q106: NO
A107: 101272098944 | B107: PUPUN03049230000017529 | C107: Mr. ARIF RAZAK SHAIKH | D107: MALE | E107: 32277 | F107: 45978 | G107: RAZAK | H107: FATHER | I107: MARRIED | J107: 9075788912 | K107: arifshaikh5545@gmail.com | L107: XXXX XXXX 6647 | M107: XXPPS076XX | N107: 461247XXXX,IFSC:KKBK0001757 | O107: NO | P107: YES | Q107: NO
A108: 102267135019 | B108: PUPUN03049230000017528 | C108: Mr. SHIVRAJ RAJKUMAR MHETRE | D108: MALE | E108: 36462 | F108: 45978 | G108: RAJKUMAR MHETRE | H108: FATHER | I108: UN-MARRIED | J108: 9359763909 | K108: NOT AVAILABLE | L108: XXXX XXXX 9303 | M108: NOT AVAILABLE | N108: NOT AVAILABLE | O108: NO | P108: YES | Q108: YES
A109: 102267132379 | B109: PUPUN03049230000017530 | C109: Mr. VISHAL RAJKUMAR KOLI | D109: MALE | E109: 38409 | F109: 45978 | G109: RAJKUMAR | H109: FATHER | I109: UN-MARRIED | J109: 8468950391 | K109: NOT AVAILABLE | L109: XXXX XXXX 0084 | M109: NOT AVAILABLE | N109: NOT AVAILABLE | O109: NO | P109: YES | Q109: YES
... A115: 102266151657 | B115: PUPUN03049230000017525 | C115: Mr. BHAGVANDAS RAMNATH JAISWAL | D115: MALE | E115: 26573 | F115: 45975 | G115: RAMANATH HARDAS JAISWAL | H115: FATHER | I115: MARRIED | J115: 7208238626 | K115: NOT AVAILABLE | L115: XXXX XXXX 3594 | M115: NOT AVAILABLE | N115: NOT AVAILABLE | O115: NO | P115: YES | Q115: YES
A116: 101686673696 | B116: PUPUN03049230000017522 | C116: Mr. NARUTE AMAR PRABHAKAR | D116: MALE | E116: 36892 | F116: 45975 | G116: NARUTE PRABHAKAR | H116: FATHER | I116: UN-MARRIED | J116: NOT AVAILABLE | K116: NOT AVAILABLE | L116: XXXX XXXX 6905 | M116: NOT AVAILABLE | N116: NOT AVAILABLE | O116: NO | P116: YES | Q116: NO
A117: 101481508832 | B117: PUPUN03049230000017523 | C117: Mr. PARAMESHWAR MAHADEO MHETRE | D117: MALE | E117: 33758 | F117: 45975 | G117: MAHADEO | H117: FATHER | I117: MARRIED | J117: 8390854736 | K117: kalburgi.bharat@gmail.com | L117: XXXX XXXX 2617 | M117: NOT AVAILABLE | N117: 3535906XXXX,IFSC:SBIN0004762 | O117: NO | P117: YES | Q117: NO
A118: 102265572722 | B118: PUPUN03049230000017516 | C118: Mr. DIPAK SUDAM SHINDE | D118: MALE | E118: 39066 | F118: 45974 | G118: SUDAM SHINDE | H118: FATHER | I118: UN-MARRIED | J118: 8261942481 | K118: NOT AVAILABLE | L118: XXXX XXXX 2412 | M118: NOT AVAILABLE | N118: NOT AVAILABLE | O118: NO | P118: YES | Q118: YES
A119: 102265574671 | B119: PUPUN03049230000017515 | C119: Mr. RAHUL VISHWANATH KAMBLE | D119: MALE | E119: 38024 | F119: 45974 | G119: VISHWANATH KAMBLE | H119: FATHER | I119: UN-MARRIED | J119: 8862039331 | K119: NOT AVAILABLE | L119: XXXX XXXX 8865 | M119: NOT AVAILABLE | N119: NOT AVAILABLE | O119: NO | P119: YES | Q119: YES
A120: 102265550592 | B120: PUPUN03049230000017513 | C120: Mr. DATTA VALMIK EKALE | D120: MALE | E120: 36138 | F120: 45974 | G120: VALMIK EKALE | H120: FATHER | I120: UN-MARRIED | J120: 9637820437 | K120: NOT AVAILABLE | L120: XXXX XXXX 7155 | M120: NOT AVAILABLE | N120: NOT AVAILABLE | O120: NO | P120: YES | Q120: YES
A121: 102265576321 | B121: PUPUN03049230000017512 | C121: Mr. SURYKANT RAJENDRA MASHALKAR | D121: MALE | E121: 37195 | F121: 45974 | G121: RAJENDRA MASHALKAR | H121: FATHER | I121: UN-MARRIED | J121: 9834859909 | K121: NOT AVAILABLE | L121: XXXX XXXX 8541 | M121: NOT AVAILABLE | N121: NOT AVAILABLE | O121: NO | P121: YES | Q121: YES
A122: 102093752491 | B122: PUPUN03049230000017509 | C122: Mr. VARUN RAJBHAR | D122: MALE | E122: 38353 | F122: 45974 | G122: KAWALDHARI | H122: FATHER | I122: UN-MARRIED | J122: 9056150509 | K122: NOT AVAILABLE | L122: XXXX XXXX 9519 | M122: NOT AVAILABLE | N122: NOT AVAILABLE | O122: NO | P122: YES | Q122: NO
A123: 102265477578 | B123: PUPUN03049230000017508 | C123: Mr. SHIVAM MAURYA | D123: MALE | E123: 38353 | F123: 45974 | G123: RAMESH MAURYA | H123: FATHER | I123: UN-MARRIED | J123: 8160514002 | K123: NOT AVAILABLE | L123: XXXX XXXX 3180 | M123: NOT AVAILABLE | N123: NOT AVAILABLE | O123: NO | P123: YES | Q123: YES
A124: 102264331389 | B124: PUPUN03049230000017511 | C124: Mr. MUTKIRI SURAJ MANIK | D124: MALE | E124: 36711 | F124: 45974 | G124: MANIK | H124: FATHER | I124: UN-MARRIED | J124: 9834128431 | K124: NOT AVAILABLE | L124: XXXX XXXX 3294 | M124: NOT AVAILABLE | N124: NOT AVAILABLE | O124: NO | P124: YES | Q124: YES
A125: 101987362724 | B125: PUPUN03049230000017518 | C125: Mr. OMKAR LAXMIKANT PATIL | D125: MALE | E125: 37401 | F125: 45974 | G125: LAXMIKANT PATIL | H125: FATHER | I125: UN-MARRIED | J125: 9922032554 | K125: NOT AVAILABLE | L125: XXXX XXXX 2401 | M125: NOT AVAILABLE | N125: 4288810001XXXX,IFSC:BARB0UDGIRX | O125: NO | P125: YES | Q125: YES
A126: 100669881522 | B126: PUPUN03049230000017510 | C126: Mr. SANTOSH RAVSAHEB PATIL | D126: MALE | E126: 34191 | F126: 45974 | G126: RAVSAHEB | H126: FATHER | I126: UN-MARRIED | J126: 8830052288 | K126: NOT AVAILABLE | L126: XXXX XXXX 9473 | M126: XXRPP727XX | N126: 3511211XXXX,IFSC:SBIN0012484 | O126: NO | P126: YES | Q126: NO
A127: 102213219501 | B127: PUPUN03049230000017514 | C127: Mr. RAJU SHIVYOGI ALLAPURE | D127: MALE | E127: 37797 | F127: 45974 | G127: SHIVYOGI ALLAPURE | H127: FATHER | I127: UN-MARRIED | J127: NOT AVAILABLE | K127: NOT AVAILABLE | L127: XXXX XXXX 7276 | M127: NOT AVAILABLE | N127: NOT AVAILABLE | O127: NO | P127: YES | Q127: NO
A128: 102020808974 | B128: PUPUN03049230000017551 | C128: Mr. SAURAV KUMAR | D128: MALE | E128: 37412 | F128: 45972 | G128: NAWAL KISHOR JHA | H128: FATHER | I128: MARRIED | J128: 8104691732 | K128: jhasaurav0606@gmail.com | L128: XXXX XXXX 7409 | M128: XXIPK064XX | N128: 364738XXXX,IFSC:KKBK0000649 | O128: YES | P128: YES | Q128: YES
A129: 101684491053 | B129: PUPUN03049230000017507 | C129: Mr. VISHAL MORE | D129: MALE | E129: 34687 | F129: 45972 | G129: SUNILDATT | H129: FATHER | I129: MARRIED | J129: 8975245781 | K129: NOT AVAILABLE | L129: XXXX XXXX 7155 | M129: NOT AVAILABLE | N129: 1014810002XXXX,IFSC:BARB0RAISHO | O129: NO | P129: YES | Q129: NO
A130: 102263674079 | B130: PUPUN03049230000017506 | C130: Mr. IRSAD ANSARI | D130: MALE | E130: 37257 | F130: 45971 | G130: NASIM ANSARI | H130: FATHER | I130: UN-MARRIED | J130: 6299601018 | K130: NOT AVAILABLE | L130: XXXX XXXX 0868 | M130: NOT AVAILABLE | N130: 629960XXXX,IFSC:AIRP0000001 | O130: NO | P130: YES | Q130: YES
A131: 102263045975 | B131: PUPUN03049230000017505 | C131: Mr. RAMBABU GOUND | D131: MALE | E131: 39010 | F131: 45970 | G131: KARAN SINGH GOUND | H131: FATHER | I131: UN-MARRIED | J131: 8815344201 | K131: NOT AVAILABLE | L131: XXXX XXXX 1531 | M131: NOT AVAILABLE | N131: NOT AVAILABLE | O131: NO | P131: YES | Q131: YES
A132: 102261619396 | B132: PUPUN03049230000017503 | C132: Mr. KASHINATH SIDHARAM TOLANURE | D132: MALE | E132: 39315 | F132: 45965 | G132: SIDHARAM | H132: FATHER | I132: UN-MARRIED | J132: 8446789099 | K132: NOT AVAILABLE | L132: XXXX XXXX 8451 | M132: NOT AVAILABLE | N132: NOT AVAILABLE | O132: NO | P132: YES | Q132: YES
A133: 101777248745 | B133: PUPUN03049230000017502 | C133: Mr. PRATIK NAGNATH SWAMI | D133: MALE | E133: 34928 | F133: 45965 | G133: NAGNATH | H133: FATHER | I133: MARRIED | J133: 7387388290 | K133: NOT AVAILABLE | L133: XXXX XXXX 6497 | M133: NOT AVAILABLE | N133: 4526810000XXXX,IFSC:BARB0HOTAGI | O133: NO | P133: YES | Q133: YES
A134: 101868329585 | B134: PUPUN03049230000017504 | C134: Mr. RAVINDRA SANDIPAN SATHE | D134: MALE | E134: 35572 | F134: 45965 | G134: SANDIPAN EKNATH SATHE | H134: FATHER | I134: MARRIED | J134: 7709997353 | K134: NOT AVAILABLE | L134: XXXX XXXX 1092 | M134: XXFPS351XX | N134: NOT AVAILABLE | O134: NO | P134: YES | Q134: NO
A135: 102103416159 | B135: PUPUN03049230000017499 | C135: Mr. ROHIT AMBADAS GHODKE | D135: MALE | E135: 38526 | F135: 45964 | G135: AMBADAS | H135: FATHER | I135: UN-MARRIED | J135: 9112645883 | K135: NOT AVAILABLE | L135: XXXX XXXX 2879 | M135: XXRPG174XX | N135: 614819XXXX,IFSC:KKBK0002039 | O135: NO | P135: YES | Q135: NO
A136: 102261340182 | B136: PUPUN03049230000017500 | C136: Mr. YUSUF ISMAIL FULARI | D136: MALE | E136: 39329 | F136: 45964 | G136: ISMAIL FULARI | H136: FATHER | I136: UN-MARRIED | J136: 9860599147 | K136: NOT AVAILABLE | L136: XXXX XXXX 0696 | M136: NOT AVAILABLE | N136: NOT AVAILABLE | O136: NO | P136: YES | Q136: YES
...

Sheet ESIC NAME
A1: empe_name | B1: empe_ip_number | C1: FromDate | D1: ToDate | E1: Status | F1: regdate | G1: IPAadhaar | H1: DepAadhaar | I1: empe_name | J1: Line-1 | K1: Line-2
A2: KUMAR ARJUN RATHOD | B2: 3316545755 | C2: -- | D2: -- | E2: NO | F2: 45607 | G2: Not Seeded | H2: Not Seeded | I2: KUMAR ARJUN RATHOD | J2: =VLOOKUP(B2,Work!E:J,6,0) -> #N/A | K2: =VLOOKUP(B2,'[4]work '!$D:$O,12,0) -> 100002746003
A3: SHRIKANT GIREPPA SHIROLE | B3: 3316506495 | C3: -- | D3: -- | E3: NO | F3: 45461 | G3: Not Seeded | H3: Not Seeded | I3: SHRIKANT GIREPPA SHIROLE | J3: =VLOOKUP(B3,Work!E:J,6,0) -> #N/A | K3: =VLOOKUP(B3,'[4]work '!$D:$O,12,0) -> 100351117645
A4: Mohammad Tajoddin Salahuddin Shaikh | B4: 3309293229 | C4: -- | D4: -- | E4: NO | F4: 45912 | G4: Seeded | H4: Not Seeded | I4: Mohammad Tajoddin Salahuddin Shaikh | J4: =VLOOKUP(B4,Work!E:J,6,0) -> #N/A | K4: =VLOOKUP(B4,'[4]work '!$D:$O,12,0) -> 100388432887
A5: BASAVARAJ BHIMASHANKAR SUTAR | B5: 3317136544 | C5: -- | D5: -- | E5: NO | F5: 45724 | G5: Not Seeded | H5: Not Seeded | I5: BASAVARAJ BHIMASHANKAR SUTAR | J5: =VLOOKUP(B5,Work!E:J,6,0) -> #N/A | K5: =VLOOKUP(B5,'[4]work '!$D:$O,12,0) -> 101033096273
A6: Sunil Siddharam Sakhare | B6: 3308839978 | C6: -- | D6: -- | E6: NO | F6: 45975 | G6: Seeded | H6: Not Seeded | I6: Sunil Siddharam Sakhare | J6: =VLOOKUP(B6,Work!E:J,6,0) -> #N/A | K6: =VLOOKUP(B6,'[4]work '!$D:$O,12,0) -> 101200213596
A7: JANBAJ IBRHIM SHAIKH | B7: 3316162580 | C7: -- | D7: -- | E7: NO | F7: 45365 | G7: Not Seeded | H7: Not Seeded | I7: JANBAJ IBRHIM SHAIKH | J7: =VLOOKUP(B7,Work!E:J,6,0) -> #N/A | K7: =VLOOKUP(B7,'[4]work '!$D:$O,12,0) -> 101326689678
A8: AMOL HANUMANTU BHASGI | B8: 3316712438 | C8: -- | D8: -- | E8: NO | F8: 45513 | G8: Not Seeded | H8: Not Seeded | I8: AMOL HANUMANTU BHASGI | J8: =VLOOKUP(B8,Work!E:J,6,0) -> #N/A | K8: =VLOOKUP(B8,'[4]work '!$D:$O,12,0) -> 101357603671
A9: AKASH ARJUN BAMANE | B9: 3318226437 | C9: -- | D9: -- | E9: NO | F9: 46007 | G9: Seeded | H9: Not Seeded | I9: AKASH ARJUN BAMANE | J9: =VLOOKUP(B9,Work!E:J,6,0) -> #N/A | K9: =VLOOKUP(B9,'[4]work '!$D:$O,12,0) -> 101404550353
A10: CHAITANYA VILAS KOLI | B10: 3317745424 | C10: -- | D10: -- | E10: NO | F10: 45838 | G10: Not Seeded | H10: Not Seeded | I10: CHAITANYA VILAS KOLI | J10: =VLOOKUP(B10,Work!E:J,6,0) -> #N/A | K10: =VLOOKUP(B10,'[4]work '!$D:$O,12,0) -> 101447270820
A11: PARAMESHWAR MAHADEO MHETRE | B11: 3318135223 | C11: -- | D11: -- | E11: NO | F11: 45975 | G11: Not Seeded | H11: Not Seeded | I11: PARAMESHWAR MAHADEO MHETRE | J11: =VLOOKUP(B11,Work!E:J,6,0) -> #N/A | K11: =VLOOKUP(B11,'[4]work '!$D:$O,12,0) -> 101481508832
A12: IMRAN SULTAN PATHAN | B12: 3315339143 | C12: -- | D12: -- | E12: NO | F12: 46030 | G12: Not Seeded | H12: Not Seeded | I12: IMRAN SULTAN PATHAN | J12: =VLOOKUP(B12,Work!E:J,6,0) -> #N/A | K12: =VLOOKUP(B12,'[4]work '!$D:$O,12,0) -> 101487538044
A13: ABHIJIT SOPAN KADAM | B13: 3317556190 | C13: -- | D13: -- | E13: NO | F13: 46096 | G13: Not Seeded | H13: Not Seeded | I13: ABHIJIT SOPAN KADAM | J13: =VLOOKUP(B13,Work!E:J,6,0) -> #N/A | K13: =VLOOKUP(B13,'[4]work '!$D:$O,12,0) -> 101558583039
... A52: AJAY BHARALE | B52: 3318134535 | C52: -- | D52: -- | E52: NO | F52: 45974 | G52: Not Seeded | H52: Not Seeded | I52: AJAY BHARALE | J52: =VLOOKUP(B52,Work!E:J,6,0) -> #N/A | K52: =VLOOKUP(B52,'[4]work '!$D:$O,12,0) -> 102265909833
A53: DATTATRAYWAGHMODE | B53: 3310860091 | C53: -- | D53: -- | E53: NO | F53: 43619 | G53: Not Seeded | H53: Not Seeded | I53: DATTATRAYWAGHMODE | J53: =VLOOKUP(B53,Work!E:J,6,0) -> 101391642731 | K53: .
A54: HARIOM THAKUR | B54: 3318334248 | C54: -- | D54: -- | E54: NO | F54: 46042 | G54: Seeded | H54: No dependants | I54: HARIOM THAKUR | J54: =VLOOKUP(B54,Work!E:J,6,0) -> #N/A | K54: =VLOOKUP(B54,'[4]work '!$D:$O,12,0) -> HARIOM. THAKUR
A55: SAGAR GUNDPPA JAMDAR | B55: 3318333195 | C55: -- | D55: -- | E55: NO | F55: 46042 | G55: Not Seeded | H55: Not Seeded | I55: SAGAR GUNDPPA JAMDAR | J55: =VLOOKUP(B55,Work!E:J,6,0) -> #N/A | K55: =VLOOKUP(B55,'[4]work '!$D:$O,12,0) -> SAGAR JAMADAR
A56: SHASHIKANT DATTATRAY ALURE | B56: 2504535280 | C56: -- | D56: -- | E56: NO | F56: 46055 | G56: Not Seeded | H56: Not Seeded | I56: SHASHIKANT DATTATRAY ALURE | J56: =VLOOKUP(B56,Work!E:J,6,0) -> #N/A | K56: =VLOOKUP(B56,'[4]work '!$D:$O,12,0) -> SHASHIKANT ALURE
A57: SHUKRAM | B57: 3318334817 | C57: -- | D57: -- | E57: NO | F57: 46042 | G57: Seeded | H57: No dependants | I57: SHUKRAM | J57: =VLOOKUP(B57,Work!E:J,6,0) -> #N/A | K57: =VLOOKUP(B57,'[4]work '!$D:$O,12,0) -> SHUKRAM THAKUR
A58: SURAJ | B58: 3318334758 | C58: -- | D58: -- | E58: NO | F58: 46042 | G58: Seeded | H58: No dependants | I58: SURAJ | J58: =VLOOKUP(B58,Work!E:J,6,0) -> #N/A | K58: =VLOOKUP(B58,'[4]work '!$D:$O,12,0) -> SURAJ THAKUR
A59: TEJAS BHINGARE | B59: 3314292252 | C59: -- | D59: -- | E59: NO | F59: 46096 | G59: Not Seeded | H59: Not Seeded | I59: TEJAS BHINGARE | J59: =VLOOKUP(B59,Work!E:J,6,0) -> #N/A | K59: =VLOOKUP(B59,'[4]work '!$D:$O,12,0) -> TEJAS BENGARE
A60: VIJAY HANAMANT GUJJE | B60: 3318277343 | C60: -- | D60: -- | E60: NO | F60: 46024 | G60: Seeded | H60: Not Seeded | I60: VIJAY HANAMANT GUJJE | J60: =VLOOKUP(B60,Work!E:J,6,0) -> #N/A | K60: =VLOOKUP(B60,'[4]work '!$D:$O,12,0) -> VIJAY GUJJI
A61: KAILASH SINGH | B61: 3318530612 | C61: -- | D61: -- | E61: NO | F61: 46107 | G61: Seeded | H61: No dependants | I61: KAILASH SINGH | J61: =VLOOKUP(B61,Work!E:J,6,0) -> #N/A
A62: SACHIN BHAGWAN GHANTE | B62: 3315397405 | C62: -- | D62: -- | E62: NO | F62: 45131 | G62: Not Seeded | H62: Not Seeded | I62: SACHIN BHAGWAN GHANTE | J62: =VLOOKUP(B62,Work!E:J,6,0) -> 100450352070
A63: DARGAPPA SHIVANAND ARWAT | B63: 3315291117 | C63: -- | D63: -- | E63: NO | F63: 45103 | G63: Not Seeded | H63: Not Seeded | I63: DARGAPPA SHIVANAND ARWAT | J63: =VLOOKUP(B63,Work!E:J,6,0) -> 100590315745
A64: AJEET KUMAR KOL | B64: 3314505032 | C64: -- | D64: -- | E64: NO | F64: 46014 | G64: Not Seeded | H64: No dependants | I64: AJEET KUMAR KOL | J64: =VLOOKUP(B64,Work!E:J,6,0) -> #N/A
A65: MANGESH NAVNATH ANKUSHRAO | B65: 3317595184 | C65: -- | D65: -- | E65: NO | F65: 45799 | G65: Not Seeded | H65: Not Seeded | I65: MANGESH NAVNATH ANKUSHRAO | J65: =VLOOKUP(B65,Work!E:J,6,0) -> 101084612898
A66: VISHAL BABURAO NAIKWADE | B66: 3317820579 | C66: -- | D66: -- | E66: NO | F66: 45856 | G66: Seeded | H66: No dependants | I66: VISHAL BABURAO NAIKWADE | J66: =VLOOKUP(B66,Work!E:J,6,0) -> #N/A
A67: HUSEN NADAF | B67: 3317732124 | C67: -- | D67: -- | E67: NO | F67: 45834 | G67: Not Seeded | H67: Not Seeded | I67: HUSEN NADAF | J67: =VLOOKUP(B67,Work!E:J,6,0) -> 101216844424
A68: VISHAL MOHAN MANE | B68: 3315883972 | C68: -- | D68: -- | E68: NO | F68: 45878 | G68: Not Seeded | H68: No dependants | I68: VISHAL MOHAN MANE | J68: =VLOOKUP(B68,Work!E:J,6,0) -> 101235372414
A69: ANIL KUMAR RAWAT | B69: 3315479975 | C69: -- | D69: -- | E69: NO | F69: 46014 | G69: Not Seeded | H69: No dependants | I69: ANIL KUMAR RAWAT | J69: =VLOOKUP(B69,Work!E:J,6,0) -> 101241926666
A70: AVINASH NILKANTH PATANGE | B70: 3315008810 | C70: -- | D70: -- | E70: NO | F70: 46031 | G70: Not Seeded | H70: Not Seeded | I70: AVINASH NILKANTH PATANGE | J70: =VLOOKUP(B70,Work!E:J,6,0) -> 101281737627
A71: KHALID ILAI SHAIKH | B71: 3311531000 | C71: -- | D71: -- | E71: NO | F71: 43834 | G71: Not Seeded | H71: Not Seeded | I71: KHALID ILAI SHAIKH | J71: =VLOOKUP(B71,Work!E:J,6,0) -> 101373078654
A72: RUSHIKESH CHANDRAKANT CHOUGULE | B72: 3310279715 | C72: -- | D72: -- | E72: NO | F72: 44789 | G72: Not Seeded | H72: Not Seeded | I72: RUSHIKESH CHANDRAKANT CHOUGULE | J72: =VLOOKUP(B72,Work!E:J,6,0) -> 101388345766
... A162: RAHUL BALU CHAVAN | B162: 3318432596 | C162: -- | D162: -- | E162: NO | F162: 46072 | G162: Not Seeded | H162: No dependants | I162: RAHUL BALU CHAVAN | J162: =VLOOKUP(B162,Work!E:J,6,0) -> RAHUL BALU CHAVHAN
A163: SHANKAR GIRMAL MALI | B163: 3318522002 | C163: -- | D163: -- | E163: NO | F163: 46104 | G163: Seeded | H163: Not Seeded | I163: SHANKAR GIRMAL MALI | J163: =VLOOKUP(B163,Work!E:J,6,0) -> 101660669647 | K163: =VLOOKUP(B163,'[4]work '!$D:$O,12,0) -> #N/A
A164: Sagar Ramesh Gharsangi | B164: 3308695163 | C164: -- | D164: -- | E164: NO | F164: 46096 | G164: Seeded | H164: Not Seeded | I164: Sagar Ramesh Gharsangi | J164: =VLOOKUP(B164,Work!E:J,6,0) -> 101934615110 | K164: =VLOOKUP(B164,'[4]work '!$D:$O,12,0) -> #N/A
A165: NAGANATH KASHINATH SONWANE | B165: 3316330556 | C165: -- | D165: -- | E165: NO | F165: 46096 | G165: Not Seeded | H165: Not Seeded | I165: NAGANATH KASHINATH SONWANE | J165: =VLOOKUP(B165,Work!E:J,6,0) -> 102067179570 | K165: =VLOOKUP(B165,'[4]work '!$D:$O,12,0) -> #N/A
A166: ABDULAZIZ MUBIN MALLABADKAR | B166: 3318459745 | C166: -- | D166: -- | E166: NO | F166: 46081 | G166: Seeded | H166: Not Seeded | I166: ABDULAZIZ MUBIN MALLABADKAR | J166: =VLOOKUP(B166,Work!E:J,6,0) -> ABDULAZIZ MALLABADKAR | K166: =VLOOKUP(B166,'[4]work '!$D:$O,12,0) -> #N/A
A167: SANJAY GOPINATH BANDGAR | B167: 3318468570 | C167: -- | D167: -- | E167: NO | F167: 46084 | G167: Seeded | H167: No dependants | I167: SANJAY GOPINATH BANDGAR | J167: =VLOOKUP(B167,Work!E:J,6,0) -> ARJUN HIRACHAND BANDAGAR | K167: =VLOOKUP(B167,'[4]work '!$D:$O,12,0) -> #N/A
A168: BALU MOHAN CHAVAN | B168: 3318432556 | C168: -- | D168: -- | E168: NO | F168: 46072 | G168: Not Seeded | H168: Not Seeded | I168: BALU MOHAN CHAVAN | J168: =VLOOKUP(B168,Work!E:J,6,0) -> #N/A | K168: =VLOOKUP(B168,'[4]work '!$D:$O,12,0) -> #N/A
A169: DHANANJAY KIRAN AMBURE | B169: 3318460591 | C169: -- | D169: -- | E169: NO | F169: 46081 | G169: Not Seeded | H169: Not Seeded | I169: DHANANJAY KIRAN AMBURE | J169: =VLOOKUP(B169,Work!E:J,6,0) -> DHANNAJAY AMBURE | K169: =VLOOKUP(B169,'[4]work '!$D:$O,12,0) -> #N/A
A170: KUMAR GURAYYA GHERADI | B170: 3318468674 | C170: -- | D170: -- | E170: NO | F170: 46084 | G170: Seeded | H170: No dependants | I170: KUMAR GURAYYA GHERADI | J170: =VLOOKUP(B170,Work!E:J,6,0) -> #N/A | K170: =VLOOKUP(B170,'[4]work '!$D:$O,12,0) -> #N/A
A171: NAGESH REVANSIDDHA BIRAJDAR | B171: 3318521941 | C171: -- | D171: -- | E171: NO | F171: 46104 | G171: Seeded | H171: Not Seeded | I171: NAGESH REVANSIDDHA BIRAJDAR | J171: =VLOOKUP(B171,Work!E:J,6,0) -> NAGESG REVANSIDHHA BIRAJDAR | K171: =VLOOKUP(B171,'[4]work '!$D:$O,12,0) -> #N/A
A172: PRAVIN LAHU WAGHMODE | B172: 3318459865 | C172: -- | D172: -- | E172: NO | F172: 46081 | G172: Not Seeded | H172: Not Seeded | I172: PRAVIN LAHU WAGHMODE | J172: =VLOOKUP(B172,Work!E:J,6,0) -> #N/A | K172: =VLOOKUP(B172,'[4]work '!$D:$O,12,0) -> #N/A
A173: ARJUN HIRACHAND BANDAGAR | B173: 3318468493 | C173: -- | D173: -- | E173: NO | F173: 46084 | G173: Seeded | H173: No dependants | I173: ARJUN HIRACHAND BANDAGAR | J173: =VLOOKUP(B173,Work!E:J,6,0) -> SANJAY GOPINATH BANDGAR | K173: =VLOOKUP(B173,'[4]work '!$D:$O,12,0) -> #N/A
A174: SHARUKH TIPUSULTAN CHOUDHARI | B174: 3318533102 | C174: -- | D174: -- | E174: NO | F174: 46108 | G174: Not Seeded | H174: Not Seeded | I174: SHARUKH TIPUSULTAN CHOUDHARI | J174: =VLOOKUP(B174,Work!E:J,6,0) -> #N/A | K174: =VLOOKUP(B174,'[4]work '!$D:$O,12,0) -> #N/A
... A177: YASH LAVHU KUMBHAR | B177: 3318522025 | C177: -- | D177: -- | E177: NO | F177: 46104 | G177: Seeded | H177: Not Seeded | I177: YASH LAVHU KUMBHAR | J177: =VLOOKUP(B177,Work!E:J,6,0) -> YASH LAVHU KUMBHAR | K177: =VLOOKUP(B177,'[4]work '!$D:$O,12,0) -> #N/A
A178: SAMARTH MANJUNATH SIRSAT | B178: 3318419564 | C178: -- | D178: -- | E178: NO | F178: 46066 | G178: Not Seeded | H178: Not Seeded | I178: SAMARTH MANJUNATH SIRSAT | J178: =VLOOKUP(B178,Work!E:J,6,0) -> SAMARTH MANJUNATH SIRSAT
A180: NILKANTH NAGANNA BAGLE | B180: 3311476751 | C180: -- | D180: -- | E180: NO | F180: 43816 | G180: Not Seeded | H180: Not Seeded | I180: NILKANTH NAGANNA BAGLE | J180: =VLOOKUP(B180,Work!E:J,6,0) -> #N/A | K180: =VLOOKUP(B180,'[4]work '!$D:$O,12,0) -> #N/A
A181: MAHESH MANE | B181: 3312197797 | C181: -- | D181: -- | E181: NO | F181: 44132 | G181: Not Seeded | H181: Not Seeded | I181: MAHESH MANE | J181: =VLOOKUP(B181,Work!E:J,6,0) -> #N/A | K181: =VLOOKUP(B181,'[4]work '!$D:$O,12,0) -> #N/A
A182: UBEDULLAH MAINODDIN SHAIKH | B182: 3314175295 | C182: -- | D182: -- | E182: NO | F182: 44764 | G182: Not Seeded | H182: No dependants | I182: UBEDULLAH MAINODDIN SHAIKH | J182: =VLOOKUP(B182,Work!E:J,6,0) -> #N/A | K182: =VLOOKUP(B182,'[4]work '!$D:$O,12,0) -> #N/A
A183: MALLIKARJUN MALI | B183: 3314175652 | C183: -- | D183: -- | E183: NO | F183: 44764 | G183: Seeded | H183: Seeded | I183: MALLIKARJUN MALI | J183: =VLOOKUP(B183,Work!E:J,6,0) -> #N/A | K183: =VLOOKUP(B183,'[4]work '!$D:$O,12,0) -> #N/A
A184: VIJAYKUMAR LANDAGE | B184: 3314211848 | C184: -- | D184: -- | E184: NO | F184: 44774 | G184: Not Seeded | H184: Not Seeded | I184: VIJAYKUMAR LANDAGE | J184: =VLOOKUP(B184,Work!E:J,6,0) -> #N/A | K184: =VLOOKUP(B184,'[4]work '!$D:$O,12,0) -> #N/A
A185: Pramod Fulari | B185: 3313276508 | C185: -- | D185: -- | E185: NO | F185: 44822 | G185: Seeded | H185: Not Seeded | I185: Pramod Fulari | J185: =VLOOKUP(B185,Work!E:J,6,0) -> #N/A | K185: =VLOOKUP(B185,'[4]work '!$D:$O,12,0) -> #N/A
A186: SWAPNIL RAM MULE | B186: 3314484435 | C186: -- | D186: -- | E186: NO | F186: 44861 | G186: Not Seeded | H186: No dependants | I186: SWAPNIL RAM MULE | J186: =VLOOKUP(B186,Work!E:J,6,0) -> #N/A | K186: =VLOOKUP(B186,'[4]work '!$D:$O,12,0) -> #N/A
A187: SHUBHAM | B187: 3314557639 | C187: -- | D187: -- | E187: NO | F187: 44883 | G187: Seeded | H187: Not Seeded | I187: SHUBHAM | J187: =VLOOKUP(B187,Work!E:J,6,0) -> #N/A | K187: =VLOOKUP(B187,'[4]work '!$D:$O,12,0) -> #N/A
A188: SANDEEP KUMAR | B188: 3314598786 | C188: -- | D188: -- | E188: NO | F188: 44895 | G188: Not Seeded | H188: No dependants | I188: SANDEEP KUMAR | J188: =VLOOKUP(B188,Work!E:J,6,0) -> #N/A | K188: =VLOOKUP(B188,'[4]work '!$D:$O,12,0) -> #N/A
A189: VINAYAK PRABHAKAR SARATE | B189: 3314649830 | C189: -- | D189: -- | E189: NO | F189: 44909 | G189: Not Seeded | H189: No dependants | I189: VINAYAK PRABHAKAR SARATE | J189: =VLOOKUP(B189,Work!E:J,6,0) -> #N/A | K189: =VLOOKUP(B189,'[4]work '!$D:$O,12,0) -> #N/A
A190: AKASH RAWAT | B190: 3314505091 | C190: -- | D190: -- | E190: NO | F190: 44915 | G190: Not Seeded | H190: No dependants | I190: AKASH RAWAT | J190: =VLOOKUP(B190,Work!E:J,6,0) -> #N/A | K190: =VLOOKUP(B190,'[4]work '!$D:$O,12,0) -> #N/A
A191: ADINATH ANNASAHEB KADAM | B191: 3313832424 | C191: -- | D191: -- | E191: NO | F191: 45076 | G191: Seeded | H191: Not Seeded | I191: ADINATH ANNASAHEB KADAM | J191: =VLOOKUP(B191,Work!E:J,6,0) -> #N/A | K191: =VLOOKUP(B191,'[4]work '!$D:$O,12,0) -> #N/A
... A329: USMAN GANI RAFIK MULLA | B329: 3318581847 | C329: -- | D329: -- | E329: NO | F329: 46125 | G329: Seeded | H329: Not Seeded | I329: USMAN GANI RAFIK MULLA | J329: =VLOOKUP(B329,Work!E:J,6,0) -> #N/A | K329: =VLOOKUP(B329,'[4]work '!$D:$O,12,0) -> #N/A

Sheet Work
D1: P | E1: ESIC | F1: PF Name | G1: ESIC No. | H1: Emp Name | K1: chaking | M1: True & False | O1: SHIFT | R1: Old Rate | S1: Employee Rate | U1: Vlookup Cupan | V1: Vlookup Attandance | W1: Vlookup Tannage Payment | X1: Vlookup Tannage Day | Y1: cupan | Z1: Attandance | AA1: Tannage Payment | AB1: Tannage Day | AD1: Regular Amount | AE1: Nilesh Adv | AF1: AVJ & Rework | AG1: jamadar | AH1: Office | AI1: PF | AJ1: PT | AK1: ESIC | AL1: Cupan | AP1: Cupan
A2: =D2=J2 -> TRUE | B2: KFIL/196 | C2: FOU49 | D2: 101447270865 | E2: 3314278646 | F2: =VLOOKUP(D2,'Name Details'!A:C,3,0) -> Mr. ABHIJIT PIRAPPA WAGHMARE | G2: =VLOOKUP(E2,'ESIC NAME'!B:I,8,0) -> ABHIJIT PIRAPPA WAGHMARE | H2: Mr. ABHIJIT PIRAPPA WAGHMARE | I2: =VLOOKUP(D2,'Google attandance April -26'!C:AK,40,0) -> #REF! | J2: 101447270865 | K2: 3314278646 | L2: =VLOOKUP(D2,'Google attandance April -26'!C:E,3,0) -> SHOT BLAST | M2: =D2=J2 -> TRUE | N2: =I2=C2 -> #REF! | O2: =VLOOKUP(D2,'Google attandance April -26'!C:E,3,0) -> SHOT BLAST | P2: BARB0SHOLAP | Q2: 043701000018040 | S2: 625 | U2: =VLOOKUP(D2,'Google attandance April -26'!C:AM,37,0) -> 439.21 | V2: =VLOOKUP(D2,'Google attandance April -26'!C:AM,34,0) -> 26 | W2: =VLOOKUP(D2,'FINAL TANNAGE AMO.'!C:AI,33,0) -> 2 | X2: =VLOOKUP(D2,'FINAL TANNAGE AMO.'!C:AI,32,0) -> 1520 | Y2: 439.21 | Z2: 26 | AA2: 2 | AB2: 1520 | AC2: =Z2-AA2 -> 24 | AD2: =AC2*S2 -> 15000 | AI2: 1308 | AJ2: 200 | AK2: 119 | AM2: 10 | AN2: =AL2*AM2 -> 0 | AR2: =W2=AA2 -> TRUE
A3: =D3=J3 -> TRUE | B3: KFIL/179 | C3: FOU32 | D3: 101747190938 | E3: 3313290894 | F3: =VLOOKUP(D3,'Name Details'!A:C,3,0) -> Mr. AKASH JAGNNATH TENGALE | G3: =VLOOKUP(E3,'ESIC NAME'!B:I,8,0) -> AKASH JAGNNATH TENGALE | H3: Mr. AKASH JAGNNATH TENGALE | I3: =VLOOKUP(D3,'Google attandance April -26'!C:AK,40,0) -> #REF! | J3: 101747190938 | K3: 3313290894 | L3: =VLOOKUP(D3,'Google attandance April -26'!C:E,3,0) -> HE | M3: =D3=J3 -> TRUE | N3: =I3=C3 -> #REF! | O3: =VLOOKUP(D3,'Google attandance April -26'!C:E,3,0) -> HE | P3: SBIN0000304 | Q3: 40315551169 | S3: 550 | U3: =VLOOKUP(D3,'Google attandance April -26'!C:AM,37,0) -> 286.28 | V3: =VLOOKUP(D3,'Google attandance April -26'!C:AM,34,0) -> 11.5 | W3: =VLOOKUP(D3,'FINAL TANNAGE AMO.'!C:AI,33,0) -> 12 | X3: =VLOOKUP(D3,'FINAL TANNAGE AMO.'!C:AI,32,0) -> 11581 | Y3: 286.28 | Z3: 11.5 | AA3: 12 | AB3: 11581 | AD3: =AC3*S3 -> 0 | AI3: 509 | AJ3: 0 | AK3: 52 | AM3: 10 | AN3: =AL3*AM3 -> 0 | AR3: =W3=AA3 -> TRUE | AT3: Ok
A4: =D4=J4 -> TRUE | B4: KFIL/198 | C4: FOU90 | D4: 102043325356 | E4: 3316016132 | F4: =VLOOKUP(D4,'Name Details'!A:C,3,0) -> Mr. AKIB SHAIKH | G4: =VLOOKUP(E4,'ESIC NAME'!B:I,8,0) -> AKIB SHAIKH | H4: Mr. AKIB SHAIKH | I4: =VLOOKUP(D4,'Google attandance April -26'!C:AK,40,0) -> #REF! | J4: 102043325356 | K4: 3316016132 | L4: =VLOOKUP(D4,'Google attandance April -26'!C:E,3,0) -> AVG | M4: =D4=J4 -> TRUE | N4: =I4=C4 -> #REF! | O4: =VLOOKUP(D4,'Google attandance April -26'!C:E,3,0) -> AVG | P4: MAHB0001127 | Q4: 60225717072 | S4: 550 | U4: =VLOOKUP(D4,'Google attandance April -26'!C:AM,37,0) -> 165.51 | V4: =VLOOKUP(D4,'Google attandance April -26'!C:AM,34,0) -> 27 | W4: =VLOOKUP(D4,'FINAL TANNAGE AMO.'!C:AI,33,0) -> #N/A | X4: =VLOOKUP(D4,'FINAL TANNAGE AMO.'!C:AI,32,0) -> #N/A | Y4: 165.51 | Z4: 27 | AD4: =AC4*S4 -> 0 | AI4: 1308 | AJ4: 200 | AK4: 119 | AM4: 10 | AN4: =AL4*AM4 -> 0
A5: =D5=J5 -> TRUE | B5: KFIL/18 | C5: 0 | D5: 101509952020 | E5: 3311275186 | F5: =VLOOKUP(D5,'Name Details'!A:C,3,0) -> Mr. AMOL TEJU RATHOD | G5: =VLOOKUP(E5,'ESIC NAME'!B:I,8,0) -> AMOL TEJU RATHOD | H5: Mr. AMOL TEJU RATHOD | I5: =VLOOKUP(D5,'Google attandance April -26'!C:AK,40,0) -> #REF! | J5: 101509952020 | K5: 3311275186 | L5: =VLOOKUP(D5,'Google attandance April -26'!C:E,3,0) -> HE | M5: =D5=J5 -> TRUE | N5: =I5=C5 -> #REF! | O5: =VLOOKUP(D5,'Google attandance April -26'!C:E,3,0) -> HE | P5: SBIN0012485 | Q5: 33804298328 | S5: 550 | U5: =VLOOKUP(D5,'Google attandance April -26'!C:AM,37,0) -> 0 | V5: =VLOOKUP(D5,'Google attandance April -26'!C:AM,34,0) -> 23 | W5: =VLOOKUP(D5,'FINAL TANNAGE AMO.'!C:AI,33,0) -> 23 | X5: =VLOOKUP(D5,'FINAL TANNAGE AMO.'!C:AI,32,0) -> 19933 | Y5: 0 | Z5: 23 | AA5: 23 | AB5: 19933 | AD5: =AC5*S5 -> 0 | AI5: 1090 | AJ5: 200 | AK5: 110 | AM5: 10 | AN5: =AL5*AM5 -> 0 | AR5: =W5=AA5 -> TRUE | AT5: ok
A6: =D6=J6 -> TRUE | B6: KFIL/502 | C6: FOU225 | D6: 102056969235 | E6: 3316230356 | F6: =VLOOKUP(D6,'Name Details'!A:C,3,0) -> Mr. ANIKET SHRIPATI DANGE | G6: =VLOOKUP(E6,'ESIC NAME'!B:I,8,0) -> ANIKET SHRIPATI DANGE | H6: Mr. ANIKET SHRIPATI DANGE | I6: =VLOOKUP(D6,'Google attandance April -26'!C:AK,40,0) -> #REF! | J6: 102056969235 | K6: 3316230356 | L6: =VLOOKUP(D6,'Google attandance April -26'!C:E,3,0) -> FD SUP | M6: =D6=J6 -> TRUE | N6: =I6=C6 -> #REF! | O6: =VLOOKUP(D6,'Google attandance April -26'!C:E,3,0) -> FD SUP | P6: UBIN0541036 | Q6: 410302010508178 | R6: 625 | S6: 650 | U6: =VLOOKUP(D6,'Google attandance April -26'!C:AM,37,0) -> 152.93 | V6: =VLOOKUP(D6,'Google attandance April -26'!C:AM,34,0) -> 21 | W6: =VLOOKUP(D6,'FINAL TANNAGE AMO.'!C:AI,33,0) -> #N/A | X6: =VLOOKUP(D6,'FINAL TANNAGE AMO.'!C:AI,32,0) -> #N/A | Y6: 152.93 | Z6: 21 | AD6: =AC6*S6 -> 0 | AE6: 3000 | AI6: 945 | AJ6: 200 | AK6: 100 | AM6: 10 | AN6: =AL6*AM6 -> 0
A7: =D7=J7 -> TRUE | B7: KFIL/06 | C7: FOU21 | D7: 101475240602 | E7: 3310877479 | F7: =VLOOKUP(D7,'Name Details'!A:C,3,0) -> Mr. ANIL G MALI | G7: =VLOOKUP(E7,'ESIC NAME'!B:I,8,0) -> Anil G Mali | H7: Mr. ANIL G MALI | I7: =VLOOKUP(D7,'Google attandance April -26'!C:AK,40,0) -> #REF! | J7: 101475240602 | K7: 3310877479 | L7: =VLOOKUP(D7,'Google attandance April -26'!C:E,3,0) -> FINAL | M7: =D7=J7 -> TRUE | N7: =I7=C7 -> #REF! | O7: =VLOOKUP(D7,'Google attandance April -26'!C:E,3,0) -> FINAL | P7: SBIN0004762 | Q7: 33910384216 | S7: 550 | U7: =VLOOKUP(D7,'Google attandance April -26'!C:AM,37,0) -> 84.6 | V7: =VLOOKUP(D7,'Google attandance April -26'!C:AM,34,0) -> 20.5 | W7: =VLOOKUP(D7,'FINAL TANNAGE AMO.'!C:AI,33,0) -> 21 | X7: =VLOOKUP(D7,'FINAL TANNAGE AMO.'!C:AI,32,0) -> 19519 | Y7: 84.6 | Z7: 20.5 | AA7: 21 | AB7: 19519 | AD7: =AC7*S7 -> 0 | AI7: 872 | AJ7: 200 | AK7: 95 | AM7: 10 | AN7: =AL7*AM7 -> 0 | AR7: =W7=AA7 -> TRUE | AT7: ok
A8: =D8=J8 -> TRUE | B8: KFIL/182 | C8: FOU70 | D8: 101835374035 | E8: 3315576432 | F8: =VLOOKUP(D8,'Name Details'!A:C,3,0) -> Mr. ANKUASH SANJAY BHALE | G8: =VLOOKUP(E8,'ESIC NAME'!B:I,8,0) -> ANKUSH SANJAY BHALE | H8: Mr. ANKUASH SANJAY BHALE | I8: =VLOOKUP(D8,'Google attandance April -26'!C:AK,40,0) -> #REF! | J8: 101835374035 | K8: 3315576432 | L8: =VLOOKUP(D8,'Google attandance April -26'!C:E,3,0) -> HE | M8: =D8=J8 -> TRUE | N8: =I8=C8 -> #REF! | O8: =VLOOKUP(D8,'Google attandance April -26'!C:E,3,0) -> HE | P8: BKID0000722 | Q8: 072210110009675 | S8: 550 | U8: =VLOOKUP(D8,'Google attandance April -26'!C:AM,37,0) -> 163.59 | V8: =VLOOKUP(D8,'Google attandance April -26'!C:AM,34,0) -> 21.5 | W8: =VLOOKUP(D8,'FINAL TANNAGE AMO.'!C:AI,33,0) -> 16 | X8: =VLOOKUP(D8,'FINAL TANNAGE AMO.'!C:AI,32,0) -> 12814 | Y8: 163.59 | Z8: 21.5 | AA8: 16 | AB8: 12814 | AC8: =Z8-AA8 -> 5.5 | AD8: =AC8*S8 -> 3025 | AI8: 945 | AJ8: 200 | AK8: 100 | AL8: 10 | AM8: 10 | AN8: =AL8*AM8 -> 100 | AR8: =W8=AA8 -> TRUE
A9: =D9=J9 -> TRUE | B9: KFIL/202 | C9: FOU81 | D9: 102025154331 | E9: 3315898061 | F9: =VLOOKUP(D9,'Name Details'!A:C,3,0) -> Mr. ARBAJ AMIN JAMADAR | G9: =VLOOKUP(E9,'ESIC NAME'!B:I,8,0) -> ARBAJ AMIN JAMADAR | H9: Mr. ARBAJ AMIN JAMADAR | I9: =VLOOKUP(D9,'Google attandance April -26'!C:AK,40,0) -> #REF! | J9: 102025154331 | K9: 3315898061 | L9: =VLOOKUP(D9,'Google attandance April -26'!C:E,3,0) -> REWORK | M9: =D9=J9 -> TRUE | N9: =I9=C9 -> #REF! | O9: =VLOOKUP(D9,'Google attandance April -26'!C:E,3,0) -> REWORK | P9: SBIN0017529 | Q9: 42327591910 | S9: 550 | U9: =VLOOKUP(D9,'Google attandance April -26'!C:AM,37,0) -> 378.07 | V9: =VLOOKUP(D9,'Google attandance April -26'!C:AM,34,0) -> 22 | W9: =VLOOKUP(D9,'FINAL TANNAGE AMO.'!C:AI,33,0) -> #N/A | X9: =VLOOKUP(D9,'FINAL TANNAGE AMO.'!C:AI,32,0) -> #N/A | Y9: 378.07 | Z9: 22 | AD9: =AC9*S9 -> 0 | AI9: 1017 | AJ9: 200 | AK9: 105 | AM9: 10 | AN9: =AL9*AM9 -> 0
A10: =D10=J10 -> TRUE | C10: FOU624 | D10: 102232142117 | E10: 3317899290 | F10: =VLOOKUP(D10,'Name Details'!A:C,3,0) -> Mr. AYAN ARIF USTAD | G10: =VLOOKUP(E10,'ESIC NAME'!B:I,8,0) -> AYAN ARIF USTAD | H10: Mr. AYAN ARIF USTAD | I10: =VLOOKUP(D10,'Google attandance April -26'!C:AK,40,0) -> #REF! | J10: 102232142117 | K10: 3317899290 | L10: =VLOOKUP(D10,'Google attandance April -26'!C:E,3,0) -> AVG | M10: =D10=J10 -> TRUE | N10: =I10=C10 -> #REF! | O10: =VLOOKUP(D10,'Google attandance April -26'!C:E,3,0) -> AVG | R10: 500 | S10: 550 | U10: =VLOOKUP(D10,'Google attandance April -26'!C:AM,37,0) -> 0 | V10: =VLOOKUP(D10,'Google attandance April -26'!C:AM,34,0) -> 0 | W10: =VLOOKUP(D10,'FINAL TANNAGE AMO.'!C:AI,33,0) -> #N/A | X10: =VLOOKUP(D10,'FINAL TANNAGE AMO.'!C:AI,32,0) -> #N/A | Y10: 0 | Z10: 0 | AD10: =AC10*S10 -> 0 | AI10: 0 | AJ10: 0 | AK10: 0 | AM10: 10 | AN10: =AL10*AM10 -> 0
A11: =D11=J11 -> TRUE | B11: =L11 -> HE | C11: FOU379 | D11: 102143026061 | E11: 3317026055 | F11: =VLOOKUP(D11,'Name Details'!A:C,3,0) -> Mr. RAJAKUMAR BADIGER | G11: =VLOOKUP(E11,'ESIC NAME'!B:I,8,0) -> RAJKUMAR M BADIGER | H11: Mr. RAJAKUMAR BADIGER | I11: =VLOOKUP(D11,'Google attandance April -26'!C:AK,40,0) -> #REF! | J11: 102143026061 | K11: 3317026055 | L11: =VLOOKUP(D11,'Google attandance April -26'!C:E,3,0) -> HE | M11: =D11=J11 -> TRUE | N11: =I11=C11 -> #REF! | O11: =VLOOKUP(D11,'Google attandance April -26'!C:E,3,0) -> HE | S11: 500 | U11: =VLOOKUP(D11,'Google attandance April -26'!C:AM,37,0) -> 417.62 | V11: =VLOOKUP(D11,'Google attandance April -26'!C:AM,34,0) -> 14.5 | W11: =VLOOKUP(D11,'FINAL TANNAGE AMO.'!C:AI,33,0) -> 15 | X11: =VLOOKUP(D11,'FINAL TANNAGE AMO.'!C:AI,32,0) -> 12091 | Y11: 417.62 | Z11: 14.5 | AA11: 15 | AB11: 12091 | AD11: =AC11*S11 -> 0 | AI11: 654 | AJ11: 175 | AK11: 72 | AM11: 10 | AN11: =AL11*AM11 -> 0 | AR11: =W11=AA11 -> TRUE
A12: =D12=J12 -> TRUE | B12: KFIL/86 | C12: FOU328 | D12: 101623086404 | E12: 3316938981 | F12: =VLOOKUP(D12,'Name Details'!A:C,3,0) -> Mr. BANDENAWAJ SAIPAN MULLA | G12: =VLOOKUP(E12,'ESIC NAME'!B:I,8,0) -> BANDENAWAJ SAIPAN MULLA | H12: Mr. BANDENAWAJ SAIPAN MULLA | I12: =VLOOKUP(D12,'Google attandance April -26'!C:AK,40,0) -> #REF! | J12: 101623086404 | K12: 3316938981 | L12: =VLOOKUP(D12,'Google attandance April -26'!C:E,3,0) -> AVG | M12: =D12=J12 -> TRUE | N12: =I12=C12 -> #REF! | O12: =VLOOKUP(D12,'Google attandance April -26'!C:E,3,0) -> AVG | P12: SBIN0017529 | Q12: 40653198192 | S12: 675 | U12: =VLOOKUP(D12,'Google attandance April -26'!C:AM,37,0) -> 433.21 | V12: =VLOOKUP(D12,'Google attandance April -26'!C:AM,34,0) -> 24 | W12: =VLOOKUP(D12,'FINAL TANNAGE AMO.'!C:AI,33,0) -> #N/A | X12: =VLOOKUP(D12,'FINAL TANNAGE AMO.'!C:AI,32,0) -> #N/A | Y12: 433.21 | Z12: 24 | AD12: =AC12*S12 -> 0 | AI12: 1235 | AJ12: 200 | AK12: 114 | AM12: 10 | AN12: =AL12*AM12 -> 0
A13: =D13=J13 -> TRUE | B13: KFIL/218 | C13: FOU84 | D13: 102028098436 | E13: 3315926963 | F13: =VLOOKUP(D13,'Name Details'!A:C,3,0) -> Mr. BSAVRAJ IRANNA TALWAR | G13: =VLOOKUP(E13,'ESIC NAME'!B:I,8,0) -> Bsavraj Iranna Talwar | H13: Mr. BSAVRAJ IRANNA TALWAR | I13: =VLOOKUP(D13,'Google attandance April -26'!C:AK,40,0) -> #REF! | J13: 102028098436 | K13: 3315926963 | L13: =VLOOKUP(D13,'Google attandance April -26'!C:E,3,0) -> AVG | M13: =D13=J13 -> TRUE | N13: =I13=C13 -> #REF! | O13: =VLOOKUP(D13,'Google attandance April -26'!C:E,3,0) -> AVG | P13: BKID0000743 | Q13: 074310110005705 | R13: 600 | S13: 625 | U13: =VLOOKUP(D13,'Google attandance April -26'!C:AM,37,0) -> 413.8 | V13: =VLOOKUP(D13,'Google attandance April -26'!C:AM,34,0) -> 28 | W13: =VLOOKUP(D13,'FINAL TANNAGE AMO.'!C:AI,33,0) -> #N/A | X13: =VLOOKUP(D13,'FINAL TANNAGE AMO.'!C:AI,32,0) -> #N/A | Y13: 413.8 | Z13: 28 | AD13: =AC13*S13 -> 0 | AI13: 1308 | AJ13: 200 | AK13: 119 | AM13: 10 | AN13: =AL13*AM13 -> 0
A14: =D14=J14 -> TRUE | B14: =L14 -> PAINTER | C14: FOU105 | D14: 102062761038 | E14: 3316249185 | F14: =VLOOKUP(D14,'Name Details'!A:C,3,0) -> Mr. BASAVRAJ SHIVANNA KOLI | G14: =VLOOKUP(E14,'ESIC NAME'!B:I,8,0) -> BASAVRAJ SHIVANNA KOLI | H14: Mr. BASAVRAJ SHIVANNA KOLI | I14: =VLOOKUP(D14,'Google attandance April -26'!C:AK,40,0) -> #REF! | J14: 102062761038 | K14: 3316249185 | L14: =VLOOKUP(D14,'Google attandance April -26'!C:E,3,0) -> PAINTER | M14: =D14=J14 -> TRUE | N14: =I14=C14 -> #REF! | O14: =VLOOKUP(D14,'Google attandance April -26'!C:E,3,0) -> PAINTER | P14: SBIN0012485 | Q14: 31688450898 | S14: 575 | U14: =VLOOKUP(D14,'Google attandance April -26'!C:AM,37,0) -> 357.04 | V14: =VLOOKUP(D14,'Google attandance April -26'!C:AM,34,0) -> 25 | W14: =VLOOKUP(D14,'FINAL TANNAGE AMO.'!C:AI,33,0) -> #N/A | X14: =VLOOKUP(D14,'FINAL TANNAGE AMO.'!C:AI,32,0) -> #N/A | Y14: 357.04 | Z14: 25 | AD14: =AC14*S14 -> 0 | AF14: 16573 | AI14: 1308 | AJ14: 200 | AK14: 119 | AL14: 10 | AM14: 10 | AN14: =AL14*AM14 -> 100
